Workbook

Sheet anagrafica
F5: BUSINESS MODEL
G6: PIANIFICAZIONE PER 2025-2026-2027
G10: Azienda: | H10: Bomè S.P.A.
G11: P.IVA: | H11: 00369120225
G12: Settore: | H12: Produzione di prodotti alimentari a base di carne (Ateco C10.13)
D31: LABORATORIO DI PIANIFICAZIONE FINANZIARIA
D32: Docente: | E32: Laura Maran | G32: A.A: | H32: 2025-26
D34: Studente: | E34: Box Alif Mahajan Fuhad

Sheet calcs →

Sheet REVENUE MODEL
B2: Tabella 1: Prezzi di vendita e volumi ipotetici per 2024 su base del bilancio consuntivo | F2: expand for details ↓ | H2: Tabella 2A: Prospettive di crescita dei ricavi e volumi per mix prodotti | L2: expand for details ↓ | Q2: Tabella 1: Prezzi di vendita e volumi ipotetici per 2024 su base del bilancio consuntivo | U2: expand for details ↓
F3: + | L3: + | V3: +
B4: Spiegazione: | C4: Partito dal fatturato per il 2024 come base dei ricavi. Ottenuti i ricavi di linea moltiplicando il fatturato totale per il valore percentuale di categoria. Coeficiente ottenuto sulla base dei fatturati nazionali per rispettive categorie da ASSICA. Maggiori dettagli su B. linea prodotti Bomè. Si è calcolato il prezzo medio di vendita sulla base di prodotti del simile livello, inteso come qualità , produttore e zona geografica e dati pubblicamente disponibili. Visibile su sheet - B. calcolo prezzi medi di vend | H4: Spiegazione: | I4: Dato il fatturato del 2024. Si proietta la crescita negli anni 2025-26-27 utilizzando il tasso di crescita annuale dei ricavi. In assenza di dati previsionali tale tasso è stato individuato effettuando una regressione lineare sulla base dei precedenti 5 anni. I Fatturati previsti annuali sono stati divisi per le rispettive categorie di prodotto usando lo stesso coeficiente individuato nel 2024, ipotizzando stablità dei coeficienti e crescita proporzionata per ciascuna linea di prodotto. Il calcolo dei prezzi di vendita è stato più avanzato, basato su tassi inflazionistici e dati previsionali sulla crescita dei prezzi degli ingredienti, visibile con maggiore dettaglio su B. calcolo prezzi medi di vend. | Q4: Spiegazione:
B5: input: | C5: Fatturato totale del 2024; coefficienti qta per cat. Prodotto; Prezzi medi per categorie; | H5: input: | I5: tasso di crescita annuale; Fatturato 2024; Prezzi medi per categrie di prodotto; coeficienti fattoriali per categorie di prodotto; | Q5: input: | R5: Fatturato 2024; coeficienti fattoriali per categorie di prodotto; Prezzi medi per categorie di prodotto 2024;
B6: output: | C6: Quantità venduta per categorie di prodotto | H6: output: | I6: Ricavi totali per 25-26-27; Ricavi per linee; Quantità di kg venduto per categorie di prodotto; | Q6: output: | R6: Ricavi per linee di prodotto; Quantità di kg venduto per categorie di prodotto 2024.;
B8: MIX PRODOTTI | D8: anno | H8: MIX PRODOTTI | J8: anno | Q8: MIX PRODOTTI | S8: anno
D9: 2024 | J9: 2025 | K9: 2026 | L9: 2027 | S9: 2024
B10: Linea Carne Salada | H10: Linea A - Carne Salada | Q10: Linea Carne Salada
C11: prezzo di vendita [€/kg] | D11: 36.08 | I11: prezzo di vendita [€/kg] | J11: ='B. linea prodotti Bomè'!J121 -> 37.243472 | K11: ='B. linea prodotti Bomè'!K121 -> 38.708555 | L11: ='B. linea prodotti Bomè'!L121 -> 39.996002 | R11: prezzo di vendita [€/kg] | S11: 36.08
C12: quantità [kg] | D12: =D13/D11 -> 44339.106 | I12: quantità [kg] | J12: =J13/J11 -> 44874.012 | K12: =K13/K11 -> 45105.519 | L12: =L13/L11 -> 45604.916 | R12: quantità [kg] | S12: =S13/S11 -> 44339.106
B13: Totale ricavi Linea A | D13: =D34*0.074534161 -> 1599754.9 | H13: Totale ricavi Linea A | J13: =0.074534161*J$34 -> 1671264 | K13: =0.074534161*K$34 -> 1745969.5 | L13: =0.074534161*L$34 -> 1824014.3 | Q13: Totale ricavi Linea A | S13: =S34*0.074534161 -> 1599754.9
B15: Linea Speck | H15: Linea B - Speck | Q15: Linea Speck
C16: prezzo di vendita [€/kg] | D16: 35 | I16: prezzo di vendita [€/kg] | J16: ='B. linea prodotti Bomè'!J125 -> 35.679266 | K16: ='B. linea prodotti Bomè'!K125 -> 36.62157 | L16: ='B. linea prodotti Bomè'!L125 -> 37.368943 | R16: prezzo di vendita [€/kg] | S16: 35
C17: quantità [kg] | D17: =D18/D16 -> 55229.636 | I17: quantità [kg] | J17: =J18/J16 -> 56599.931 | K17: =K18/K16 -> 57608.485 | L17: =L18/L16 -> 58979.922 | R17: quantità [kg] | S17: =S18/S16 -> 55229.636
B18: Totale ricavi Linea B | D18: =0.090062112*D34 -> 1933037.2 | H18: Totale ricavi Linea B | J18: =0.090062112*J$34 -> 2019444 | K18: =0.090062112*K$34 -> 2109713.2 | L18: =0.090062112*L$34 -> 2204017.3 | Q18: Totale ricavi Linea B | S18: =0.090062112*S34 -> 1933037.2
B20: Linea Grasso e Lardo | H20: Linea C - Grasso e Lardo | Q20: Linea Grasso e Lardo
C21: prezzo di vendita [€/kg] | D21: 35.88 | I21: prezzo di vendita [€/kg] | J21: ='B. linea prodotti Bomè'!J122 -> 36.66848 | K21: ='B. linea prodotti Bomè'!K122 -> 37.731717 | L21: ='B. linea prodotti Bomè'!L122 -> 38.598731 | R21: prezzo di vendita [€/kg] | S21: 35.88
C22: quantità [kg] | D22: =D23/D21 -> 70594.909 | I22: quantità [kg] | J22: =J23/J21 -> 72164.649 | K22: =K23/K21 -> 73265.994 | L22: =L23/L21 -> 74821.701 | R22: quantità [kg] | S22: =S23/S21 -> 70594.909
B23: Totale ricavi Linea C | D23: =0.118012422*D34 -> 2532945.3 | H23: Totale ricavi Linea C | J23: =0.118012422*J$34 -> 2646168 | K23: =0.118012422*K$34 -> 2764451.7 | L23: =0.118012422*L$34 -> 2888022.7 | Q23: Totale ricavi Linea C | S23: =0.118012422*S34 -> 2532945.3
B25: Linea Salumi cotti | H25: Linea D - Salumi cotti | Q25: Linea Salumi cotti
C26: prezzo di vendita [€/kg] | D26: 28.83 | I26: prezzo di vendita [€/kg] | J26: ='B. linea prodotti Bomè'!J124 -> 29.540523 | K26: ='B. linea prodotti Bomè'!K124 -> 30.476486 | L26: ='B. linea prodotti Bomè'!L124 -> 31.258232 | R26: prezzo di vendita [€/kg] | S26: 28.83
C27: quantità [kg] | D27: =D28/D26 -> 358368.05 | I27: quantità [kg] | J27: =J28/J26 -> 365382.16 | K27: =K28/K26 -> 369991.9 | L27: =L28/L26 -> 376863.69 | R27: quantità [kg] | S27: =S28/S26 -> 358368.05
B28: Totale ricavi Linea D | D28: =0.48136646*D34 -> 10331751 | H28: Totale ricavi Linea D | J28: =0.48136646*J$34 -> 10793580 | K28: =0.48136646*K$34 -> 11276053 | L28: =0.48136646*L$34 -> 11780093 | Q28: Totale ricavi Linea D | S28: =0.48136646*S34 -> 10331751
B30: Linea Prosciutto alternativo | H30: Linea E - Prosciutto alternativo | Q30: Linea Prosciutto alternativo
C31: prezzo di vendita [€/kg] | D31: 34.47 | I31: prezzo di vendita [€/kg] | J31: ='B. linea prodotti Bomè'!I123 -> 34.47 | K31: ='B. linea prodotti Bomè'!J123 -> 35.593848 | L31: ='B. linea prodotti Bomè'!K123 -> 37.00682 | R31: prezzo di vendita [€/kg] | S31: 34.47
C32: quantità [kg] | D32: =D33/D31 -> 146965.21 | I32: quantità [kg] | J32: =J33/J31 -> 153534.55 | K32: =K33/K31 -> 155333.12 | L32: =L33/L31 -> 156080.56 | R32: quantità [kg] | S32: =S33/S31 -> 146965.21
B33: Totale ricavi Linea E | D33: =0.236024845*D34 -> 5065890.7 | H33: Totale ricavi Linea E | J33: =0.236024845*J$34 -> 5292336 | K33: =0.236024845*K$34 -> 5528903.4 | L33: =0.236024845*L$34 -> 5776045.4 | Q33: Totale ricavi Linea E | S33: =0.236024845*S34 -> 5065890.7
B34: TOTALE RICAVI | D34: 21463379 | H34: TOTALE RICAVI | J34: =S34*(1+M37) -> 22422792 | K34: =J34*(1+M37) -> 23425091 | L34: =K34*(1+M37) -> 24472192 | Q34: TOTALE RICAVI | S34: 21463379
L37: Tasso di crescita annuale dei ricavi previsto: | M37: 0.0447
H39: Ottenuto tramite simple linear regression dei fatturati nazionali dal 2020-2024; Maggiori dettagli su B. linea prodotti Bomè;
H40: Si utilizza questo valore considerandolo più conservativo rispetto al tasso di crescita previsto di +5,7%; presentato a pagina 93 del documento "Assica: Rapporto annuale 2024"
H45: Tabella 2B: Prospettive di crescita dei volumi con valori percentuale rispetto al totale del prodotto | L45: expand for details ↓
L46: +
H47: Spiegazione: | I47: Calcolato le percentuali di volume da produrre rispetto al totale per ciascuna categoria di prodotto per ciascun anno.
H48: input: | I48: Quantità di volume venduto per prodotto 25-26-27;
H49: output: | I49: Percentuale di volume per linea rispetto al totale 25-26-27;
H51: MIX PRODOTTI | J51: anno
J52: 2025 | K52: 2026 | L52: 2027
H54: Linea A - Carne Salada | J54: =J55/J$68 -> 0.064794842 | K54: =K55/K$68 -> 0.06431655 | L54: =L55/L$68 -> 0.064020307
I55: quantità [kg] | J55: =J12 -> 44874.012 | K55: =K12 -> 45105.519 | L55: =L12 -> 45604.916
H57: Linea B - Speck | J57: =J58/J$68 -> 0.081726226 | K57: =K58/K$68 -> 0.082144692 | L57: =L58/L$68 -> 0.082796177
I58: quantità [kg] | J58: =J17 -> 56599.931 | K58: =K17 -> 57608.485 | L58: =L17 -> 58979.922
H60: Linea C - Grasso e Lardo | J60: =J61/J$68 -> 0.10420056 | K60: =K61/K$68 -> 0.10447094 | L60: =L61/L$68 -> 0.10503491
I61: quantità [kg] | J61: =J22 -> 72164.649 | K61: =K22 -> 73265.994 | L61: =L22 -> 74821.701
H63: Linea D - Salumi cotti | J63: =J64/J$68 -> 0.52758553 | K63: =K64/K$68 -> 0.52757629 | L63: =L64/L$68 -> 0.52904228
I64: quantità [kg] | J64: =J27 -> 365382.16 | K64: =K27 -> 369991.9 | L64: =L27 -> 376863.69
H66: Linea E - Prosciutto alternativo | J66: =J67/J$68 -> 0.22169284 | K66: =K67/K$68 -> 0.22149153 | L66: =L67/L$68 -> 0.21910633
I67: quantità [kg] | J67: =J32 -> 153534.55 | K67: =K32 -> 155333.12 | L67: =L32 -> 156080.56
H68: TOTALE QUANTITA | J68: =J55+J58+J61+J64+J67 -> 692555.3 | K68: =K55+K58+K61+K64+K67 -> 701305.02 | L68: =L55+L58+L61+L64+L67 -> 712350.79

Sheet COSTI DI GESTIONE & BEP
B2: Tabella 3: Costi di gestione dettagliati per 2024-25-26-27 | E2: expand for details ↓ | H2: expand for details → | M2: Tabella 4: Punto di pareggio per fatturato, volume, margine di sicurezza e indice di flessibilità | P2: expand for details ↓
E3: + | J3: + | P3: +
B4: Spiegazione: | C4: Individuate varie voci di costi rispetto al bilancio consuntivo del 2024. Ciascuna voce ha avuto progressione di crescita/diminuzione o stabilità rispetto ai fattori presi in considerazione, visibile espandendo il banner laterale alla destra della tabella. | M4: Spiegazione: | N4: Individuazione del punto di pareggio rispetto al fatturato e rispetto al volume. Considerate le parti di costo variabile, differenziandolo dal ricavo si ottiene il margine di contribuzione. Mc/Ricavi da margine di contribuzione unitario. BEP è CF/MdC%.
B5: input: | C5: variabili varie; | M5: input: | N5: ricavi, costi variabili, costi totali
B6: output: | C6: costi di gestione; | M6: output: | N6: margine di contribuzione; costi fissi; BEP; indici di flessibilità; MdS;
B8: COSTI DI GESTIONE | C8: tipo | D8: 2024 | E8: 2025 | F8: 2026 | G8: 2027 | J8: dettagli | M8: PUNTO DI PAREGGIO DEL FATTURATO | N8: 2025 | O8: 2026 | P8: 2027
B9: Acquisto materie prime | C9: var. | D9: 14699595 | E9: =D9+3.52%*D9 -> 15217021 | F9: =E9+3.52%*E9 -> 15752660 | G9: =F9+3.52%*F9 -> 16307154 | J9: Spese di acquisto per materie prime, crescita prevista del 3,5% annuale, rispettando le proiezioni di ASSICA | M9: Ricavi | N9: ='REVENUE MODEL'!J34 -> 22422792 | O9: ='REVENUE MODEL'!K34 -> 23425091 | P9: ='REVENUE MODEL'!L34 -> 24472192
B10: var. rimanenze | C10: var. | D10: =-CCN!C8 -> 431532 | J10: var rimanenze ignote e molto variabili, non considerate. Si valutano le rimanenze medie in CCNO | M10: Totale costi variabili | N10: =E9+E23+E26+E33+E34+E35 -> 16975741 | O10: =F9+F23+F26+F33+F34+F35 -> 17627516 | P10: =G9+G23+G26+G33+G34+G35 -> 18269795
B11: Costo del venduto | D11: =SUM(D9:D10) -> 15131127 | E11: =SUM(E9:E9) -> 15217021 | F11: =SUM(F9:F9) -> 15752660 | G11: =SUM(G9:G9) -> 16307154
M12: Margine di contribuzione | N12: =N9-N10 -> 5447051.4 | O12: =O9-O10 -> 5797575.3 | P12: =P9-P10 -> 6202397.1
B13: Salari e stipendi | C13: fisso | D13: =HR!E20 -> 1114481 | E13: =HR!F20 -> 1194598.9 | F13: =HR!G20 -> 1224812.2 | G13: =HR!H20 -> 1277755.8 | J13: Spese per salari visibile in modo dettagliato sullo sheet - HR; dettagliato sulla base di numeri di dipendenti, tipo di profilo lavorativo. | M13: Margine di contribuzione in % | N13: =N12/N9 -> 0.24292476 | O13: =O12/O9 -> 0.24749425 | P13: =P12/P9 -> 0.25344673
B14: Oneri sociali | C14: fisso | D14: =HR!O7 -> 304319 | E14: =HR!P7 -> 330903.91 | F14: =HR!Q7 -> 339272.97 | G14: =HR!R7 -> 353938.35 | J14: visibile in modo dettagliato sullo sheet - HR;
B15: TFR | C15: fisso | D15: =34063+HR!H70+HR!H71 -> 79658 | E15: =HR!P8 -> 78592.036 | F15: =HR!Q8 -> 80579.747 | G15: =HR!R8 -> 84062.88 | J15: visibile in modo dettagliato sullo sheet - HR; | M15: Costi fissi | N15: =E14+E21+E27+E28+E29+E37+E41+E43+E45+E50+E30+E31+E32+E44 -> 939333.91 | O15: =F14+F21+F27+F28+F29+F37+F41+F43+F45+F50+F30+F31+F32+F44 -> 958405.07 | P15: =G14+G21+G27+G28+G29+G37+G41+G43+G45+G50+G30+G31+G32+G44 -> 984200.75
B16: Costi del personale | D16: =SUM(D13:D15) -> 1498458 | E16: =SUM(E13:E15) -> 1604094.9 | F16: =SUM(F13:F15) -> 1644664.9 | G16: =SUM(G13:G15) -> 1715757 | J16: Totale sommando le voci inerenti precedenti. | M16: Costi di manodopera (compreso TFR) | N16: =E13+E15 -> 1273191 | O16: =F13+F15 -> 1305391.9 | P16: =G13+G15 -> 1361818.7
M17: Costi di sviluppo | N17: =E24+E25 -> 332790.4 | O17: =F24+F25 -> 343625.52 | P17: =G24+G25 -> 357338.6
B18: Amministratori (5) | C18: fisso | D18: =HR!E29+HR!E30 -> 170000 | E18: =HR!F29+HR!F30 -> 172000 | F18: =HR!G29+HR!G30 -> 174000 | G18: =HR!H29+HR!H30 -> 176000 | J18: visibile in modo dettagliato sullo sheet - HR; | M18: Ammortamenti | N18: =incidenze!D16+incidenze!D18 -> 799296.26 | O18: =incidenze!E16+incidenze!E18 -> 749688.49 | P18: =incidenze!F16+incidenze!F18 -> 730241.24
B19: Sindaci (5) | C19: fisso | D19: =HR!E31+HR!E32 -> 122000 | E19: =HR!F31+HR!F32 -> 122000 | F19: =HR!G31+HR!G32 -> 122000 | G19: =HR!H31+HR!H32 -> 122000 | J19: visibile in modo dettagliato sullo sheet - HR; | M19: Totale costi fissi | N19: =SUM(N15:N18) -> 3344611.6 | O19: =SUM(O15:O18) -> 3357111 | P19: =SUM(P15:P18) -> 3433599.3
B20: Spese per collaboratori | C20: fisso | D20: =HR!E27 -> 54900 | E20: =HR!F27 -> 56600 | F20: =HR!G27 -> 56600 | G20: =HR!H27 -> 56600 | J20: visibile in modo dettagliato sullo sheet - HR;
B21: Servizi: amministratori-consulenti-servizi tecnici | D21: =SUM(D18:D20) -> 346900 | E21: =SUM(E18:E20) -> 350600 | F21: =SUM(F18:F20) -> 352600 | G21: =SUM(G18:G20) -> 354600 | J21: Totale sommando le voci inerenti precedenti. | M21: BEP Fatturato (CF/MDC%) | N21: =N19/N13 -> 13768096 | O21: =O19/O13 -> 13564400 | P21: =P19/P13 -> 13547617
B23: provvigioni ed oneri concessi | C23: var. | D23: =0.3*0.1*D9 -> 440987.85 | E23: =0.3*0.1*E9 -> 456510.62 | F23: =0.3*0.1*F9 -> 472579.8 | G23: =0.3*0.1*G9 -> 489214.61 | J23: Provvigioni concesse ipotizzando che il 30% del sales sia di generazione da parte di salespeople, il compenso è pari al 10% del lead generato per l'intermediazione.
B24: diritti d'autore, R&D, royalties, brevetti,costi di licenze export, certificazioni | C24: fisso | D24: 285349.92 | E24: 285349.92 | F24: 285349.92 | G24: 285349.92 | J24: Spese/budget costante per questa voce.
B25: mostre, fiere, viaggi | C25: fisso | D25: =2354.6+122+4842+14442+20000 -> 41760.6 | E25: =20000+27440.48 -> 47440.48 | F25: =38275.6+20000 -> 58275.6 | G25: =51988.68+20000 -> 71988.68 | J25: Si procede con un crescente investimento nel processo di marketing del proprio marchio, questo viene effettuato intensificando la propria presenza nei expo/fiere di settore a livello nazionale e internazionale. Dettagli in fondo pagina | M25: INDICE DI FLESSIBILITA | N25: 2025 | O25: 2026 | P25: 2027
B26: spese doganali import-export-trasporti | C26: var. | D26: =0.05*D9 -> 734979.75 | E26: =0.05*E9 -> 760851.04 | F26: =0.05*F9 -> 787632.99 | G26: =0.05*G9 -> 815357.68 | J26: Ipotizzate spese doganali pari al 5% del fatturato. Non include VAT. Include spese doganali, trasporti e relativa gestione. Impossibile quantificare, dipende da: prodotto x paese di export/import x spese di trasporto x assicurazioni | M26: Indice di flessibilità (CV tot/CF tot) | N26: =N10/N19 -> 5.0755492 | O26: =O10/O19 -> 5.2507992 | P26: =P10/P19 -> 5.3208875
B27: spese per consulenza commerciale | C27: fisso | D27: =300*12 -> 3600 | E27: =300*12 -> 3600 | F27: =300*12 -> 3600 | G27: =300*12 -> 3600 | J27: Consulenza commerciale per 300 mensili IVA esclusa. Costo tipico di consulenza. | M27: %CV su CT | N27: =N10/(N10+N19) -> 0.83540583 | O27: =O10/(O10+O19) -> 0.84002046 | P27: =P10/(P10+P19) -> 0.84179437
B28: spese per consulenza tributaria/legale | C28: fisso | D28: =3000*1.5 -> 4500 | E28: =3000*1.5 -> 4500 | F28: =3000*1.5 -> 4500 | G28: =3000*1.5 -> 4500 | J28: Spese annuali ricorrenti per servizio di un studio legale. | M28: %CF su CT | N28: =N19/(N19+N10) -> 0.16459417 | O28: =O19/(O19+O10) -> 0.15997954 | P28: =P19/(P19+P10) -> 0.15820563
B29: spese di auditing | C29: fisso | D29: 10000 | E29: 10000 | F29: 10000 | G29: 10000 | J29: Spesa di auditing tecnico/sanitario/amministrativo.
B30: spese per servizi di laboratorio avanzato | C30: fisso | D30: 4000 | E30: =D30 -> 4000 | F30: =E30 -> 4000 | G30: =F30 -> 4000 | J30: Spese di ricerca relative all'analisi dei prodotti alimentari, servizio outsourced a terzi.
B31: spese abbonamenti software professionali e gestionali | C31: fisso | D31: 8000 | E31: 8000 | F31: 8000 | G31: 8000 | J31: Spese ipotetiche di gestionale custom, SaaS.
B32: spese servizi di manutenzione | C32: fisso | D32: 30000 | E32: 30000 | F32: =E32 -> 30000 | G32: =F32 -> 30000 | J32: Spese di manutenzione ipotetiche relative a macchinari, strumenti, auto.
B33: spese gestione rifiuti | C33: var. | D33: =0.25*85*('REVENUE MODEL'!S12+'REVENUE MODEL'!S17+'REVENUE MODEL'!S22+'REVENUE MODEL'!S27+'REVENUE MODEL'!S32)/1000 -> 14354.309 | E33: =0.25*85*('REVENUE MODEL'!J12+'REVENUE MODEL'!J17+'REVENUE MODEL'!J22+'REVENUE MODEL'!J27+'REVENUE MODEL'!J32)/1000 -> 14716.8 | F33: =0.25*85*('REVENUE MODEL'!K12+'REVENUE MODEL'!K17+'REVENUE MODEL'!K22+'REVENUE MODEL'!K27+'REVENUE MODEL'!K32)/1000 -> 14902.732 | G33: =0.25*85*('REVENUE MODEL'!L12+'REVENUE MODEL'!L17+'REVENUE MODEL'!L22+'REVENUE MODEL'!L27+'REVENUE MODEL'!L32)/1000 -> 15137.454 | J33: Spese di gestione rifiuti, calcolato tramite 85 euro * tonnelata *25% di scarto rispetto a materie prime acquistate.(ossa, grassi, membrane etc.) | M33: PUNTO DI PAREGGIO OPERATIVO IN VOLUME | N33: 2025 | O33: 2026 | P33: 2027
B34: spese gestione idrica | C34: var. | D34: =0.02*6000*1*0.16*0.001*('REVENUE MODEL'!S12+'REVENUE MODEL'!S17+'REVENUE MODEL'!S22+'REVENUE MODEL'!S27+'REVENUE MODEL'!S32) -> 12969.541 | E34: =0.02*6000*1*0.16*0.001*('REVENUE MODEL'!J12+'REVENUE MODEL'!J17+'REVENUE MODEL'!J22+'REVENUE MODEL'!J27+'REVENUE MODEL'!J32) -> 13297.062 | F34: =0.02*6000*1*0.16*0.001*('REVENUE MODEL'!K12+'REVENUE MODEL'!K17+'REVENUE MODEL'!K22+'REVENUE MODEL'!K27+'REVENUE MODEL'!K32) -> 13465.056 | G34: =0.02*6000*1*0.16*0.001*('REVENUE MODEL'!L12+'REVENUE MODEL'!L17+'REVENUE MODEL'!L22+'REVENUE MODEL'!L27+'REVENUE MODEL'!L32) -> 13677.135 | J34: Spese di gestione idrica, 0,16 euro k-litro consumo di 6 litri per chilo di prodotto in output. | M34: Quantità in kg | N34: ='REVENUE MODEL'!J12+'REVENUE MODEL'!J17+'REVENUE MODEL'!J22+'REVENUE MODEL'!J27+'REVENUE MODEL'!J32 -> 692555.3 | O34: ='REVENUE MODEL'!K12+'REVENUE MODEL'!K17+'REVENUE MODEL'!K22+'REVENUE MODEL'!K27+'REVENUE MODEL'!K32 -> 701305.02 | P34: ='REVENUE MODEL'!L12+'REVENUE MODEL'!L17+'REVENUE MODEL'!L22+'REVENUE MODEL'!L27+'REVENUE MODEL'!L32 -> 712350.79
B35: spese gestione elettrica | C35: var. | D35: =2.36862669519772E-06*0.262937559*('REVENUE MODEL'!S12+'REVENUE MODEL'!S17+'REVENUE MODEL'!S22+'REVENUE MODEL'!S27+'REVENUE MODEL'!S32)*1000000 -> 420700.09 | E35: =1000000*2.36862669519772E-06*0.312937559*('REVENUE MODEL'!J12+'REVENUE MODEL'!J17+'REVENUE MODEL'!J22+'REVENUE MODEL'!J27+'REVENUE MODEL'!J32) -> 513344.33 | F35: =1000000*2.36862669519772E-06*0.352937559*('REVENUE MODEL'!K12+'REVENUE MODEL'!K17+'REVENUE MODEL'!K22+'REVENUE MODEL'!K27+'REVENUE MODEL'!K32) -> 586275.1 | G35: =1000000*2.36862669519772E-06*0.372937559*('REVENUE MODEL'!L12+'REVENUE MODEL'!L17+'REVENUE MODEL'!L22+'REVENUE MODEL'!L27+'REVENUE MODEL'!L32) -> 629254.97 | J35: Spese di gestione elettrica, 1,6 GW/h a 0,26 kW/h euro. Sulla base di dimensione del punto produttivo e consumo medio per tipo di impresa. Prezzo medio per val di Ledro. | M35: Ricavo unitario ponderato | N35: ='REVENUE MODEL'!J11*('REVENUE MODEL'!J13/'REVENUE MODEL'!J34)+'REVENUE MODEL'!J16*('REVENUE MODEL'!J18/'REVENUE MODEL'!J34)+'REVENUE MODEL'!J21*('REVENUE MODEL'!J23/'REVENUE MODEL'!J34)+'REVENUE MODEL'!J26*('REVENUE MODEL'!J28/'REVENUE MODEL'!J34)+'REVENUE MODEL'!J31*('REVENUE MODEL'!J33/'REVENUE MODEL'!J34) -> 32.67219 | O35: ='REVENUE MODEL'!K11*('REVENUE MODEL'!K13/'REVENUE MODEL'!K34)+'REVENUE MODEL'!K16*('REVENUE MODEL'!K18/'REVENUE MODEL'!K34)+'REVENUE MODEL'!K21*('REVENUE MODEL'!K23/'REVENUE MODEL'!K34)+'REVENUE MODEL'!K26*('REVENUE MODEL'!K28/'REVENUE MODEL'!K34)+'REVENUE MODEL'!K31*('REVENUE MODEL'!K33/'REVENUE MODEL'!K34) -> 33.707527 | P35: ='REVENUE MODEL'!L11*('REVENUE MODEL'!L13/'REVENUE MODEL'!L34)+'REVENUE MODEL'!L16*('REVENUE MODEL'!L18/'REVENUE MODEL'!L34)+'REVENUE MODEL'!L21*('REVENUE MODEL'!L23/'REVENUE MODEL'!L34)+'REVENUE MODEL'!L26*('REVENUE MODEL'!L28/'REVENUE MODEL'!L34)+'REVENUE MODEL'!L31*('REVENUE MODEL'!L33/'REVENUE MODEL'!L34) -> 34.682918
B36: spese per servizi: altro | C36: fisso | D36: 44123.94 | J36: Altra spesa | M36: Costo variabile unitario | N36: =N10/('REVENUE MODEL'!J12+'REVENUE MODEL'!J17+'REVENUE MODEL'!J22+'REVENUE MODEL'!J27+'REVENUE MODEL'!J32) -> 24.511747 | O36: =O10/('REVENUE MODEL'!K12+'REVENUE MODEL'!K17+'REVENUE MODEL'!K22+'REVENUE MODEL'!K27+'REVENUE MODEL'!K32) -> 25.135305 | P36: =P10/('REVENUE MODEL'!L12+'REVENUE MODEL'!L17+'REVENUE MODEL'!L22+'REVENUE MODEL'!L27+'REVENUE MODEL'!L32) -> 25.647189
B37: spese di pulizia | C37: fisso | D37: 20000 | E37: =D37 -> 20000 | F37: =E37 -> 20000 | G37: =F37 -> 20000 | J37: Spese di pulizia annuali outsourced. Prezzo alto perché pulizia frequente, professionale e inclusa sanitarizzazione | M37: Margine di contribuzione unitario | N37: =N35-N36 -> 8.1604431 | O37: =O35-O36 -> 8.5722225 | P37: =P35-P36 -> 9.0357287
B38: Servizi: costi servizi commerciali | D38: =SUM(D23:D37) -> 2075326 | E38: =SUM(E23:E37) -> 2171610.3 | F38: =SUM(F23:F37) -> 2298581.2 | G38: =SUM(G23:G37) -> 2400080.4
B39: Servizi totali | D39: =D21+D38 -> 2422226 | E39: =E38+E21 -> 2522210.3 | F39: =F38+F21 -> 2651181.2 | G39: =G38+G21 -> 2754680.4 | M39: BEP in volume (kg) (CF/MDCu) | N39: =N19/N37 -> 409856.61 | O39: =O19/O37 -> 391626.67 | P39: =P19/P37 -> 380002.47
B41: Godimento di beni terzi | C41: fisso | D41: 117380 | E41: =D41*1.05 -> 123249 | F41: =E41*1.05 -> 129411.45 | G41: =F41*1.05 -> 135882.02
B43: budget cancelleria varia, inchiostro stampanti, fogli | C43: fisso | D43: =50*12 -> 600 | E43: =D43 -> 600 | F43: =E43 -> 600 | G43: =F43 -> 600 | J43: Budget di cancelleria annuale, 3 uffici per tot 600 euro. | M43: MARGINE DI SICUREZZA | N43: 2025 | O43: 2026 | P43: 2027
B44: altri costi, includendo imposte non sul reddito | C44: fisso | D44: =52056-(D43+D45) -> 27886 | E44: =D44*1.0447 -> 29132.504 | F44: =1.0447*E44 -> 30434.727 | G44: =1.0447*F44 -> 31795.159 | J44: Spese di imposte extra-reddito e altre spese | M44: MDS assoluto
B45: assicurazioni | C45: fisso | D45: =6000+6000+(119*30)+8000 -> 23570 | E45: =D45*1.05 -> 24748.5 | F45: =E45*1.05 -> 25985.925 | G45: =F45*1.05 -> 27285.221 | J45: Spesa di assicurazione calcolata con dettagli, crescente al 5% annuale. | M45: +Ricavi effettivi | N45: ='REVENUE MODEL'!J34 -> 22422792 | O45: ='REVENUE MODEL'!K34 -> 23425091 | P45: ='REVENUE MODEL'!L34 -> 24472192
B46: Oneri diversi di gestione | C46: fisso | D46: =SUM(D43:D45) -> 52056 | E46: =SUM(E43:E45) -> 54481.004 | F46: =SUM(F43:F45) -> 57020.652 | G46: =SUM(G43:G45) -> 59680.381 | M46: -Fatturato di pareggio (EBIT) | N46: =N21 -> 13768096 | O46: =O21 -> 13564400 | P46: =P21 -> 13547617
M47: Margine di sicurezza | N47: =N45-N46 -> 8654695.7 | O47: =O45-O46 -> 9860690.9 | P47: =P45-P46 -> 10924575
B48: accantonamenti per rischi | C48: fisso | D48: 0 | E48: =D48 -> 0 | F48: =E48 -> 0 | G48: =F48 -> 0 | J48: no accantonamenti
B49: altri accantonamenti | C49: fisso | D49: 0 | E49: =D49 -> 0 | F49: =E49 -> 0 | G49: =F49 -> 0 | J49: no accantonamenti | M49: MDS Relativo
B50: Accantonamenti per rischi e oneri | C50: fisso | D50: =SUM(D48:D49) -> 0 | E50: =SUM(E48:E49) -> 0 | F50: =SUM(F48:F49) -> 0 | G50: =SUM(G48:G49) -> 0 | J50: no accantonamenti | M50: Margine di sicurezza | N50: =N47 -> 8654695.7 | O50: =O47 -> 9860690.9 | P50: =P47 -> 10924575
M51: Ricavi | N51: =N45 -> 22422792 | O51: =O45 -> 23425091 | P51: =P45 -> 24472192
B52: TOTALE COSTI DI GESTIONE | D52: =D50+D46+D41+D39+D16+D11 -> 19221247 | E52: =E50+E46+E41+E39+E16+E11 -> 19521056 | F52: =F50+F46+F41+F39+F16+F11 -> 20234938 | G52: =G50+G46+G41+G39+G16+G11 -> 20973153 | J52: Totale | M52: MDS% | N52: =N50/N51 -> 0.38597761 | O52: =O50/O51 -> 0.42094569 | P52: =P50/P51 -> 0.4464077
B56: calcolo rimanenze x SP | D56: 2024 | E56: 2025 | F56: 2026 | G56: 2027
B57: var rim | D57: =D10 -> 431532 | E57: =E58*360/ANALISI!D24 -> 446721.93 | F57: =F58*360/ANALISI!E24 -> 462446.54 | G57: =G58*360/ANALISI!F24 -> 478724.66
B58: scorte magazzino | D58: =D10/360*ANALISI!C24 -> 133266.59 | E58: =E59*E60 -> 137957.57 | F58: =F59*F60 -> 142813.68 | G58: =G59*G60 -> 147840.72
B59: acq materie prime | D59: =D9 -> 14699595 | E59: =E9 -> 15217021 | F59: =F9 -> 15752660 | G59: =G9 -> 16307154
B60: rapporto scorte/Mp acquisite | D60: =D58/D59 -> 0.009066004 | E60: =D60 -> 0.009066004 | F60: =E60 -> 0.009066004 | G60: =F60 -> 0.009066004
B63: Tabella 3A: Pianificazione eventi e fiere per promuovere il marchio | G63: expand for details ↓
G64: +
B65: Spiegazione: | C65: Si utilizzano le piattaforme di esposizione e fiere per promuovere il marchio; Inizialmente presentandosi in fiere nazionali ed europee famose, successivamente anche in eventi internazionali. I costi sono calcolati per stand standard e prezzi esposti.
B67: Intensificazione marketing del marchio commerciale in fiere e mostre buyer internazionali e gdo
B68: Anno; Eventi; Costi relativi;
B69: 2024:Marca at BolognaFiere | C69: Festa del Pane | D69: Cibus 24 | E69: New york authorization
B70: =1930*1.22 -> 2354.6 | C70: =100*1.22 -> 122 | D70: =(200*18*1.22)+450 -> 4842 | E70: =(4500+21+2500+200)*2 -> 14442
B72: 2025: Marca at BolognaFiere | C72: Cibus25 | D72: Pitti TASTE | E72: Identità milano | F72: iMeat | G72: Distinti salumi
B73: =B70 -> 2354.6 | C73: 4842 | D73: 5000 | E73: 2000 | F73: =2450*1.22 -> 2989 | G73: =6800*1.03*1.22+1100+500*1.22 -> 10254.88 | H73: =5000*1.22+80*1.22 -> 6197.6
B75: 2026: Marca at BolognaFiere | C75: Cibus TEC | D75: Tuttofood | E75: iMeat | F75: Formaticum&Salumi | G75: Gulfood(Dubai), Anuga(DE)
B76: =B73 -> 2354.6 | C76: 4842 | D76: =4500*1.22 -> 5490 | E76: 2989 | F76: 4000 | G76: =15000*1.22+300 -> 18600 | H76: =8040*1.22+940+250+1120+690*3 -> 14188.8
B78: 2027: Marca at BolognaFiere | C78: Sigep World | D78: Taste | E78: Distinti salumi | F78: Cibus | G78: SIAL paris(FR), ANUGA(DE)
B79: =B76 -> 2354.6 | C79: 4842 | D79: =290*18*1.22+3000 -> 9368.4 | E79: 10254.88 | F79: =375*20*1.22*1.2 -> 10980 | G79: 14188.8

Sheet HR
B2: Tabella 5: Costi per risorse umane interne ed esterne all'azienda | H2: expand for details ↓ | L2: Tabella 6: Altri costi per risorse umane | Q2: expand for details ↓
H3: + | Q3: +
B4: Spiegazione: | C4: Proiezione dei costi di risorse umane per il 2025, 2026 e 2027 partendo da valori del 2024 | L4: Spiegazione: | M4: Rendiconto delle altre spese per dipendenti
B6: COSTI PER RISORSE UMANE | D6: qta | E6: 2024 | F6: 2025 | G6: 2026 | H6: 2027 | L6: ALTRE SPESE PER DIPENDENTI | O6: 2024 | P6: 2025 | Q6: 2026 | R6: 2027
B7: =E122 -> Responsabile di pianificazione | D7: =D122 -> 1 | F7: =F129 -> 39840 | G7: =K129 -> 40812 | H7: =P129 -> 41412 | L7: Oneri sociali | O7: 304319 | P7: =O20 -> 330903.91 | Q7: =P20 -> 339272.97 | R7: =Q20 -> 353938.35
B8: =E123 -> Responsabile alimentare | D8: =D123 -> 1 | F8: =H129 -> 27780 | G8: =M129 -> 28548 | H8: =R129 -> 29040 | L8: TFR | O8: 34063 | P8: =O21 -> 78592.036 | Q8: =P21 -> 80579.747 | R8: =Q21 -> 84062.88
B9: =E387 -> Responsabile commerciale | D9: =D387 -> 1 | F9: =H393 -> 61560 | G9: =M393 -> 63312 | H9: =R393 -> 64440
B10: =E430 -> Responsabile finanziario | D10: =D430 -> 1 | F10: =F441 -> 55776 | G10: =I441 -> 57136.8 | H10: =L441 -> 57976.8
B11: =E474 -> Responsabile esecutivo | D11: =D474 -> 1 | F11: =F485 -> 56767.2 | G11: =I485 -> 58447.2 | H11: =L485 -> 59556
B12: =E166 -> Operaio | D12: =D166 -> 11 | F12: =F173 -> 247896 | G12: =K173 -> 254100 | H12: =P173 -> 258324
B13: =E167 -> Operai con uso di strumenti tecnici | D13: =D167 -> 5 | F13: =H173 -> 127680 | G13: =M173 -> 131040 | H13: =R173 -> 133320
B14: =E210 -> Addetto al magazzino | D14: =D210 -> 4 | F14: =F217 -> 89184 | G14: =K217 -> 91008 | H14: =P217 -> 106656
B15: =E211 -> Camionisti | D15: =D211 -> 2 | F15: =H217 -> 46056 | G15: =M217 -> 46992 | H15: =R217 -> 58080
B16: =E254 -> Impiegato tecnico | D16: =D254 -> 2 | F16: =G261 -> 51072 | G16: =J261 -> 52416 | H16: =M261 -> 53328
B17: =E298 -> Impiegato tecnico-informatico | D17: =D298 -> 1 | F17: =G305 -> 27780 | G17: =J305 -> 28548 | H17: =M305 -> 29040
B18: =E342 -> Impiegato amministrativo-contabile | D18: =D342 -> 2 | F18: =G349 -> 48072 | G18: =J349 -> 49320 | H18: =M349 -> 50160 | L18: RENDICONTO COSTI RISORSE UMANE SULLA BASE DEL PROFILO | O18: 2025 | P18: 2026 | Q18: 2027
B19: =E386 -> Agente commerciale | D19: =D386 -> 1 | F19: =F393 -> 25536 | G19: =K393 -> 26208 | H19: =P393 -> 26664 | L19: RAL | O19: =(I129+I173+I217+G261+G305+G349+I393+F441+F485)*N27 -> 1194598.9 | P19: =(N129+N173+N217+J261+J305+J349+N393+I441+I485)*N27 -> 1224812.2 | Q19: =(S129+S173+S217+M261+M305+M349+S393+L441+L485)*N27 -> 1277755.8
B20: Dipendenti | D20: =SUM(D7:D19) -> 33 | E20: =H67 -> 1114481 | F20: =SUM(F7:F19)*N27 -> 1194598.9 | G20: =SUM(G7:G19)*N27 -> 1224812.2 | H20: =SUM(H7:H19)*N27 -> 1277755.8 | L20: oneri sociali | O20: =(I130+I174+I218+G262+G306+G350+I394+G438+G482)*N27 -> 330903.91 | P20: =(N130+N174+N218+J262+J306+J350+N394+J438+J482)*N27 -> 339272.97 | Q20: =(S130+S174+S218+M262+M306+M350+S394+M438+M482)*N27 -> 353938.35
L21: TFR | O21: =(I131+I175+I219+G263+G307+G351+I395+G439+G483)*N27 -> 78592.036 | P21: =(N131+N175+N219+J263+J307+J351+N395+J439+J483)*N27 -> 80579.747 | Q21: =(S131+S175+S219+M263+M307+M351+S395+M439+M483)*N27 -> 84062.88
B22: RSPP | D22: 1 | E22: =D22*200*1.22*12*1.5 -> 4392 | F22: =E22 -> 4392 | G22: =F22 -> 4392 | H22: =G22 -> 4392 | L22: costi accessori | O22: =(I132+I176+I220+G264+G308+G352+I396+G440+G484)*N27 -> 5972.9947 | P22: =(N132+N176+N220+J264+J308+J352+N396+J440+J484)*N27 -> 6124.0608 | Q22: =(S132+S176+S220+M264+M308+M352+S396+M440+M484)*N27 -> 6388.7789
B23: Tecnologo | D23: 1 | E23: =600*1.22*12*1.5 -> 13176 | F23: =E23 -> 13176 | G23: =F23 -> 13176 | H23: =G23 -> 13176 | L23: Totale | O23: =SUM(O19:O22) -> 1610067.9 | P23: =SUM(P19:P22) -> 1650788.9 | Q23: =SUM(Q19:Q22) -> 1722145.8
B24: consulente HACCP | D24: 1 | E24: =D24*(450*1.22*12*1.5) -> 9882 | F24: =E24 -> 9882 | G24: =F24 -> 9882 | H24: =G24 -> 9882
B25: Studio legale | D25: 1 | E25: =10000*1.22*D25*1.5 -> 18300 | F25: 20000 | G25: =F25 -> 20000 | H25: =G25 -> 20000 | L25: Acconti IRPEF per conto dipendenti | O25: =TAX!M33 -> 166339.5 | P25: =TAX!N33 -> 165911.11 | Q25: =TAX!O33 -> 174286.37
B26: Studio commerciale | D26: 1 | E26: =5000*1.22*1.5 -> 9150 | F26: =E26 -> 9150 | G26: =F26 -> 9150 | H26: =G26 -> 9150 | L26: Debito vs erario in bilancio | O26: =(1/12)*O25 -> 13861.625 | P26: =(1/12)*P25 -> 13825.925 | Q26: =(1/12)*Q25 -> 14523.864
B27: Collaboratori | D27: =SUM(D22:D26) -> 5 | E27: =SUM(E22:E26) -> 54900 | F27: =SUM(F22:F26) -> 56600 | G27: =SUM(G22:G26) -> 56600 | H27: =SUM(H22:H26) -> 56600 | L27: coeficiente di maggiorazione e altro complessivi di premi: | N27: 1.32
L28: usato per avere volume salari simile a quelli in bilancio dato che i valori ccnl sono minimi indicativi senza contrattazione datore-dipendente
B29: Presidente del Cda (F. Bomè) | D29: 1 | E29: =12*D29*E51+20000 -> 20000 | F29: =E29+2000 -> 22000 | G29: =F29+2000 -> 24000 | H29: =G29+2000 -> 26000
B30: unità Consiglio di amministrazione | D30: 5 | E30: =D30*30000 -> 150000 | F30: =E30 -> 150000 | G30: =F30 -> 150000 | H30: =G30 -> 150000 | L30: Debito vs erario in bilancio: l'ultima mensilità non viene pagata a chiusura di conti dato che viene pagata entro il 16 di gennaio
B31: presidente del colleggio sindacale | D31: 1 | E31: 26000 | F31: =E31 -> 26000 | G31: =F31 -> 26000 | H31: =G31 -> 26000
B32: unità sindaci | D32: 4 | E32: =D32*24000 -> 96000 | F32: =E32 -> 96000 | G32: =F32 -> 96000 | H32: =G32 -> 96000
B33: Amministratori e Sindaci | D33: =SUM(D29:D32) -> 11 | E33: =SUM(E29:E32) -> 292000 | F33: =SUM(F29:F32) -> 294000 | G33: =SUM(G29:G32) -> 296000 | H33: =SUM(H29:H32) -> 298000
B34: Totale | D34: =D33+D27+D20 -> 49 | E34: =E33+E27+E20 -> 1461381 | F34: =F33+F27+F20 -> 1545198.9 | G34: =G33+G27+G20 -> 1577412.2 | H34: =H33+H27+H20 -> 1632355.8
B37: Proiezioni spese per dipendenti BT
B38: al 2024 sono presenti complessivamente 30 + 2 dipendenti | E38: su base di bilancio AIDA
B39: Nel 2025 si sostituisce un OSA, uscito nel 2024 | E39: su base di bilancio AIDA, e pagina recruiting sul sito aziendale nel 2025
B40: per il 2026 | E40: si ipotizza rimane invariato
B41: per il 2027 | E41: si ipotizza rimane invariato
B43: Le assunzioni sul numero di dipendenti sono fatti sulla base delle foto disponibili sul sito aziendale, sulle immagini e dimensione del sito produttivo e dal numero di auto presenti e chiaramente inerenti all'impresa produttiva.
B50: SPESE PER COLLABORATORI
B52: RSPP | C52: https://www.adecco.com/it-it/candidati/il-lavoro-che-cambia/rspp-cosa-fa | E52: =E22 -> 4392
B53: Tecnologo | C53: https://www.glassdoor.it/Stipendi/consulente-tecnico-alimentare-stipendio-SRCH_KO0,29.htm | E53: =E23 -> 13176
B54: HCCP | C54: https://www.jobbydoo.it/stipendio/consulente-haccp#:~:text=Domande%20Frequenti%20sullo%20Stipendio%20del%20Consulente%20HACCP,%C3%A8%20di%20circa%2050.000%20%E2%82%AC%20lordi%20all'anno. | E54: =E24 -> 9882
B60: CALCOLO COSTI DIPENDENTI SU BASE DEL PROFILO
F61: Sezione di individuazione dei coefficienti da utilizzare per il calcolo degli oneri sociali, TFR e altri costi accessori.
B63: Metodo di calcolo:
B64: Basato su: https://www.dipendentincloud.it/blog/costo-personale-dipendente/#contributi-inps-inail
M65: projections
B66: given data | F66: PROCESSO DI REV.E. | G66: 2023 | H66: 2024 | I66: actual coef | K66: given coef cross-check | M66: 2025 | N66: 2026 | O66: 2027
B67: RAL (12, 13 o 14) | F67: RAL (14 mensilità) | G67: 1153603 | H67: 1114481 | I67: =G67 -> 1153603 | J67: =H67 -> 1114481 | K67: =G67 -> 1153603 | L67: =H67 -> 1114481 | M67: =O19 -> 1194598.9 | N67: =P19 -> 1224812.2 | O67: =Q19 -> 1277755.8
B68: +oneri sociali aka contributi INPS/INAIL (35% RAL) | F68: oneri sociali | G68: 320564 | H68: 304319 | I68: =G68/I67 -> 0.27788069 | J68: =H68/J67 -> 0.27305894 | K68: =0.35*K67 -> 403761.05 | L68: =L67*0.35 -> 390068.35 | M68: =O20 -> 330903.91 | N68: =P20 -> 339272.97 | O68: =Q20 -> 353938.35
B69: +TFR (RAL/13,5) | F69: TFR | G69: 69740 | H69: 34063 | I69: =I67/SUM(G69:G70) -> 15.275463 | J69: =J67/SUM(H69:H70) -> 15.122269 | K69: =K67/13.5 -> 85452.074 | L69: =L67/13.5 -> 82554.148 | M69: =O21 -> 78592.036 | N69: =P21 -> 80579.747 | O69: =Q21 -> 84062.88
B70: +T.Q e altri Obbl. simili | F70: T.quiesenza | G70: 5780 | H70: 39635 | K70: 0 | L70: 0 | M70: 0 | N70: 0 | O70: 0
B71: +costi accessori per dipendente singolo | F71: costi accessori | G71: 6380 | H71: 5960 | I71: =G71/I67 -> 0.0055304988 | J71: =H71/J67 -> 0.0053477807 | K71: =G71 -> 6380 | L71: =H71 -> 5960 | M71: =O22 -> 5972.9947 | N71: =P22 -> 6124.0608 | O71: =Q22 -> 6388.7789
B72: Totale | F72: Totale | G72: =SUM(G67:G71) -> 1556067 | H72: =SUM(H67:H71) -> 1498458 | K72: =SUM(K67:K71) -> 1649196.1 | L72: =SUM(L67:L71) -> 1593063.5 | M72: =SUM(M67:M71) -> 1610067.9 | N72: =SUM(N67:N71) -> 1650788.9 | O72: =SUM(O67:O71) -> 1722145.8
B75: calculated data | E75: coefficienti da utilizzare
B76: RAL (12, 13 o 14) | E76: 1
B77: +oneri sociali aka contributi INPS/INAIL | E77: 0.277
B78: +TFR | E78: 15.2
B79: +T.Q e altri Obbl. simili
B80: +costi accessori per dipendente singolo | E80: 0.005
B81: Totale
B88: ANALISI INDIVIDUALE PROFILI DI DIPENDENTI
B90: L'analisi è svolta partendo dal documento di analisi del processo opeativo industriale di Bomè, dove sono state individuate i profili neccessari in base alle esigenze aziendali e struttura dell'impresa.
B91: Si individuano i RAL per ciascuna figura, rispettivamente per gli anni di interesse e il numero di figure neccessarie, indivuando complessivamente il RAL totale.
B92: I RAL individuati potrebbero essere una rappresentazione minore rispetto ai valori effettivi.
C95: Figura di riferimento: | E95: Responsabile del Settore Alimentare (OSA)
C96: Fig. neccessarie | E96: 2
C97: CCNL | E97: Alimentari e industria
C98: src | E98: https://www.conflavoro.it/ccnl/contratto-nazionale-alimentari-industria/#:~:text=Table_title:%20Settore%20Alimentare%20Table_content:%20header:%20%7C%20Livello,%7C%20Minimi%20al%2001.01.2026:%20%E2%82%AC%202.379%2C00%20%7C
E99: https://www.coverflex.com/it/blog/ccnl-industria-alimentare
C101: mensiilità | E101: 14
C102: paga giornaliera | E102: 26 gg
C103: paga oraria | E103: 173
E106: Settore Alimentare
E108: Livello | F108: Minimi al | G108: Minimi al | H108: Minimi al
F109: 01.07.2025 | G109: 01.01.2026 | H109: 01.01.2027
E110: Quadri* | F110: 3379 | G110: 3479 | H110: 3545
E111: Primo livello | F111: 3320 | G111: 3401 | H111: 3451
E112: Secondo livello | F112: 3003 | G112: 3091 | H112: 3148
E113: Terzo livello | F113: 2565 | G113: 2638 | H113: 2685
E114: Quarto livello | F114: 2315 | G114: 2379 | H114: 2420
E115: Quinto livello | F115: 2128 | G115: 2184 | H115: 2222
E116: Sesto livello | F116: 2003 | G116: 2055 | H116: 2090
E117: Settimo livello | F117: 1878 | G117: 1925 | H117: 1957
E118: Ottavo livello | F118: 1753 | G118: 1797 | H118: 1825
F121: Livello
C122: Figure neccessarie: | D122: 1 | E122: Responsabile di pianificazione | F122: Primo | G122: rotazione nel 2025 | H122: https://www.bome.it/annuncio-di-ricerca-personale/
D123: 1 | E123: Responsabile alimentare | F123: Quarto
C126: Calcolo costi dipendenti | E126: 2025 | J126: 2026 | O126: 2027 | T126: 2027
C127: Figura | E127: Responsabile di pianificazione | G127: Responsabile alimentare | I127: Totale | J127: Responsabile di pianificazione | L127: Responsabile alimentare | N127: Totale | O127: Responsabile di pianificazione | Q127: Responsabile alimentare | S127: Totale | T127: Responsabile di pianificazione | V127: Responsabile alimentare | X127: Totale
C128: costo | E128: unitario | F128: totale | G128: unitario | H128: totale | J128: unitario | K128: totale | L128: unitario | M128: totale | O128: unitario | P128: totale | Q128: unitario | R128: totale | T128: unitario | U128: totale | V128: unitario | W128: totale
C129: RAL | E129: =F111*12 -> 39840 | F129: =E129*$D$122 -> 39840 | G129: =F114*12 -> 27780 | H129: =G129*$D$123 -> 27780 | I129: =H129+F129 -> 67620 | J129: =G111*12 -> 40812 | K129: =J129*$D$122 -> 40812 | L129: =G114*12 -> 28548 | M129: =L129*$D$123 -> 28548 | N129: =M129+K129 -> 69360 | O129: =H111*12 -> 41412 | P129: =O129*$D$122 -> 41412 | Q129: =H114*12 -> 29040 | R129: =Q129*$D$123 -> 29040 | S129: =R129+P129 -> 70452 | T129: =H111*12 -> 41412 | U129: =T129*$D$122 -> 41412 | V129: =H114*12 -> 29040 | W129: =V129*$D$123 -> 29040 | X129: =W129+U129 -> 70452
C130: contributi INPS/INAIL | E130: =E129*$E$77 -> 11035.68 | F130: =E130*$D$122 -> 11035.68 | G130: =G129*$E$77 -> 7695.06 | H130: =G130*$D$123 -> 7695.06 | I130: =H130+F130 -> 18730.74 | J130: =J129*$E$77 -> 11304.924 | K130: =J130*$D$122 -> 11304.924 | L130: =L129*$E$77 -> 7907.796 | M130: =L130*$D$123 -> 7907.796 | N130: =M130+K130 -> 19212.72 | O130: =O129*$E$77 -> 11471.124 | P130: =O130*$D$122 -> 11471.124 | Q130: =Q129*$E$77 -> 8044.08 | R130: =Q130*$D$123 -> 8044.08 | S130: =R130+P130 -> 19515.204 | T130: =T129*$E$77 -> 11471.124 | U130: =T130*$D$122 -> 11471.124 | V130: =V129*$E$77 -> 8044.08 | W130: =V130*$D$123 -> 8044.08 | X130: =W130+U130 -> 19515.204
C131: TFR | E131: =E129/$E$78 -> 2621.0526 | F131: =E131*$D$122 -> 2621.0526 | G131: =G129/$E$78 -> 1827.6316 | H131: =G131*$D$123 -> 1827.6316 | I131: =H131+F131 -> 4448.6842 | J131: =J129/$E$78 -> 2685 | K131: =J131*$D$122 -> 2685 | L131: =L129/$E$78 -> 1878.1579 | M131: =L131*$D$123 -> 1878.1579 | N131: =M131+K131 -> 4563.1579 | O131: =O129/$E$78 -> 2724.4737 | P131: =O131*$D$122 -> 2724.4737 | Q131: =Q129/$E$78 -> 1910.5263 | R131: =Q131*$D$123 -> 1910.5263 | S131: =R131+P131 -> 4635 | T131: =T129/$E$78 -> 2724.4737 | U131: =T131*$D$122 -> 2724.4737 | V131: =V129/$E$78 -> 1910.5263 | W131: =V131*$D$123 -> 1910.5263 | X131: =W131+U131 -> 4635
C132: costi accessori | E132: =E129*$E$80 -> 199.2 | F132: =E132*$D$122 -> 199.2 | G132: =G129*$E$80 -> 138.9 | H132: =G132*$D$123 -> 138.9 | I132: =H132+F132 -> 338.1 | J132: =J129*$E$80 -> 204.06 | K132: =J132*$D$122 -> 204.06 | L132: =L129*$E$80 -> 142.74 | M132: =L132*$D$123 -> 142.74 | N132: =M132+K132 -> 346.8 | O132: =O129*$E$80 -> 207.06 | P132: =O132*$D$122 -> 207.06 | Q132: =Q129*$E$80 -> 145.2 | R132: =Q132*$D$123 -> 145.2 | S132: =R132+P132 -> 352.26 | T132: =T129*$E$80 -> 207.06 | U132: =T132*$D$122 -> 207.06 | V132: =V129*$E$80 -> 145.2 | W132: =V132*$D$123 -> 145.2 | X132: =W132+U132 -> 352.26
I133: =SUM(I129:I132) -> 91137.524 | N133: =SUM(N129:N132) -> 93482.678 | S133: =SUM(S129:S132) -> 94954.464 | X133: =SUM(X129:X132) -> 94954.464
C139: Figura di riferimento: | E139: Operai generici
C140: Fig. neccessarie | E140: =D166+D167 -> 16
C141: CCNL | E141: Alimentari e industria
C142: src | E142: https://www.conflavoro.it/ccnl/contratto-nazionale-alimentari-industria/#:~:text=Table_title:%20Settore%20Alimentare%20Table_content:%20header:%20%7C%20Livello,%7C%20Minimi%20al%2001.01.2026:%20%E2%82%AC%202.379%2C00%20%7C
...

Sheet INV
B2: Tabella 7: Spese di investimento e immobilizzazioni per 25-26-27 | H2: expand for details ↓
H3: +
B4: Spiegazione: | C4: Individuate rispettive voci di investimento rispetto al bilancio consuntivo del 2024. Si scompongono gli investimenti in immobilizzazioni per individuare gli ammortamenti annuali e verificare se le aliquote soiano corrette.In questo modo si calcolano gli ammortamenti futuri. Successivamente si cerca di calcolare gli investimenti storici e in base agli ammortamenti i fondi ammortamento e i numeri di ammortamenti effettuati e rimanenti per ciascuna immobilizzazione.
B7: SPESE DI INVESTIMENTO | C7: 2022 | D7: 2023 | E7: 2024 | F7: 2025 | G7: 2026 | H7: 2027
B8: Diritti brevetti industriali | C8: 130172 | D8: 97381 | E8: 64590 | F8: =N46 -> 35088 | G8: =SUM(N85:N86) -> 992 | H8: =SUM(O85:O86) -> 0
B9: Concessioni, Licenze | C9: 9545 | D9: 8999 | E9: 8453 | F9: =M87 -> 7907 | G9: =N87 -> 7361 | H9: =O87 -> 6815
B10: Altre immobilizzazioni immateriali | C10: 0 | D10: 0 | E10: 16480 | F10: =M88 -> 14832 | G10: =N88 -> 13184 | H10: =O88 -> 11536
B11: Totale investimenti immateriali | C11: =SUM(C8:C10) -> 139717 | D11: =SUM(D8:D10) -> 106380 | E11: =SUM(E8:E10) -> 89523 | F11: =SUM(F8:F10) -> 57827 | G11: =SUM(G8:G10) -> 21537 | H11: =SUM(H8:H10) -> 18351
B14: Terreni e fabbricati | C14: 6543383 | D14: 6328571 | E14: 6069102 | F14: =N56 -> 5796679.2 | G14: =O56 -> 5524256.4 | H14: =P56 -> 5251833.7
B15: Impianti | C15: 2352511 | D15: 2137598 | E15: 1774810 | F15: =N57 -> 1834142.7 | G15: =O57 -> 1409009.1 | H15: =P57 -> 1003322.8
B16: Attrezzature industriali | C16: 184756 | D16: 187192 | E16: 197170 | F16: =N58 -> 168713.53 | G16: =O58 -> 140257.05 | H16: =P58 -> 111800.58
B17: Altri beni immobilizzati | C17: 312178 | D17: 244518 | E17: 177873 | F17: =N59 -> 156391.32 | G17: =O59 -> 134909.64 | H17: =P59 -> 113427.96
B18: Immobilizzazioni in corso | C18: 23700 | D18: 119891 | E18: 475770 | F18: 0 | G18: 0 | H18: 0
B19: Totale investimenti materiali | C19: =SUM(C14:C18) -> 9416528 | D19: =SUM(D14:D18) -> 9017770 | E19: =SUM(E14:E18) -> 8694725 | F19: =SUM(F14:F18) -> 7955926.7 | G19: =SUM(G14:G18) -> 7208432.2 | H19: =SUM(H14:H18) -> 6480385
B22: Partecipazioni | C22: 58702 | D22: =C22 -> 58702 | E22: =D22 -> 58702 | F22: =M126 -> 58702 | G22: =N126 -> 58702 | H22: =O126 -> 58702
B23: Totale investimenti finanziari | C23: =SUM(C22) -> 58702 | D23: =SUM(D22) -> 58702 | E23: =SUM(E22) -> 58702 | F23: =SUM(F22) -> 58702 | G23: =SUM(G22) -> 58702 | H23: =SUM(H22) -> 58702
B26: Ammto immobilizzazioni immateriali | C26: 37282 | D26: 33337 | E26: =SUM(K85:K88) -> 37282 | F26: =SUM(Q85:Q88) -> 36290 | G26: =SUM(R85:R88) -> 2194 | H26: =SUM(S85:S88) -> 2194
B27: Ammto immobilizzazioni materiali | C27: 822987 | D27: 866491 | E27: 879520 | F27: =SUM(Q91:Q95)+SUM(Q98:Q104)+SUM(Q107:Q114)+SUM(Q117:Q121) -> 763006.26 | G27: =SUM(R91:R95)+SUM(R98:R104)+SUM(R107:R114)+SUM(R117:R121) -> 747494.49 | H27: =SUM(S91:S95)+SUM(S98:S104)+SUM(S107:S114)+SUM(S117:S121) -> 728047.24
B28: Totale ammortamenti | C28: =SUM(C26:C27) -> 860269 | D28: =D27+D26 -> 899828 | E28: =E27+E26 -> 916802 | F28: =F27+F26 -> 799296.26 | G28: =G27+G26 -> 749688.49 | H28: =H27+H26 -> 730241.24
B36: PROCESSO DI ANALISI INVESTIMENTI IN IMMOBILIZZAZIONI
L38: Tabella 7A: PROIEZIONI VOCI DI BILANCIO RELATIVE ALLE IMMOBILIZZAZIONI PER IL 2025/26/27
L39: RENDICONTO RISPETTO ALLE ELABORAZIONI PRESENTI IN SEGUITO
B41: BILANCIO CONSUNTIVO | C41: 2024 | D41: 2023 | E41: 2022 | F41: 2021 | G41: 2020 | H41: 2019 | I41: 2018 | J41: 2017 | L41: PROIEZIONE IMMOBILIZZAZIONI | N41: 2025 | O41: 2026 | P41: 2027
B42: B. TOTALE IMMOBILIZZAZIONI sep.ind. Di quelle conc. In loc. Finanz. | C42: 8842950 | D42: 9182852 | E42: 9614947 | F42: 9565702 | G42: 7073181 | H42: 2616289 | I42: 1201123 | J42: 908499 | L42: =B42 -> B. TOTALE IMMOBILIZZAZIONI sep.ind. Di quelle conc. In loc. Finanz. | N42: =N43+N54+N63 -> 8072455.7 | O42: =O43+O54+O63 -> 7288671.2 | P42: =P43+P54+P63 -> 6557438
B43: B.I. TOTALE IMMOB. IMMATERIALI | C43: 89523 | D43: 106380 | E43: 139717 | F43: 76490 | G43: 33453 | H43: 7543 | I43: 0 | J43: 1977 | L43: =B43 -> B.I. TOTALE IMMOB. IMMATERIALI | N43: =SUM(N44:N52) -> 57827 | O43: =SUM(O44:O52) -> 21537 | P43: =SUM(P44:P52) -> 18351
B44: B.I.1. Costi Impianto e ampl. | C44: 0 | D44: 0 | E44: 0 | F44: 0 | G44: 0 | H44: 0 | I44: 0 | J44: 0 | L44: =B44 -> B.I.1. Costi Impianto e ampl. | N44: 0 | O44: 0 | P44: 0
B45: B.I.2. Costi ricerca e pubb. | C45: 0 | D45: 0 | E45: 0 | F45: 0 | G45: 0 | H45: 0 | I45: 0 | J45: 0 | L45: =B45 -> B.I.2. Costi ricerca e pubb. | N45: 0 | O45: 0 | P45: 0
B46: B.I.3. Diritti brevetto ind. | C46: 64590 | D46: 97381 | E46: 130172 | F46: 3968 | G46: 4960 | H46: 0 | I46: 0 | J46: 0 | L46: =B46 -> B.I.3. Diritti brevetto ind. | N46: =C46-SUM(M85:M86) -> 35088 | O46: =N46-K86 -> 992 | P46: 0
B47: B.I.4. Concessioni, licenze | C47: 8453 | D47: 8999 | E47: 9545 | F47: 0 | G47: 0 | H47: 0 | I47: 0 | J47: 0 | L47: =B47 -> B.I.4. Concessioni, licenze | N47: =C47-Q87 -> 7907 | O47: =N47-R87 -> 7361 | P47: =O47-S87 -> 6815
B48: B.I.5. Avviamento/Differenza di consolidamento | C48: 0 | D48: 0 | E48: 0 | F48: 0 | G48: 0 | H48: 0 | I48: 0 | J48: 0 | L48: =B48 -> B.I.5. Avviamento/Differenza di consolidamento | N48: 0 | O48: 0 | P48: 0
B49: di cui: Avviamento | C49: 0 | D49: 0 | E49: 0 | F49: 0 | G49: 0 | H49: 0 | I49: 0 | J49: 0 | L49: =B49 -> di cui: Avviamento | N49: 0 | O49: 0 | P49: 0
B50: B.I.6. Imm. in corso | C50: 0 | D50: 0 | E50: 0 | F50: 67622 | G50: 28493 | H50: 7543 | I50: 0 | J50: 0 | L50: =B50 -> B.I.6. Imm. in corso | N50: 0 | O50: 0 | P50: 0
B51: B.I.7. Altre immobiliz. Immateriali | C51: 16480 | D51: 0 | E51: 0 | F51: 4900 | G51: 0 | H51: 0 | I51: 0 | J51: 1977 | L51: =B51 -> B.I.7. Altre immobiliz. Immateriali | N51: =C51-Q88 -> 14832 | O51: =N51-R88 -> 13184 | P51: =O51-S88 -> 11536
B52: Fondo amm.to Immob. Immateriali | C52: n.d. | D52: n.d. | E52: n.d. | F52: n.d. | G52: n.d. | H52: n.d. | I52: n.d. | J52: n.d. | L52: =B52 -> Fondo amm.to Immob. Immateriali | N52: n.d. | O52: n.d. | P52: n.d.
L53: =B53 -> 0
B54: B.II. TOTALE IMMOB. MATERIALI | C54: 8694725 | D54: 9017770 | E54: 9416528 | F54: 9430510 | G54: 7025024 | H54: 2594042 | I54: 1186419 | J54: 891818 | L54: =B54 -> B.II. TOTALE IMMOB. MATERIALI | N54: =SUM(N55:N61) -> 7955926.7 | O54: =SUM(O55:O61) -> 7208432.2 | P54: =SUM(P55:P61) -> 6480385
B55: di cui: Beni materiali concessi in locazione finanziaria | C55: n.d. | D55: n.d. | E55: n.d. | F55: n.d. | G55: n.d. | H55: n.d. | I55: n.d. | J55: n.d. | L55: =B55 -> di cui: Beni materiali concessi in locazione finanziaria | N55: n.d. | O55: =N55 -> n.d. | P55: =O55 -> n.d.
B56: B.II.1. Terreni e fabbricati | C56: 6069102 | D56: 6328571 | E56: 6543383 | F56: 6374984 | G56: 396319 | H56: 412628 | I56: 418736 | J56: 324645 | L56: =B56 -> B.II.1. Terreni e fabbricati | N56: =C56-SUM(Q91:Q95) -> 5796679.2 | O56: =N56-SUM(R91:R95) -> 5524256.4 | P56: =O56-SUM(S91:S95) -> 5251833.7
B57: B.II.2. Impianti | C57: 1774810 | D57: 2137598 | E57: 2352511 | F57: 2232169 | G57: 1801043 | H57: 258024 | I57: 302043 | J57: 336024 | L57: =B57 -> B.II.2. Impianti | N57: =C57-SUM(Q99:Q103)+U103 -> 1834142.7 | O57: =N57-SUM(R98:R104) -> 1409009.1 | P57: =O57-SUM(S98:S104) -> 1003322.8
B58: B.II.3. Attrez. industriali | C58: 197170 | D58: 187192 | E58: 184756 | F58: 168289 | G58: 141111 | H58: 110856 | I58: 130147 | J58: 133231 | L58: =B58 -> B.II.3. Attrez. industriali | N58: =C58-SUM(Q107:Q114) -> 168713.53 | O58: =N58-SUM(R107:R114) -> 140257.05 | P58: =O58-SUM(S107:S114) -> 111800.58
B59: B.II.4. Altri beni | C59: 177873 | D59: 244518 | E59: 312178 | F59: 236539 | G59: 116965 | H59: 45295 | I59: 68843 | J59: 97918 | L59: =B59 -> B.II.4. Altri beni | N59: =C59-SUM(Q117:Q121) -> 156391.32 | O59: =N59-SUM(R117:R121) -> 134909.64 | P59: =O59-SUM(S117:S121) -> 113427.96
B60: B.II.5. Imm. in corso/acconti | C60: 475770 | D60: 119891 | E60: 23700 | F60: 418529 | G60: 4569586 | H60: 1767239 | I60: 266650 | J60: 0 | L60: =B60 -> B.II.5. Imm. in corso/acconti | N60: 0 | O60: 0 | P60: 0
B61: Fondo amm.to Immob. Materiali | C61: n.d. | D61: n.d. | E61: n.d. | F61: n.d. | G61: n.d. | H61: n.d. | I61: n.d. | J61: n.d. | L61: =B61 -> Fondo amm.to Immob. Materiali
L62: =B62 -> 0
B63: B.III. TOTALE IMMOB. FINANZIARIE | C63: 58702 | D63: 58702 | E63: 58702 | F63: 58702 | G63: 14704 | H63: 14704 | I63: 14704 | J63: 14704 | L63: =B63 -> B.III. TOTALE IMMOB. FINANZIARIE | N63: 58702 | O63: =N63 -> 58702 | P63: =O63 -> 58702
B64: di cui: esigibili entro l'esercizio successivo | C64: 0 | D64: 0 | E64: 0 | F64: 0 | G64: 8192 | H64: 8192 | I64: 8192 | J64: 0 | L64: =B64 -> di cui: esigibili entro l'esercizio successivo | N64: 0 | O64: 0 | P64: 0
B65: B.III.1. TOT Partecipazioni | C65: 58702 | D65: 58702 | E65: 58702 | F65: 58702 | G65: 6512 | H65: 6512 | I65: 6512 | J65: 6512 | L65: =B65 -> B.III.1. TOT Partecipazioni | N65: =N63 -> 58702 | O65: =O63 -> 58702 | P65: =P63 -> 58702
B66: var tot. Immobilizzazioni | C66: =C42-D42 -> -339902 | D66: =D42-E42 -> -432095 | E66: =E42-F42 -> 49245 | F66: =F42-G42 -> 2492521 | G66: =G42-H42 -> 4456892 | H66: =H42-I42 -> 1415166 | I66: =I42-J42 -> 292624 | J66: n.d.
B67: amti imm | C67: 33337 | D67: =D43-C43+C51 -> 33337 | E67: ok
B68: amti mat | C68: 866491 | D68: =D56-C56+D57-C57+D59-C59 -> 688902 | E68: ammortizati
B69: ammortamento x-1 ufficiale | C69: -899828 | D69: immobilizzazioni calano meno di quanto ammortato
B70: ammortamento x-1 calcolato | C70: =SUM(K85:K87)+SUM(K91:K94)+SUM(K98:K102)+SUM(K107:K113)-K109+SUM(K119:K121) -> 824821.53 | D70: =C68-D68 -> 177589 | E70: altri ammortizzati
B71: diff | C71: =C70+C69 -> -75006.473 | D71: =D54-C54+D70 -> 500634 | E71: investimento effettivo in corso B.II.5
B72: imm fin - (inm iniz -amti) = investimenti | C72: =C66-C69 -> 559926 | D72: nuovi investimenti
B73: inv calcolato | C73: =C58-D58+C60-D60 -> 365857
B75: Dati i numerosi recenti investimenti di ampliamento, riteniamo sia in corso un periodo di ottenere ROI e recupero, inoltre data la linea di prodotti ben completa e il crescente andamento dei tassi di interesse, non riteniamo necessario investire al momento in altri impianti o immobilizzazioni.
B80: PROCESSO DI SPACCHETTO INVESTIMENTI
F81: spiegazione: | G81: voce contabile = investimento iniziale - fdo ammortamento; prima voce è investimento meno ammortamento di competenza; seconda voce è netto di 2 ammortamenti. Così si individua la rata di ammortamento ipotizzando che non ci siano state variazioni di aliquote.
B83: Lista di tutte le immobilizzazioni | C83: indivudate attraverso la separazione storico-contabile | Q83: Spacchetto ammortamenti | U83: Costo storico basato su bilanci consuntivi
B84: TABELLA INVESTIMENTI | C84: 2017 | D84: 2018 | E84: 2019 | F84: 2020 | G84: 2021 | H84: 2022 | I84: 2023 | J84: 2024 | K84: AMMTO | L84: ALIQ | M84: 2025 | N84: 2026 | O84: 2027 | Q84: 2025 | R84: 2026 | S84: 2027 | U84: Investimento iniziale
B85: brevetto 1 | F85: 4960 | G85: =F85-K85 -> 3968 | H85: =G85-K85 -> 2976 | I85: =H85-K85 -> 1984 | J85: =I85-K85 -> 992 | K85: 992 | L85: 0.2 | M85: =J85-K85 -> 0 | N85: 0 | O85: 0 | Q85: 0 | R85: 0 | S85: 0 | U85: =F85 -> 4960
B86: brevetto 2 | H86: =130172-H85 -> 127196 | I86: =97381-I85 -> 95397 | J86: =64590-J85 -> 63598 | K86: =H86-I86+2297 -> 34096 | L86: =K86/H86 -> 0.26805874 | M86: =J86-K86 -> 29502 | N86: 992 | O86: 0 | Q86: =J86-M86 -> 34096 | R86: 0 | S86: 0 | U86: =H86 -> 127196
B87: licenza 1 | H87: 9545 | I87: 8999 | J87: 8453 | K87: =H87-I87 -> 546 | L87: =K87/H87 -> 0.057202724 | M87: =J87-K87 -> 7907 | N87: =M87-K87 -> 7361 | O87: =N87-K87 -> 6815 | Q87: =J87-M87 -> 546 | R87: =M87-N87 -> 546 | S87: =R87 -> 546 | U87: =H87 -> 9545
B88: altre immobilizzazioni immateriali | J88: 16480 | K88: =J88*L88 -> 1648 | L88: 0.1 | M88: =J88-K88 -> 14832 | N88: =M88-K88 -> 13184 | O88: =N88-K88 -> 11536 | Q88: =R88 -> 1648 | R88: =M88-N88 -> 1648 | S88: =N88-O88 -> 1648 | U88: =J88 -> 16480
B89: check | C89: =SUM(C85:C88) -> 0 | D89: =SUM(D85:D88) -> 0 | E89: =SUM(E85:E88) -> 0 | F89: =SUM(F85:F88) -> 4960 | G89: =SUM(G85:G88) -> 3968 | H89: =SUM(H85:H88) -> 139717 | I89: =SUM(I85:I88) -> 106380 | J89: =SUM(J85:J88) -> 89523 | K89: =SUM(K85:K88) -> 37282 | M89: =SUM(M85:M88) -> 52241 | N89: =SUM(N85:N88) -> 21537 | O89: =SUM(O85:O88) -> 18351
B91: Terreno o fabbricato 1 | E91: 412628 | F91: 396319 | G91: =F91-K91 -> 380010 | H91: =G91-K91 -> 363701 | I91: =H91-K91 -> 347392 | J91: =I91-K91 -> 331083 | K91: =E91-F91 -> 16309 | L91: =K91/E91 -> 0.039524705 | M91: =J91-K91 -> 314774 | N91: =M91-K91 -> 298465 | O91: =N91-K91 -> 282156 | Q91: =K91 -> 16309 | R91: =Q91 -> 16309 | S91: =R91 -> 16309 | U91: =E91 -> 412628
B92: Terreno o fabbricato 2 | G92: =6374984-G91 -> 5994974 | H92: =G92-K92 -> 5758172.5 | I92: =H92-K92 -> 5521371.1 | J92: =I92-K92 -> 5284569.6 | K92: =G92*L92 -> 236801.47 | L92: 0.0395 | M92: =J92-K92 -> 5047768.1 | N92: =M92-K92 -> 4810966.6 | O92: =N92-K92 -> 4574165.2 | Q92: =K92 -> 236801.47 | R92: =Q92 -> 236801.47 | S92: =R92 -> 236801.47 | U92: =G92 -> 5994974
B93: Terreno o fabbricato 3 | H93: =6543383-H92-H91 -> 421509.47 | I93: =H93-K93 -> 404859.85 | J93: =I93-K93 -> 388210.22 | K93: =L93*H93 -> 16649.624 | L93: 0.0395 | M93: =J93-K93 -> 371560.6 | N93: =M93-K93 -> 354910.98 | O93: =N93-K93 -> 338261.35 | Q93: =K93 -> 16649.624 | R93: =Q93 -> 16649.624 | S93: =R93 -> 16649.624 | U93: =H93 -> 421509.47
B94: Terreno o fabbricato 4 | I94: =6328571-I93-I92-I91 -> 54948.097 | J94: =I94-K94 -> 52777.647 | K94: =I94*L94 -> 2170.4498 | L94: 0.0395 | M94: =J94-K94 -> 50607.198 | N94: =M94-K94 -> 48436.748 | O94: =N94-K94 -> 46266.298 | Q94: =K94 -> 2170.4498 | R94: =Q94 -> 2170.4498 | S94: =R94 -> 2170.4498 | U94: =I94 -> 54948.097
B95: Terreno o fabbricato 5 | J95: =6069102-SUM(J91:J94) -> 12461.547 | K95: =J95*L95 -> 492.23111 | L95: 0.0395 | M95: =J95-K95 -> 11969.316 | N95: =M95-K95 -> 11477.085 | O95: =N95-K95 -> 10984.854 | Q95: =K95 -> 492.23111 | R95: =Q95 -> 492.23111 | S95: =R95 -> 492.23111 | U95: =J95 -> 12461.547
B96: check | C96: =SUM(C91:C95) -> 0 | D96: =SUM(D91:D95) -> 0 | E96: =SUM(E91:E95) -> 412628 | F96: =SUM(F91:F95) -> 396319 | G96: =SUM(G91:G95) -> 6374984 | H96: =SUM(H91:H95) -> 6543383 | I96: =SUM(I91:I95) -> 6328571 | J96: =SUM(J91:J95) -> 6069102 | M96: =SUM(M91:M95) -> 5796679.2 | N96: =SUM(N91:N95) -> 5524256.4 | O96: =SUM(O91:O95) -> 5251833.7
B98: Impianto 1 | C98: 336024 | D98: 302043 | E98: 258024 | F98: =E98-K98 -> 214004.86 | G98: =F98-K98 -> 169985.71 | H98: =G98-K98 -> 125966.57 | I98: =H98-K98 -> 81947.424 | J98: =I98-K98 -> 37928.28 | K98: =C98*L98 -> 44019.144 | L98: 0.131 | M98: 0 | N98: 0 | O98: 0 | Q98: 0 | R98: 0 | S98: 0 | U98: =C98 -> 336024
B99: Impianto 2 | F99: =1801043-F98 -> 1587038.1 | G99: =F99-K99 -> 1388658.4 | H99: =G99-K99 -> 1190278.6 | I99: =H99-K99 -> 991898.84 | J99: =I99-K99 -> 793519.07 | K99: =L99*F99 -> 198379.77 | L99: 0.125 | M99: =J99-K99 -> 595139.3 | N99: =M99-K99 -> 396759.54 | O99: =N99-K99 -> 198379.77 | Q99: =K99 -> 198379.77 | R99: =Q99 -> 198379.77 | S99: =R99 -> 198379.77 | U99: =F99 -> 1587038.1
B100: Impianto 3 | G100: =2232169-G99-G98 -> 673524.91 | H100: =G100-K100 -> 585293.15 | I100: =H100-K100 -> 497061.39 | J100: =I100-L100 -> 497061.25 | K100: =L100*G100 -> 88231.763 | L100: 0.131 | M100: =J100-K100 -> 408829.49 | N100: =M100-K100 -> 320597.73 | O100: =N100-K100 -> 232365.96 | Q100: =K100 -> 88231.763 | R100: =Q100 -> 88231.763 | S100: =R100 -> 88231.763 | U100: =G100 -> 673524.91
B101: Impianto 4 | H101: =2352511-H100-H99-H98 -> 450972.68 | I101: =H101-K101 -> 391895.25 | J101: =I101-L101 -> 391895.12 | K101: =L101*H101 -> 59077.42 | L101: 0.131 | M101: =J101-K101 -> 332817.7 | N101: =M101-K101 -> 273740.28 | O101: =N101-K101 -> 214662.86 | Q101: =K101 -> 59077.42 | R101: =Q101 -> 59077.42 | S101: =R101 -> 59077.42 | U101: =H101 -> 450972.68
B102: Impianto 5 | I102: =2137598-SUM(I98:I101) -> 174795.1 | J102: =I102-K102-85429.81 -> 54406.267 | K102: =L102*I102 -> 34959.019 | L102: 0.2 | M102: =J102-K102 -> 19447.248 | N102: 0 | O102: 0 | Q102: =K102 -> 34959.019 | R102: =M102 -> 19447.248 | S102: 0 | U102: =I102 -> 174795.1
B103: impianto nuovo (imm.in corso 2022-2025) | J103: 0 | K103: =L103*U103 -> 59997.36 | L103: 0.12 | M103: =U103-K151 -> 439978 | N103: =M103-L151 -> 379978 | O103: =N103-M151 -> 319978 | Q103: =K103 -> 59997.36 | R103: =Q103 -> 59997.36 | S103: =R103 -> 59997.36 | U103: 499978 | W103: https://www.bome.it/programma-fesr-2021-2027/ | X103: individuato investimento in corso ipotizzato per 500000 euro quindi 2025
B104: ammto straordinario | J104: 85429.81
B105: check | C105: =C98 -> 336024 | D105: =D98 -> 302043 | E105: =E98 -> 258024 | F105: =SUM(F98:F102) -> 1801043 | G105: =SUM(G98:G104) -> 2232169 | H105: =SUM(H98:H102) -> 2352511 | I105: =SUM(I98:I102) -> 2137598 | J105: 1774810 | M105: =SUM(M98:M103) -> 1796211.7 | N105: =SUM(N98:N102) -> 991097.55 | O105: =SUM(O98:O102) -> 645408.59
B107: Attrez. industriale 1 | C107: 133231 | D107: =C107-K107 -> 121240.21 | E107: =D107-K107 -> 109249.42 | F107: =E107-K107 -> 97258.63 | G107: =F107-K107 -> 85267.84 | H107: =G107-K107 -> 73277.05 | I107: =H107-K107 -> 61286.26 | J107: =I107-K107 -> 49295.47 | K107: =L107*C107 -> 11990.79 | L107: 0.09 | M107: =J107-K107 -> 37304.68 | N107: =M107-K107 -> 25313.89 | O107: =N107-K107 -> 13323.1 | Q107: =K107 -> 11990.79 | R107: =Q107 -> 11990.79 | S107: =R107 -> 11990.79 | U107: =C107 -> 133231
B108: ammto straordinario | E108: -5518.85
B109: Attrez. industriale 2 | D109: =130147-D107 -> 8906.79 | E109: =D109-K109 -> 7125.432 | F109: =E109-K109 -> 5344.074 | G109: =F109-K109 -> 3562.716 | H109: =G109-K109 -> 1781.358 | I109: =H109-K109 -> 0 | J109: 0 | K109: =L109*D109 -> 1781.358 | L109: 0.2 | M109: 0 | N109: 0 | O109: 0 | Q109: 0 | R109: 0 | S109: 0 | U109: =D109 -> 8906.79
B110: Attrez. industriale 3 | F110: =141111-SUM(F107:F109) -> 38508.296 | G110: =F110-$K$110 -> 35042.549 | H110: =G110-$K$110 -> 31576.803 | I110: =H110-$K$110 -> 28111.056 | J110: =I110-$K$110 -> 24645.309 | K110: =L110*F110 -> 3465.7466 | L110: 0.09 | M110: =J110-K110 -> 21179.563 | N110: =M110-K110 -> 17713.816 | O110: =N110-K110 -> 14248.07 | Q110: =K110 -> 3465.7466 | R110: =Q110 -> 3465.7466 | S110: =R110 -> 3465.7466 | U110: =F110 -> 38508.296
B111: Attrez. industriale 4 | G111: =168289-SUM(G107:G110) -> 44415.895 | H111: =G111-K111 -> 40418.464 | I111: =H111-K111 -> 36421.034 | J111: =I111-K111 -> 32423.603 | K111: =L111*G111 -> 3997.4305 | L111: 0.09 | M111: =J111-K111 -> 28426.173 | N111: =M111-K111 -> 24428.742 | O111: =N111-K111 -> 20431.312 | Q111: =K111 -> 3997.4305 | R111: =Q111 -> 3997.4305 | S111: =R111 -> 3997.4305 | U111: =G111 -> 44415.895
B112: Attrez. industriale 5 | H112: =184756-SUM(H107:H111) -> 37702.325 | I112: =H112-K112 -> 34309.116 | J112: =I112-K112 -> 30915.907 | K112: =H112*L112 -> 3393.2093 | L112: 0.09 | M112: =J112-K112 -> 27522.697 | N112: =M112-K112 -> 24129.488 | O112: =N112-K112 -> 20736.279 | Q112: =K112 -> 3393.2093 | R112: =Q112 -> 3393.2093 | S112: =R112 -> 3393.2093 | U112: =H112 -> 37702.325
B113: Attrez. industriale 6 | I113: =187192-SUM(I107:I112) -> 27064.534 | J113: =I113-K113 -> 24628.726 | K113: =L113*I113 -> 2435.8081 | L113: 0.09 | M113: =J113-K113 -> 22192.918 | N113: =M113-K113 -> 19757.11 | O113: =N113-K113 -> 17321.302 | Q113: =K113 -> 2435.8081 | R113: =Q113 -> 2435.8081 | S113: =R113 -> 2435.8081 | U113: =I113 -> 27064.534
B114: Attrez. industriale 7 | J114: =197170-SUM(J107:J113) -> 35260.985 | K114: =J114*L114 -> 3173.4886 | L114: 0.09 | M114: =J114-K114 -> 32087.496 | N114: =M114-K114 -> 28914.007 | O114: =N114-K114 -> 25740.519 | Q114: =K114 -> 3173.4886 | R114: =Q114 -> 3173.4886 | S114: =R114 -> 3173.4886 | U114: =J114 -> 35260.985
B115: check | C115: =SUM(C107:C114) -> 133231 | D115: =SUM(D107:D114) -> 130147 | E115: =SUM(E107:E114) -> 110856 | F115: =SUM(F107:F114) -> 141111 | G115: =SUM(G107:G114) -> 168289 | H115: =SUM(H107:H114) -> 184756 | I115: =SUM(I107:I114) -> 187192 | J115: =SUM(J107:J114) -> 197170 | M115: =SUM(M107:M114) -> 168713.53 | N115: =SUM(N107:N114) -> 140257.05 | O115: =SUM(O107:O114) -> 111800.58
B117: Altri beni immobilizzati | C117: =97918-C118 -> 5527 | D117: 0 | E117: 0 | F117: 0 | G117: 0 | H117: 0 | I117: 0 | J117: 0 | K117: 5527 | L117: n.d | M117: 0 | N117: 0 | O117: 0 | Q117: 0 | R117: 0 | S117: 0 | U117: =C117 -> 5527
B118: Altri beni immobilizzati | C118: =D118+K118 -> 92391 | D118: 68843 | E118: 45295 | F118: =E118-K118 -> 21747 | G118: 0 | H118: 0 | I118: 0 | J118: 0 | K118: =D118-E118 -> 23548 | L118: 0.2 | M118: 0 | N118: 0 | O118: 0 | Q118: 0 | R118: 0 | S118: 0 | U118: =C118 -> 92391
B119: Altri beni immobilizzati | E119: =116965-E118 -> 71670 | F119: =E119-K119 -> 57336 | G119: =F119-K119 -> 43002 | H119: =G119-K119 -> 28668 | I119: =H119-K119 -> 14334 | J119: 0 | K119: =L119*E119 -> 14334 | L119: 0.2 | M119: 0 | N119: 0 | O119: 0 | Q119: 0 | R119: 0 | S119: 0 | U119: =E119 -> 71670
B120: Altri beni immobilizzati | F120: =236539-SUM(F117:F119) -> 157456 | G120: =F120-K120 -> 125964.8 | H120: =G120-K120 -> 94473.6 | I120: =H120-K120 -> 62982.4 | J120: =I120-K120 -> 31491.2 | K120: =L120*F120 -> 31491.2 | L120: 0.2 | M120: 0 | N120: 0 | O120: 0 | Q120: 0 | R120: 0 | S120: 0 | U120: =F120 -> 157456
B121: Altri beni immobilizzati | G121: =312178-SUM(G117:G120) -> 143211.2 | H121: =G121-K121 -> 121729.52 | I121: =H121-K121 -> 100247.84 | J121: =I121-K121 -> 78766.16 | K121: =L121*G121 -> 21481.68 | L121: 0.15 | M121: =J121-K121 -> 57284.48 | N121: =M121-K121 -> 35802.8 | O121: =N121-K121 -> 14321.12 | Q121: =K121 -> 21481.68 | R121: =Q121 -> 21481.68 | S121: =R121 -> 21481.68 | U121: =G121 -> 143211.2
B122: check | C122: =SUM(C117:C121) -> 97918 | D122: =SUM(D117:D121) -> 68843 | E122: =SUM(E117:E121) -> 116965 | F122: =SUM(F117:F121) -> 236539 | G122: =SUM(G117:G121) -> 312178 | H122: =SUM(H117:H121) -> 244871.12 | I122: =SUM(I117:I121) -> 177564.24 | J122: =SUM(J117:J121) -> 110257.36 | M122: =SUM(M117:M121) -> 57284.48 | N122: =SUM(N117:N121) -> 35802.8 | O122: =SUM(O117:O121) -> 14321.12
B124: =B60 -> B.II.5. Imm. in corso/acconti | C124: =J60 -> 0 | D124: =I60 -> 266650 | E124: =H60 -> 1767239 | F124: =G60 -> 4569586 | G124: =F60 -> 418529 | H124: =E60 -> 23700 | I124: =D60 -> 119891 | J124: =C60 -> 475770 | M124: =J124 -> 475770 | N124: =M124 -> 475770 | O124: =N124 -> 475770 | Q124: 0 | R124: 0 | S124: 0 | U124: 0
B126: Partecipazioni | G126: 58702 | H126: 58702 | I126: 58702 | J126: 58702 | M126: 58702 | N126: 58702 | O126: 58702 | Q126: 0 | R126: 0 | S126: 0 | U126: =G126 -> 58702
P127: Totale ammortamenti | Q127: =SUM(Q85:Q126) -> 799296.26 | R127: =SUM(R85:R126) -> 749688.49 | S127: =SUM(S85:S126) -> 730241.24
B128: https://www.agenziaentrate.gov.it/portale/documents/20143/1704562/Decreto+del+31_12_1988+-+Min.+Finanze+coefficienti+di+ammortamento.pdf/f7d5c11d-cc79-ecf7-efc8-f1fc90cc00a3#page=6.00
K131: proiezioni
B132: FDO AMMORTAMENTI | C132: 2017 | D132: 2018 | E132: 2019 | F132: 2020 | G132: 2021 | H132: 2022 | I132: 2023 | J132: 2024 | K132: 2025 | L132: 2026 | M132: 2027 | N132: aliquota | O132: RT ammortizzate | P132: RT rimanenti | Q132: fondo attuale - 2027
...

Sheet CCN
B2: Tabella 10A: Proiezione CCN operativo | F2: expand for details ↓
B4: Spiegazione: | C4: Calcolo delle varie voci del CCN operativo, utilizzando il foglio incidenze.
B6: CCN OPERATIVO | C6: 2024 | D6: 2025 | E6: 2026 | F6: 2027
B7: Rimanenze | C7: =incidenze!C55 -> 4608814 | D7: =incidenze!D55 -> 4634976.5 | E7: =incidenze!E55 -> 4798127.7 | F7: =incidenze!F55 -> 4967021.8
B8: var rim x-1 | C8: =-573471+141939 -> -431532
B9: Crediti verso clienti | C9: =incidenze!C47 -> 4256399 | D9: =incidenze!D47 -> 4446660 | E9: =incidenze!E47 -> 4645425.7 | F9: =incidenze!F47 -> 4853076.3
B10: Altri crediti | C10: =incidenze!C51 -> 757317 | D10: =incidenze!D51 -> 965508.85 | E10: =incidenze!E51 -> 1035131.8 | F10: =incidenze!F51 -> 1115356.2
B11: Ratei e risconti attivi | C11: 82949 | D11: =incidenze!D58*incidenze!D8 -> 89691.168 | E11: =incidenze!E58*incidenze!E8 -> 93700.363 | F11: =incidenze!F58*incidenze!F8 -> 97888.77
B12: Attivo circolante | C12: =C7+C9+C10+C11 -> 9705479 | D12: =SUM(D7:D11) -> 10136837 | E12: =SUM(E7:E11) -> 10572386 | F12: =SUM(F7:F11) -> 11033343
B13: var. | C13: 0 | D13: =D12-C12 -> 431357.57 | E13: =E12-D12 -> 435549 | F13: =F12-E12 -> 460957.46
B15: Debiti verso fornitori | C15: =incidenze!C62 -> 2274193 | D15: =incidenze!D62 -> 2372164.5 | E15: =incidenze!E62 -> 2455664.6 | F15: =incidenze!F62 -> 2542104
B16: Altri debiti | C16: =incidenze!C65 -> 1126361 | D16: =FONTI!C22 -> 1436005.7 | E16: =FONTI!D22 -> 1539556.2 | F16: =FONTI!E22 -> 1658874.4
B17: Ratei e risconti passivi | C17: =935845 -> 935845 | D17: =incidenze!D67*incidenze!D8 -> 977677.27 | E17: =incidenze!E67*incidenze!E8 -> 1021379.4 | F17: =incidenze!F67*incidenze!F8 -> 1067035.1
B18: Utilizzo fondo TFR | C18: 0 | D18: 0 | E18: 0 | F18: 0
B19: Fondo imposte | C19: 0 | D19: 0 | E19: 0 | F19: 0
B20: Passivo circolante | C20: =SUM(C15:C18) -> 4336399 | D20: =SUM(D15:D18) -> 4785847.4 | E20: =SUM(E15:E18) -> 5016600.3 | F20: =SUM(F15:F18) -> 5268013.5
B21: var. | C21: 0 | D21: =D20-C20 -> 449448.41 | E21: =E20-D20 -> 230752.87 | F21: =F20-E20 -> 251413.22
B23: CCN operativo | C23: =-C20+C12 -> 5369080 | D23: =-D20+D12 -> 5350989.2 | E23: =-E20+E12 -> 5555785.3 | F23: =-F20+F12 -> 5765329.5
B24: var. CCN operativo | C24: 0 | D24: =D23-C23 -> -18090.838 | E24: =E23-D23 -> 204796.13 | F24: =F23-E23 -> 209544.25
C28: Tabella 10B: Individuazione del fabbisogno finanziario a BT
C31: FABBISOGNO FINANZIARIO | D31: 2025 | E31: 2026 | F31: 2027
C32: =B23 -> CCN operativo | D32: =D23 -> 5350989.2 | E32: =E23 -> 5555785.3 | F32: =F23 -> 5765329.5
C33: Immobilizzazioni nette | D33: =INV!N42 -> 8072455.7 | E33: =INV!O42 -> 7288671.2 | F33: =INV!P42 -> 6557438
C35: Fabbisogno fin. | D35: =D32+D33-D34 -> 13423445 | E35: =SUM(E32:E33)-E34 -> 12844457 | F35: =SUM(F32:F33)-F34 -> 12322768
C39: Tabella 10C: Calcolo del volume operativo a BT
C42: VOLUME OPERATIVO | D42: 2025 | E42: 2026 | F42: 2027
C43: crediti commerciali | D43: =D9 -> 4446660 | E43: =E9 -> 4645425.7 | F43: =F9 -> 4853076.3
C44: debiti vs fornitori | D44: =D15 -> 2372164.5 | E44: =E15 -> 2455664.6 | F44: =F15 -> 2542104
C45: scorte | D45: =D7 -> 4634976.5 | E45: =E7 -> 4798127.7 | F45: =F7 -> 4967021.8
C49: Tabella 10D: Misura della durata del ciclo finanziario
C52: CICLO FINANZIARIO | D52: 2025 | E52: 2026 | F52: 2027
C53: giorni medi di permanenza delle scorte in magazzino | D53: =incidenze!D54 -> 111.17593 | E53: =incidenze!E54 -> 111.17593 | F53: =incidenze!F54 -> 111.17593
C54: giorni medi di pagamento dei fornitori | D54: =incidenze!D64 -> 46 | E54: =incidenze!E64 -> 46 | F54: =incidenze!F64 -> 46
C55: giorni medi di incasso clienti | D55: =incidenze!D49 -> 58.517654 | E55: =incidenze!E49 -> 58.517654 | F55: =incidenze!F49 -> 58.517654
C56: ciclo finanziario | D56: =D55-(D54-D53) -> 123.69358 | E56: =E55-(E54-E53) -> 123.69358 | F56: =F55-(F54-F53) -> 123.69358
C58: Dettagli sulla durata del ciclo finanziario | F58: expand for details ↓
F59: +
C61: gg medi di pagamento dei fornitori
C62: gg medi permanenza in magazzino
E63: ciclo finanziario
C65: A | D65: V | E65: pagamento | F65: incasso
E66: fornitori | F66: crediti clienti
D67: gg medi di incasso crediti
C70: Nel nostro caso, indica che il tempo in cui l'azienda finanzia l'attività operative con risorse proprie.
C71: permanenza in magazzino di 111 giorni
C72: pagamento dei fornitori dopo 46 giorni di acquisto, quindi paga i fornitori ancora con permanenza delle scorte in magazzino
C73: incassa i crediti dei clienti dopo 59 giorni dalla vendita.
C74: Si vende a fine permanenza media in magazzino
C75: Quindi l'intervallo che dura dal pagamento dei debiti vs fornitori all'incasso di crediti dei clienti dura 124 giorni
C77: Ci sono 65 giorni di permanenza media in magazzino dopo che i fornitori sono stati pagati e non si ha ancora venduto.

Sheet FONTI
B2: Tabella 8: Proiezione di attività correnti
B4: PROIEZIONE ATT. CORRENTE | C4: 2023 | D4: 2024 | E4: 2025 | F4: 2026 | G4: 2027
B5: Disponibilità liquide | C5: =SUM(C6:C8) -> 891542 | D5: =SUM(D6:D8) -> 242430 | E5: =SUM(E6:E8) -> 184573.18 | F5: =SUM(F6:F8) -> 33419.72 | G5: =SUM(G6:G8) -> 40280.87 | L5: dipende dal tipo di gestione cassa | O5: analisi liquidità | P5: 2024 quick ratio | Q5: =(D5+4256399)/D60 -> 1.325019
B6: Depositi bancari | C6: 891422 | D6: 241919 | E6: =182756.83+21.36 -> 182778.19 | F6: =R43-55.04+20.74 -> 25516.72 | G6: =S43-0.25+20.1 -> 25570.87 | P6: (disp.liq+crediti bt)/debiti imm | R6: -> utilizziamo questo indice come obbiettivo, cerchiamo diavere una capacità sufficiente di ripagare i debiti immediati
B7: Assegni | C7: 0 | D7: 0 | E7: 1700 | F7: 7000 | G7: 14000 | R7: dipende molto dai crediti però
B8: Cassa | C8: 120 | D8: 511 | E8: 94.99 | F8: 903 | G8: 710 | P8: 2024 liq. Imm | Q8: =D5/D60 -> 0.07140177 | R8: -> nel 2024 con le sole disponibilità liquide si sarebbe potuto coprire il 7% di passività
B12: Tabella 8A: Fabbisogno finanziario
B14: FABBISOGNO FINANZIARIO | C14: 2025 | D14: 2026 | E14: 2027
B15: FF netto | C15: =CCN!D35 -> 13423445 | D15: =CCN!E35 -> 12844457 | E15: =CCN!F35 -> 12322768
B16: Debiti v/terzi BT | C16: =G73 -> 2417759.7 | D16: =H73 -> 1349773.2 | E16: =I73 -> 228946.52
B17: Debiti v/terzi ML | C17: =G74 -> 3638932.4 | D17: =H74 -> 2031522.6 | E17: =I74 -> 344583.83
B18: Riserve patrimoniali | C18: =BP!D63 -> 5617287 | D18: =BP!E63 -> 7141058.9 | E18: =BP!F63 -> 8998219.3
B19: check altri debiti | C19: =C15-(C16+C17+C18+C22)-C20-C21 -> 0.0034313193 | D19: =D15-(D16+D17+D18+D22)-D20-D21 -> -0.0044050174 | E19: =E15-(E16+E17+E18+E22)-E20-E21 -> 0.00030418835
B20: Proventi | C20: =C32 -> 129438 | D20: =D32 -> 129438 | E20: =E32 -> 129438
B21: eccesso prov. | C21: 184022.04 | D21: 653107.64 | E21: 962705.51
B22: Altri debiti | C22: =1436005.68 -> 1436005.7 | D22: =1539556.19 -> 1539556.2 | E22: =1658874.35 -> 1658874.4
B26: Tabella 8B: Proventi | G26: expand for details ↓
B27: Spiegazione: | C27: L'impianto fotovoltaico maturato nel 2025 produce energia elettrica. Son disponibili vari approcci ma principalmente c'è ne sono 2: -considerare un valore, ricavo finanziario il saldo tra il consumo di energia elettrica e la produzione (produzione capacità produttiva molto superiore al consumo, anche se considerato capacità produttiva solo giornaliera e in presenza di sole) -considerare il costo di consumo di energia seprato dal ricavo di produzione, provente di vendita extra caratteristico. Nel nostro caso si segue il secondo approccio: capacità produttiva: 399,5 kWP ricavo potenziale a prezzo medio di mercato per zona: 129.438 euro a 0,27 euro kwh rivalutato rispetto a giorni soleggiati annuali per zona e ore solari di produzione:
B31: ALTRI PROVENTI | C31: 2025 | D31: 2026 | E31: 2027
B32: proventi di vendita capacità elettrica | C32: 129438 | D32: 129438 | E32: 129438
B38: Tabella 9: Proiezione finanziamenti
B40: PROIEZIONE INDEBITAMENTI | C40: 2023 | D40: 2024 | E40: 2025 | F40: 2026 | G40: 2027 | O40: LIQ. RICERCATA | P40: 2024 | Q40: 2025 | R40: 2026 | S40: 2027
B41: Debiti pregressi a breve | C41: =C60 -> 3987523 | D41: =D60 -> 3395294 | E41: =G73 -> 2417759.7 | F41: =H73 -> 1349773.2 | G41: =I73 -> 228946.52 | L41: -> ogni anno una parte di debiti a m/l viene traformato in bt, la parte a scadenza. Il debito a B7t può essere rimandato o versato. | O41: debiti v/banche entro | P41: =D60 -> 3395294 | Q41: =E60 -> 1953157.2 | R41: =F60 -> 255510.2 | S41: =G60 -> 255510.2
B42: interesse ipoteticamente noto | C42: =INV!D219+INV!D253+INV!D287+INV!D322+INV!D335 -> 121080.71 | D42: =INV!C348 -> 118261.19 | E42: =E41*E54 -> 109524.52 | F42: =#REF!*F54 -> #REF! | G42: =#REF!*G54 -> #REF! | O42: indice di liquidità immediata | P42: =Q8 -> 0.07140177 | Q42: 0.1 | R42: 0.1 | S42: 0.1
B43: Oneri finanziari BT | C43: =C42 -> 121080.71 | D43: =D42 -> 118261.19 | E43: =E41*E54 -> 109524.52 | F43: =F41*F54 -> 60739.795 | G43: =G41*G54 -> 11195.485 | O43: disponibilità liq. Immediate | P43: =P41*P42 -> 242430 | Q43: =Q41*Q42 -> 195315.72 | R43: =R41*R42 -> 25551.02 | S43: =S41*S42 -> 25551.02
B45: Debiti pregressi a medio/lungo | C45: =C61 -> 6691873 | D45: =D61 -> 5110204 | E45: =G74 -> 3638932.4 | F45: =H74 -> 2031522.6 | G45: =I74 -> 344583.83
B46: Oneri finanziari M/L | C46: =C47-C43 -> 407262.29 | D46: =503404-D43 -> 385142.81 | E46: =E45*E55 -> 160840.81 | F46: =F45*F55 -> 110921.14 | G46: =G45*G55 -> 17905.762
B47: Totale oneri di competenza | C47: 528343 | D47: =D46+D43 -> 503404 | E47: =E46+E43 -> 270365.33 | F47: =F46+F43 -> 171660.93 | G47: =G46+G43 -> 29101.247
B51: Tabella 9A: Rapporto di indebitamento
B53: RAPPORTO INDEBITAMENTO | C53: 2023 | D53: 2024 | E53: 2025 | F53: 2026 | G53: 2027
B54: Rapporto oneri/debito breve | C54: =C43/C41 -> 0.030364893 | D54: =D43/D41 -> 0.034830913 | E54: 0.0453 | F54: 0.045 | G54: 0.0489
B55: Rapporto oneri/debito medio/lungo | C55: =E78 -> 0.049473116 | D55: =F78 -> 0.059185717 | E55: 0.0442 | F55: =E55+0.0104 -> 0.0546 | G55: =_xlfn.FORECAST.LINEAR(G53,C55:F55,C53:F53) -> 0.051963442
E56: https://www.bancaria.it/news/pubblicato-il-rapporto-abi-di-settembre-2025/
B59: Analisi indebitamento | C59: 2023 | D59: 2024 | E59: 2025 | F59: 2026 | G59: 2027
B60: Banche entro | C60: =INV!C372 -> 3987523 | D60: =INV!D372 -> 3395294 | E60: =0.5*D60+0.05*D61 -> 1953157.2 | F60: =0.05*D61 -> 255510.2 | G60: =D61*0.05 -> 255510.2
B61: Banche oltre | C61: =INV!C371 -> 6691873 | D61: =INV!D371 -> 5110204 | E61: =0.9*D61 -> 4599183.6 | F61: =E61-F60 -> 4343673.4 | G61: =F61-G60 -> 4088163.2
B62: Altri fin entro | C62: 435 | D62: 435 | E62: =D62 -> 435 | F62: =E62 -> 435 | G62: =F62 -> 435
B63: Debiti tributari entro | C63: 135216 | D63: 235721 | E63: =TAX!D8+TAX!D12 -> 585090.24 | F63: =TAX!E8+TAX!E12 -> 700688.55 | G63: =TAX!F8+TAX!F12 -> 825126.81
B64: Istituti previdenza entro | C64: 86558 | D64: 70140 | E64: 0 | F64: 0 | G64: 0
B65: Altri debiti entro | C65: 669806 | D65: 820065 | E65: =INV!H190 -> 669806 | F65: =INV!I190 -> 519547 | G65: =INV!J190 -> 369288
B70: Tabella 9B: Analisi indebitamento
B72: ANALISI INDEBITAMENTO | C72: 2021 | D72: 2022 | E72: 2023 | F72: 2024 | G72: 2025 | H72: 2026 | I72: 2027
B73: Debiti pregressi a breve | C73: 3495062 | D73: 4519420 | E73: 3987523 | F73: 3395294 | G73: =G76*G75 -> 2417759.7 | H73: =H75*H76 -> 1349773.2 | I73: =I75*I76 -> 228946.52
B74: Debiti pregressi a medio/lungo | C74: 7333471 | D74: 6691933 | E74: 6691873 | F74: 5110204 | G74: =G75-G73 -> 3638932.4 | H74: =H75-H73 -> 2031522.6 | I74: =I75-I73 -> 344583.83
B75: Debiti totali | C75: =SUM(C73:C74) -> 10828533 | D75: =SUM(D73:D74) -> 11211353 | E75: =SUM(E73:E74) -> 10679396 | F75: =SUM(F73:F74) -> 8505498 | G75: =6056692.18 -> 6056692.2 | H75: =3381295.85 -> 3381295.9 | I75: =573530.35 -> 573530.35
B76: Rapporto debiti pregressi BT/TOT | C76: =C73/C75 -> 0.32276413 | D76: =D73/D75 -> 0.40311103 | E76: =E73/E75 -> 0.37338469 | F76: =F73/F75 -> 0.39918815 | G76: =F76 -> 0.39918815 | H76: =G76 -> 0.39918815 | I76: =H76 -> 0.39918815
B77: Rapporto oneri/debito breve | C77: =_xlfn.FORECAST.LINEAR(C72,D77:F77,D72:F72) -> 0.021432854 | D77: =_xlfn.FORECAST.LINEAR(D72,E77:F77,E72:F72) -> 0.025898873 | E77: =C43/E73 -> 0.030364893 | F77: =D43/F73 -> 0.034830913 | G77: =E54 -> 0.0453 | H77: =F54 -> 0.045 | I77: =G54 -> 0.0489
B78: Rapporto oneri/debito medio/lungo | C78: =C79/C75 -> 0.019153841 | D78: =D79/D75 -> 0.022626529 | E78: =E79/E75 -> 0.049473116 | F78: =F79/F75 -> 0.059185717 | G78: =E55 -> 0.0442 | H78: =F55 -> 0.0546 | I78: =G55 -> 0.051963442
B79: Totale oneri finanziari | C79: 207408 | D79: 253674 | E79: 528343 | F79: =D47 -> 503404 | G79: =E47 -> 270365.33 | H79: =F47 -> 171660.93 | I79: =G47 -> 29101.247

Sheet TAX
B2: Tabella 18A: Simulazione imposizione fiscale
B4: IMPOSTE | C4: 2024 | D4: 2025 | E4: 2026 | F4: 2027
B5: Aliquota media d'imposta IRES | C5: =incidenze!C36 -> 0.24 | D5: =incidenze!D36 -> 0.24 | E5: =incidenze!E36 -> 0.24 | F5: =incidenze!F36 -> 0.24
B6: utile ante-imposte | C6: =BP!C31 -> 1087201 | D6: =BP!D31 -> 2108862.1 | E6: =BP!E31 -> 2557849 | F6: =BP!F31 -> 3041515.9
B7: Imponibile IRES (utile+costi non deducibili-redditi non imponibili) | C7: =incidenze!C38 -> 1087201 | D7: =incidenze!D38 -> 2108862.1 | E7: =incidenze!E38 -> 2557849 | F7: =incidenze!F38 -> 3041515.9
B8: IRES | C8: =incidenze!C39 -> 260928.24 | D8: =incidenze!D39 -> 506126.91 | E8: =incidenze!E39 -> 613883.76 | F8: =incidenze!F39 -> 729963.81
B10: Aliquota media d'imposta IRAP | C10: =incidenze!C41 -> 0.0268 | D10: =incidenze!D41 -> 0.0268 | E10: =incidenze!E41 -> 0.0268 | F10: =incidenze!F41 -> 0.0268
B11: Imponibile IRAP (A-B) | C11: =incidenze!C42 -> 2279854 | D11: =incidenze!D42 -> 2946393.1 | E11: =incidenze!E42 -> 3238984.5 | F11: =incidenze!F42 -> 3550858.2
B12: IRAP | C12: =incidenze!C43 -> 61100.087 | D12: =incidenze!D43 -> 78963.336 | E12: =incidenze!E43 -> 86804.785 | F12: =incidenze!F43 -> 95163
B16: Tabella 18B: Struttura acconti Irpef per conto dipendenti
D18: RAL | G18: RAL a netto di contributi previdenziali | J18: acconto individuale | M18: acconto totale
B19: CALCOLO ACCONTI IRPEF PER CONTO DIPENDENTI | C19: figure | D19: 2025 | E19: 2026 | F19: 2027 | G19: 2025 | H19: 2026 | I19: 2027 | J19: 2025 | K19: 2026 | L19: 2027 | M19: 2025 | N19: 2026 | O19: 2027
B20: Responsabile di pianificazione | C20: 1 | D20: =HR!F129 -> 39840 | E20: =HR!K129 -> 40812 | F20: =HR!P129 -> 41412 | G20: =D20*0.9081 -> 36178.704 | H20: =E20*0.9081 -> 37061.377 | I20: =F20*0.9081 -> 37606.237 | J20: =IF(G20<28000, G20*$C$39, IF(G20<50000, ((6440+G20-28000)*$C$40), (6440+7700+(G20-50000)*$C$41))) -> 5116.5464 | K20: =IF(H20<28000, H20*$D$39, IF(H20<50000, ((6440+H20-28000)*$D$40), (6440+7700+(H20-50000)*$D$41))) -> 5115.4545 | L20: =IF(I20<28000, I20*$E$39, IF(I20<50000, ((6440+I20-28000)*$E$40), (6440+7700+(I20-50000)*$E$41))) -> 5295.2583 | M20: =J20*$C20 -> 5116.5464 | N20: =K20*$C20 -> 5115.4545 | O20: =L20*$C20 -> 5295.2583
B21: Responsabile alimentare | C21: 1 | D21: =HR!H129 -> 27780 | E21: =HR!M129 -> 28548 | F21: =HR!R129 -> 29040 | G21: =D21*0.9081 -> 25227.018 | H21: =E21*0.9081 -> 25924.439 | I21: =F21*0.9081 -> 26371.224 | J21: =IF(G21<28000, G21*$C$39, IF(G21<50000, ((6440+G21-28000)*$C$40), (6440+7700+(G21-50000)*$C$41))) -> 5802.2141 | K21: =IF(H21<28000, H21*$D$39, IF(H21<50000, ((6440+H21-28000)*$D$40), (6440+7700+(H21-50000)*$D$41))) -> 5962.6209 | L21: =IF(I21<28000, I21*$E$39, IF(I21<50000, ((6440+I21-28000)*$E$40), (6440+7700+(I21-50000)*$E$41))) -> 6065.3815 | M21: =J21*$C21 -> 5802.2141 | N21: =K21*$C21 -> 5962.6209 | O21: =L21*$C21 -> 6065.3815
B22: Operaio | C22: 11 | D22: =HR!E173 -> 22536 | E22: =HR!J173 -> 23100 | F22: =HR!O173 -> 23484 | G22: =D22*0.9081 -> 20464.942 | H22: =E22*0.9081 -> 20977.11 | I22: =F22*0.9081 -> 21325.82 | J22: =IF(G22<28000, G22*$C$39, IF(G22<50000, ((6440+G22-28000)*$C$40), (6440+7700+(G22-50000)*$C$41))) -> 4706.9366 | K22: =IF(H22<28000, H22*$D$39, IF(H22<50000, ((6440+H22-28000)*$D$40), (6440+7700+(H22-50000)*$D$41))) -> 4824.7353 | L22: =IF(I22<28000, I22*$E$39, IF(I22<50000, ((6440+I22-28000)*$E$40), (6440+7700+(I22-50000)*$E$41))) -> 4904.9387 | M22: =J22*$C22 -> 51776.302 | N22: =K22*$C22 -> 53072.088 | O22: =L22*$C22 -> 53954.326
B23: Operai con uso di strumenti tecnici | C23: 5 | D23: =HR!G173 -> 25536 | E23: =HR!L173 -> 26208 | F23: =HR!Q173 -> 26664 | G23: =D23*0.9081 -> 23189.242 | H23: =E23*0.9081 -> 23799.485 | I23: =F23*0.9081 -> 24213.578 | J23: =IF(G23<28000, G23*$C$39, IF(G23<50000, ((6440+G23-28000)*$C$40), (6440+7700+(G23-50000)*$C$41))) -> 5333.5256 | K23: =IF(H23<28000, H23*$D$39, IF(H23<50000, ((6440+H23-28000)*$D$40), (6440+7700+(H23-50000)*$D$41))) -> 5473.8815 | L23: =IF(I23<28000, I23*$E$39, IF(I23<50000, ((6440+I23-28000)*$E$40), (6440+7700+(I23-50000)*$E$41))) -> 5569.123 | M23: =J23*$C23 -> 26667.628 | N23: =K23*$C23 -> 27369.408 | O23: =L23*$C23 -> 27845.615
B24: Addetto al magazzino | C24: 4 | D24: =HR!E217 -> 22296 | E24: =HR!J217 -> 22752 | F24: =HR!O217 -> 26664 | G24: =D24*0.9081 -> 20246.998 | H24: =E24*0.9081 -> 20661.091 | I24: =F24*0.9081 -> 24213.578 | J24: =IF(G24<28000, G24*$C$39, IF(G24<50000, ((6440+G24-28000)*$C$40), (6440+7700+(G24-50000)*$C$41))) -> 4656.8094 | K24: =IF(H24<28000, H24*$D$39, IF(H24<50000, ((6440+H24-28000)*$D$40), (6440+7700+(H24-50000)*$D$41))) -> 4752.051 | L24: =IF(I24<28000, I24*$E$39, IF(I24<50000, ((6440+I24-28000)*$E$40), (6440+7700+(I24-50000)*$E$41))) -> 5569.123 | M24: =J24*$C24 -> 18627.238 | N24: =K24*$C24 -> 19008.204 | O24: =L24*$C24 -> 22276.492
B25: Camionisti | C25: 2 | D25: =HR!G217 -> 23028 | E25: =HR!L217 -> 23496 | F25: =HR!Q217 -> 29040 | G25: =D25*0.9081 -> 20911.727 | H25: =E25*0.9081 -> 21336.718 | I25: =F25*0.9081 -> 26371.224 | J25: =IF(G25<28000, G25*$C$39, IF(G25<50000, ((6440+G25-28000)*$C$40), (6440+7700+(G25-50000)*$C$41))) -> 4809.6972 | K25: =IF(H25<28000, H25*$D$39, IF(H25<50000, ((6440+H25-28000)*$D$40), (6440+7700+(H25-50000)*$D$41))) -> 4907.445 | L25: =IF(I25<28000, I25*$E$39, IF(I25<50000, ((6440+I25-28000)*$E$40), (6440+7700+(I25-50000)*$E$41))) -> 6065.3815 | M25: =J25*$C25 -> 9619.3943 | N25: =K25*$C25 -> 9814.8901 | O25: =L25*$C25 -> 12130.763
B26: Impiegato tecnico | C26: 2 | D26: =HR!E261 -> 25536 | E26: =HR!H261 -> 26208 | F26: =HR!K261 -> 26664 | G26: =D26*0.9081 -> 23189.242 | H26: =E26*0.9081 -> 23799.485 | I26: =F26*0.9081 -> 24213.578 | J26: =IF(G26<28000, G26*$C$39, IF(G26<50000, ((6440+G26-28000)*$C$40), (6440+7700+(G26-50000)*$C$41))) -> 5333.5256 | K26: =IF(H26<28000, H26*$D$39, IF(H26<50000, ((6440+H26-28000)*$D$40), (6440+7700+(H26-50000)*$D$41))) -> 5473.8815 | L26: =IF(I26<28000, I26*$E$39, IF(I26<50000, ((6440+I26-28000)*$E$40), (6440+7700+(I26-50000)*$E$41))) -> 5569.123 | M26: =J26*$C26 -> 10667.051 | N26: =K26*$C26 -> 10947.763 | O26: =L26*$C26 -> 11138.246
B27: Impiegato tecnico-informatico | C27: 1 | D27: =HR!E305 -> 27780 | E27: =HR!H305 -> 28548 | F27: =HR!K305 -> 29040 | G27: =D27*0.9081 -> 25227.018 | H27: =E27*0.9081 -> 25924.439 | I27: =F27*0.9081 -> 26371.224 | J27: =IF(G27<28000, G27*$C$39, IF(G27<50000, ((6440+G27-28000)*$C$40), (6440+7700+(G27-50000)*$C$41))) -> 5802.2141 | K27: =IF(H27<28000, H27*$D$39, IF(H27<50000, ((6440+H27-28000)*$D$40), (6440+7700+(H27-50000)*$D$41))) -> 5962.6209 | L27: =IF(I27<28000, I27*$E$39, IF(I27<50000, ((6440+I27-28000)*$E$40), (6440+7700+(I27-50000)*$E$41))) -> 6065.3815 | M27: =J27*$C27 -> 5802.2141 | N27: =K27*$C27 -> 5962.6209 | O27: =L27*$C27 -> 6065.3815
B28: Impiegato amministrativo-contabile | C28: 2 | D28: =HR!E349 -> 24036 | E28: =HR!H349 -> 24660 | F28: =HR!K349 -> 25080 | G28: =D28*0.9081 -> 21827.092 | H28: =E28*0.9081 -> 22393.746 | I28: =F28*0.9081 -> 22775.148 | J28: =IF(G28<28000, G28*$C$39, IF(G28<50000, ((6440+G28-28000)*$C$40), (6440+7700+(G28-50000)*$C$41))) -> 5020.2311 | K28: =IF(H28<28000, H28*$D$39, IF(H28<50000, ((6440+H28-28000)*$D$40), (6440+7700+(H28-50000)*$D$41))) -> 5150.5616 | L28: =IF(I28<28000, I28*$E$39, IF(I28<50000, ((6440+I28-28000)*$E$40), (6440+7700+(I28-50000)*$E$41))) -> 5238.284 | M28: =J28*$C28 -> 10040.462 | N28: =K28*$C28 -> 10301.123 | O28: =L28*$C28 -> 10476.568
B29: Agente commerciale | C29: 1 | D29: =HR!E393 -> 25536 | E29: =HR!J393 -> 26208 | F29: =HR!O393 -> 26664 | G29: =D29*0.9081 -> 23189.242 | H29: =E29*0.9081 -> 23799.485 | I29: =F29*0.9081 -> 24213.578 | J29: =IF(G29<28000, G29*$C$39, IF(G29<50000, ((6440+G29-28000)*$C$40), (6440+7700+(G29-50000)*$C$41))) -> 5333.5256 | K29: =IF(H29<28000, H29*$D$39, IF(H29<50000, ((6440+H29-28000)*$D$40), (6440+7700+(H29-50000)*$D$41))) -> 5473.8815 | L29: =IF(I29<28000, I29*$E$39, IF(I29<50000, ((6440+I29-28000)*$E$40), (6440+7700+(I29-50000)*$E$41))) -> 5569.123 | M29: =J29*$C29 -> 5333.5256 | N29: =K29*$C29 -> 5473.8815 | O29: =L29*$C29 -> 5569.123
B30: Responsabile commerciale | C30: 1 | D30: =HR!G393 -> 30780 | E30: =HR!L393 -> 31656 | F30: =HR!Q393 -> 32220 | G30: =D30*0.9081 -> 27951.318 | H30: =E30*0.9081 -> 28746.814 | I30: =F30*0.9081 -> 29258.982 | J30: =IF(G30<28000, G30*$C$39, IF(G30<50000, ((6440+G30-28000)*$C$40), (6440+7700+(G30-50000)*$C$41))) -> 6428.8031 | K30: =IF(H30<28000, H30*$D$39, IF(H30<50000, ((6440+H30-28000)*$D$40), (6440+7700+(H30-50000)*$D$41))) -> 2371.6485 | L30: =IF(I30<28000, I30*$E$39, IF(I30<50000, ((6440+I30-28000)*$E$40), (6440+7700+(I30-50000)*$E$41))) -> 2540.6641 | M30: =J30*$C30 -> 6428.8031 | N30: =K30*$C30 -> 2371.6485 | O30: =L30*$C30 -> 2540.6641
B31: Responsabile finanziario | C31: 1 | D31: =HR!E437 -> 39840 | E31: =HR!H437 -> 40812 | F31: =HR!K437 -> 41412 | G31: =D31*0.9081 -> 36178.704 | H31: =E31*0.9081 -> 37061.377 | I31: =F31*0.9081 -> 37606.237 | J31: =IF(G31<28000, G31*$C$39, IF(G31<50000, ((6440+G31-28000)*$C$40), (6440+7700+(G31-50000)*$C$41))) -> 5116.5464 | K31: =IF(H31<28000, H31*$D$39, IF(H31<50000, ((6440+H31-28000)*$D$40), (6440+7700+(H31-50000)*$D$41))) -> 5115.4545 | L31: =IF(I31<28000, I31*$E$39, IF(I31<50000, ((6440+I31-28000)*$E$40), (6440+7700+(I31-50000)*$E$41))) -> 5295.2583 | M31: =J31*$C31 -> 5116.5464 | N31: =K31*$C31 -> 5115.4545 | O31: =L31*$C31 -> 5295.2583
B32: Responsabile esecutivo | C32: 1 | D32: =HR!E481 -> 40548 | E32: =HR!H481 -> 41748 | F32: =HR!K481 -> 42540 | G32: =D32*0.9081 -> 36821.639 | H32: =E32*0.9081 -> 37911.359 | I32: =F32*0.9081 -> 38630.574 | J32: =IF(G32<28000, G32*$C$39, IF(G32<50000, ((6440+G32-28000)*$C$40), (6440+7700+(G32-50000)*$C$41))) -> 5341.5736 | K32: =IF(H32<28000, H32*$D$39, IF(H32<50000, ((6440+H32-28000)*$D$40), (6440+7700+(H32-50000)*$D$41))) -> 5395.9484 | L32: =IF(I32<28000, I32*$E$39, IF(I32<50000, ((6440+I32-28000)*$E$40), (6440+7700+(I32-50000)*$E$41))) -> 5633.2894 | M32: =J32*$C32 -> 5341.5736 | N32: =K32*$C32 -> 5395.9484 | O32: =L32*$C32 -> 5633.2894
L33: TOTALE: | M33: =SUM(M20:M32) -> 166339.5 | N33: =SUM(N20:N32) -> 165911.11 | O33: =SUM(O20:O32) -> 174286.37
B36: Tabella 18C: Aliquote irpef effettive
B38: ALIQUOTE IRPEF | C38: 2025 | D38: 2026 | E38: 2027
B39: fino 28000 | C39: 0.23 | D39: 0.23 | E39: 0.23
B40: da 28.001 a 50.000 | C40: 0.35 | D40: 0.33 | E40: 0.33
B41: oltre 50.0000 | C41: 0.43 | D41: 0.43 | E41: 0.43
B45: Tabella 18D: Debiti verso l'erario a chiusura del bilancio
B47: IMPOSTE A CHIUSURA DEL BILANCIO | C47: 2024 | D47: 2025 | E47: 2026 | F47: 2027
B48: Erario c/IVA | C48: =(BP!C6*0.22*1/12)-('COSTI DI GESTIONE & BEP'!D11+'COSTI DI GESTIONE & BEP'!D43+'COSTI DI GESTIONE & BEP'!D39)*(1/12)*0.22 -> 71672.81 | D48: =(BP!D6*0.22*1/12)-('COSTI DI GESTIONE & BEP'!E11+'COSTI DI GESTIONE & BEP'!E43+'COSTI DI GESTIONE & BEP'!E39)*(1/12)*0.22 -> 85854.286 | E48: =(BP!E6*0.22*1/12)-('COSTI DI GESTIONE & BEP'!F11+'COSTI DI GESTIONE & BEP'!F43+'COSTI DI GESTIONE & BEP'!F39)*(1/12)*0.22 -> 92045.246 | F48: =(BP!F6*0.22*1/12)-('COSTI DI GESTIONE & BEP'!G11+'COSTI DI GESTIONE & BEP'!G43+'COSTI DI GESTIONE & BEP'!G39)*(1/12)*0.22 -> 99178.905
B49: Debito: Acconto IRPEF per conto dipendenti | D49: =1/12*M33 -> 13861.625 | E49: =1/12*N33 -> 13825.925 | F49: =1/12*O33 -> 14523.864
D51: Si tratta del pagamento dell'ultima mensilità

Sheet incidenze
B2: Tabella 11: Ipotesi e incidenze previsionali | H2: expand for details ↓
H3: +
B4: Spiegazione: | C4: Individuate varie voci di costi rispetto al bilancio consuntivo del 2024. Ciascuna voce ha avuto progressione di crescita/diminuzione o stabilità rispetto ai fattori presi in considerazione, visibile espandendo il banner laterale alla destra della tabella.
B6: IPOTESI PREVISIONALI | C6: 2024 | D6: 2025 | E6: 2026 | F6: 2027 | H6: Benchmark di settore
B7: CONTO ECONOMICO
B8: Ricavi | C8: ='REVENUE MODEL'!S34 -> 21463379 | D8: ='REVENUE MODEL'!J34 -> 22422792 | E8: ='REVENUE MODEL'!K34 -> 23425091 | F8: ='REVENUE MODEL'!L34 -> 24472192
B9: Costo del venduto / Ricavi | C9: ='COSTI DI GESTIONE & BEP'!D11/incidenze!C8 -> 0.70497413 | D9: ='COSTI DI GESTIONE & BEP'!E11/incidenze!D8 -> 0.67864076 | E9: ='COSTI DI GESTIONE & BEP'!F11/incidenze!E8 -> 0.67246953 | F9: ='COSTI DI GESTIONE & BEP'!G11/incidenze!F8 -> 0.66635442 | G9: → | H9: ='D. Benchmark di settore'!P15 -> 0.74703255
B10: Costi per servizi / Ricavi | C10: ='COSTI DI GESTIONE & BEP'!D39/incidenze!C8 -> 0.1128539 | D10: ='COSTI DI GESTIONE & BEP'!E39/incidenze!D8 -> 0.11248422 | E10: ='COSTI DI GESTIONE & BEP'!F39/incidenze!E8 -> 0.11317699 | F10: ='COSTI DI GESTIONE & BEP'!G39/incidenze!F8 -> 0.1125637 | G10: → | H10: ='D. Benchmark di settore'!Q15 -> 0.55114031
B11: Costo del lavoro / Ricavi | C11: ='COSTI DI GESTIONE & BEP'!D16/incidenze!C8 -> 0.069814636 | D11: ='COSTI DI GESTIONE & BEP'!E16/incidenze!D8 -> 0.071538588 | E11: ='COSTI DI GESTIONE & BEP'!F16/incidenze!E8 -> 0.070209541 | F11: ='COSTI DI GESTIONE & BEP'!G16/incidenze!F8 -> 0.070110474 | G11: → | H11: ='D. Benchmark di settore'!R15 -> 0.086370682
B12: Accantonamento TFR/Ricavi | C12: ='COSTI DI GESTIONE & BEP'!D15 -> 79658 | D12: ='COSTI DI GESTIONE & BEP'!E15 -> 78592.036 | E12: ='COSTI DI GESTIONE & BEP'!F15 -> 80579.747 | F12: ='COSTI DI GESTIONE & BEP'!G15 -> 84062.88
B13: Accantonamenti per rischi / Ricavi | C13: =C12/C8 -> 0.0037113448 | D13: =D12/D8 -> 0.0035050067 | E13: =E12/E8 -> 0.0034398905 | F13: =F12/F8 -> 0.0034350367 | G13: → | H13: ='D. Benchmark di settore'!S15 -> 0.00088948735
B14: Oneri diversi di gestione / ricavi | C14: ='COSTI DI GESTIONE & BEP'!D46/incidenze!C8 -> 0.0024253404 | D14: ='COSTI DI GESTIONE & BEP'!E46/incidenze!D8 -> 0.0024297154 | E14: ='COSTI DI GESTIONE & BEP'!F46/incidenze!E8 -> 0.0024341699 | F14: ='COSTI DI GESTIONE & BEP'!G46/incidenze!F8 -> 0.0024387018
B16: Ammortamento immobilizzazioni immateriali | C16: =INV!E26 -> 37282 | D16: =INV!F26 -> 36290 | E16: =INV!G26 -> 2194 | F16: =INV!H26 -> 2194
A17: extra CE | B17: Fondo ammortamento immobilizzazioni immateriali | C17: =INV!J137 -> 197250 | D17: =INV!K137 -> 99722 | E17: =INV!L137 -> 50958 | F17: =INV!M137 -> 53152
B18: Ammortamento immobilizzazioni materiali | C18: =INV!E27 -> 879520 | D18: =INV!F27 -> 763006.26 | E18: =INV!G27 -> 747494.49 | F18: =INV!H27 -> 728047.24
A19: extra CE | B19: Fondo ammortamento immobilizzazioni materiali | C19: =INV!J169 -> 1082927.4 | D19: =INV!K169 -> 1845936.3 | E19: =INV!L169 -> 2573986.1 | F19: =INV!M169 -> 3302036
B21: Costo medio dell'indebitamento finanz a M/L | C21: =FONTI!D55 -> 0.059185717 | D21: =FONTI!E55 -> 0.0442 | E21: =FONTI!F55 -> 0.0546 | F21: =FONTI!G55 -> 0.051963442 | G21: → | H21: ='D. Benchmark di settore'!X15 -> 0.0068905791
B22: Accensione e rimborso debiti finanziari | C22: =INV!C358+INV!C349 -> 452724.33 | D22: =-(FONTI!F75-FONTI!G75) -> -2448805.8 | E22: =-(FONTI!G75-FONTI!H75) -> -2675396.3 | F22: =-(FONTI!H75-FONTI!I75) -> -2807765.5
B23: Costo medio dell'indebitamento finanziario a breve | C23: =FONTI!D54 -> 0.034830913 | D23: =FONTI!E54 -> 0.0453 | E23: =FONTI!F54 -> 0.045 | F23: =FONTI!G54 -> 0.0489 | G23: → | H23: ='D. Benchmark di settore'!Y15 -> 0.020338064
B24: Valore medio annuo dell'esposizione fin a breve | C24: =AVERAGE(INV!C372:D372) -> 3691408.5 | D24: =FONTI!G73 -> 2417759.7 | E24: =FONTI!H73 -> 1349773.2 | F24: =FONTI!I73 -> 228946.52
B26: Proventi finanziari / Ricavi | C26: =1756/C8 -> 8.1813772e-05 | D26: 0.0001 | E26: 0.0001 | F26: 0.0001 | G26: → | H26: ='D. Benchmark di settore'!Z15 -> 0.0013724513
B27: Rettifiche attività finanziarie / Ricavi | C27: 0 | D27: 0 | E27: 0 | F27: 0
A29: extra CE | B29: Fondo TFR | C29: 191675 | D29: =C29+'COSTI DI GESTIONE & BEP'!E15 -> 270267.04 | E29: =D29+'COSTI DI GESTIONE & BEP'!F15 -> 350846.78 | F29: =E29+'COSTI DI GESTIONE & BEP'!G15 -> 434909.66
B30: Utilizzo fondo TFR | C30: =CCN!C18 -> 0 | D30: =CCN!D18 -> 0 | E30: =CCN!E18 -> 0 | F30: =CCN!F18 -> 0
B31: Utilizzo fondo rischi e oneri | C31: 0 | D31: 0 | E31: 0 | F31: 0
B33: Partite straordinarie / ricavi | C33: 0.013286585 | D33: =C33 -> 0.013286585 | E33: =D33 -> 0.013286585 | F33: =E33 -> 0.013286585
B35: IMPOSTE
B36: Aliquota media d'imposta IRES | C36: 0.24 | D36: 0.24 | E36: 0.24 | F36: 0.24
B37: utile ante-imposte | C37: =BP!C31 -> 1087201 | D37: =BP!D31 -> 2108862.1 | E37: =BP!E31 -> 2557849 | F37: =BP!F31 -> 3041515.9
B38: Imponibile IRES (utile+costi non deducibili-redditi non imponibili) | C38: =C37 -> 1087201 | D38: =D37 -> 2108862.1 | E38: =E37 -> 2557849 | F38: =F37 -> 3041515.9
B39: IRES | C39: =C38*C36 -> 260928.24 | D39: =D38*D36 -> 506126.91 | E39: =E38*E36 -> 613883.76 | F39: =F38*F36 -> 729963.81
B41: Aliquota media d'imposta IRAP | C41: 0.0268 | D41: 0.0268 | E41: 0.0268 | F41: 0.0268
B42: Imponibile IRAP (A-B) | C42: =C8-(C8*C9+C8*C10+C8*C11+C8*C14+C8*C13) -> 2279854 | D42: =D8-(D8*D9+D8*D10+D8*D11+D8*D14+D8*D13) -> 2946393.1 | E42: =E8-(E8*E9+E8*E10+E8*E11+E8*E14+E8*E13) -> 3238984.5 | F42: =F8-(F8*F9+F8*F10+F8*F11+F8*F14+F8*F13) -> 3550858.2
B43: IRAP | C43: =C42*C41 -> 61100.087 | D43: =D42*D41 -> 78963.336 | E43: =E42*E41 -> 86804.785 | F43: =F42*F41 -> 95163
B45: CREDITI
B46: Crediti vs clienti / fatturato | C46: =C47/C8 -> 0.19830983 | D46: =D47/D8 -> 0.19830983 | E46: =E47/E8 -> 0.19830983 | F46: =F47/F8 -> 0.19830983 | G46: → | H46: ='D. Benchmark di settore'!AA15 -> 0.13493917
B47: Crediti vs clienti | C47: 4256399 | D47: =D48*D49 -> 4446660 | E47: =E48*E49 -> 4645425.7 | F47: =F48*F49 -> 4853076.3
B48: Ricavi di vendita con IVA, giornalieri | C48: =(C8*1.22)/360 -> 72737.007 | D48: =(D8*1.22)/360 -> 75988.351 | E48: =(E8*1.22)/360 -> 79385.03 | F48: =(F8*1.22)/360 -> 82933.541
B49: Tempo medio di incasso da clienti [gg] | C49: =C47/C48 -> 58.517654 | D49: =C49 -> 58.517654 | E49: =D49 -> 58.517654 | F49: =E49 -> 58.517654 | G49: → | H49: ='D. Benchmark di settore'!O15 -> 40.371145
B50: Altri crediti / fatturato (inclusi crediti per iva non compensata) | C50: =C51/C8 -> 0.035284146 | D50: =D51/D8 -> 0.043059261 | E50: =E51/E8 -> 0.044189019 | F50: =F51/F8 -> 0.045576473 | G50: → | H50: ='D. Benchmark di settore'!AB15 -> 0.062559822
B51: Altri crediti | C51: =SUM(C52:C53) -> 757317 | D51: =SUM(D52:D53) -> 965508.85 | E51: =SUM(E52:E53) -> 1035131.8 | F51: =SUM(F52:F53) -> 1115356.2
B52: Crediti vs altri | C52: =120585+613458 -> 734043 | D52: =D53/(9.76%) -> 879654.57 | E52: =E53/(9.76%) -> 943086.54 | F52: =F53/(9.76%) -> 1016177.3
B53: Crediti tributari | C53: 23274 | D53: =TAX!D48 -> 85854.286 | E53: =TAX!E48 -> 92045.246 | F53: =TAX!F48 -> 99178.905
B54: gg rotazione mp | C54: =C55*365/(C9*C8) -> 111.17593 | D54: =C54 -> 111.17593 | E54: =D54 -> 111.17593 | F54: =E54 -> 111.17593
B55: Rimanenze | C55: 4608814 | D55: =D54*(D9*D8)/365 -> 4634976.5 | E55: =E54*(E9*E8)/365 -> 4798127.7 | F55: =F54*(F9*F8)/365 -> 4967021.8
B56: Rimanenze / Costo del venduto | C56: =C55/(C9*C8) -> 0.30459159 | D56: =D55/(D9*D8) -> 0.30459159 | E56: =E55/(E9*E8) -> 0.30459159 | F56: =F55/(F9*F8) -> 0.30459159 | G56: → | H56: ='D. Benchmark di settore'!AC15 -> 0.20416287
B57: Rimanenze/Ricavi | C57: =CCN!C7/BP!C6 -> 0.21472919 | D57: =C57 -> 0.21472919 | E57: =D57 -> 0.21472919 | F57: =E57 -> 0.21472919
B58: Ratei e risconti attivi/ fatturato | C58: =CCN!C11/incidenze!C8 -> 0.0038646757 | D58: 0.004 | E58: 0.004 | F58: 0.004 | G58: → | H58: ='D. Benchmark di settore'!AE15 -> 0.017561602
B60: DEBITI
B61: Debiti vs fornitori / costo del venduto | C61: =CCN!C15/'COSTI DI GESTIONE & BEP'!D11 -> 0.15029898 | D61: =C61 -> 0.15029898 | E61: =D61 -> 0.15029898 | F61: =E61 -> 0.15029898 | G61: → | H61: ='D. Benchmark di settore'!AD15 -> 0.19212397
B62: Debiti vs fornitori | C62: 2274193 | D62: =D63*D64 -> 2372164.5 | E62: =E63*E64 -> 2455664.6 | F62: =F63*F64 -> 2542104
B63: Acquisti con IVA giornaliera | C63: =1.22*('COSTI DI GESTIONE & BEP'!D9/360) -> 49815.294 | D63: =1.22*('COSTI DI GESTIONE & BEP'!E9/360) -> 51568.793 | E63: =1.22*('COSTI DI GESTIONE & BEP'!F9/360) -> 53384.014 | F63: =1.22*('COSTI DI GESTIONE & BEP'!G9/360) -> 55263.131
B64: Tempo medio di pagamento fornitori [gg] | C64: =C62/C63 -> 45.652506 | D64: 46 | E64: 46 | F64: 46
B65: Altri debiti | C65: =820065+70140+235721+435 -> 1126361 | D65: =CCN!D16 -> 1436005.7 | E65: =CCN!E16 -> 1539556.2 | F65: =CCN!F16 -> 1658874.4
B66: =TAX!B49 -> Debito: Acconto IRPEF per conto dipendenti | D66: =TAX!D49 -> 13861.625 | E66: =TAX!E49 -> 13825.925 | F66: =TAX!F49 -> 14523.864
B67: Ratei e risconti passivi/fatturato | C67: =CCN!C17/incidenze!C8 -> 0.043601942 | D67: =C67 -> 0.043601942 | E67: =D67 -> 0.043601942 | F67: =E67 -> 0.043601942 | G67: → | H67: ='D. Benchmark di settore'!AF15 -> 0.073580494
B69: CAPITALE SOCIALE
B70: Sottoscrizione, aumenti o riscatti capitale sociale | C70: 0 | D70: 0 | E70: 0 | F70: 0
B71: Utilizzo riserve | C71: 0 | D71: 0 | E71: 0 | F71: 0
B72: Dividendi distribuiti / utile netto | C72: 0 | D72: 0 | E72: 0 | F72: 0

Sheet main sheets →

Sheet BP
B2: Tabella 12: BP Conto economico previsionale | J2: Tabella 13A: Riclassificazione SP 2024
B4: CONTO ECONOMICO | C4: 2024 | D4: 2025 | E4: 2026 | F4: 2027 | J4: Impieghi | L4: Fonti
J5: Attivo circolante | K5: =SUM(K6:K9) -> 9705479 | L5: Passivo circolante | M5: =SUM(M6:M10) -> 4528074
B6: Ricavi | C6: =incidenze!C8 -> 21463379 | D6: =incidenze!D8 -> 22422792 | E6: =incidenze!E8 -> 23425091 | F6: =incidenze!F8 -> 24472192 | J6: Rimanenze | K6: =C48 -> 4608814 | L6: Debiti verso fornitori | M6: =C77 -> 2274193
B7: % di crescita ricavi | C7: n.d. | D7: =(D6-C6)/C6 -> 0.0447 | E7: =(E6-D6)/D6 -> 0.0447 | F7: =(F6-E6)/E6 -> 0.0447 | J7: Crediti verso clienti | K7: =C49 -> 4256399 | L7: Altri debiti | M7: =C78 -> 1126361
B8: (Costo del venduto) | C8: =-'COSTI DI GESTIONE & BEP'!D11 -> -15131127 | D8: =-'COSTI DI GESTIONE & BEP'!E11 -> -15217021 | E8: =-'COSTI DI GESTIONE & BEP'!F11 -> -15752660 | F8: =-'COSTI DI GESTIONE & BEP'!G11 -> -16307154 | J8: Altri crediti | K8: =C50 -> 757317 | L8: Ratei e risconti passivi | M8: =C79 -> 935845
B9: Valore aggiunto | C9: =C6+C8 -> 6332252 | D9: =D6+D8 -> 7205771.3 | E9: =E6+E8 -> 7672431 | F9: =F6+F8 -> 8165038.9 | J9: Ratei e risconti attivi | K9: =C52 -> 82949 | L9: Fondo TFR | M9: =C74 -> 191675
B10: % di crescita valore aggiunto | C10: =C7 -> n.d. | D10: =(D9-C9)/C9 -> 0.13794765 | E10: =(E9-D9)/D9 -> 0.064761932 | F10: =(F9-E9)/E9 -> 0.064204935 | L10: Fondo imposte | M10: 0
B11: (Costi per servizi) | C11: =-incidenze!C10*incidenze!C8 -> -2422226 | D11: =-incidenze!D10*incidenze!D8 -> -2522210.3 | E11: =-incidenze!E10*incidenze!E8 -> -2651181.2 | F11: =-incidenze!F10*incidenze!F8 -> -2754680.4
B12: (Godimento beni di terzi) | C12: =-'COSTI DI GESTIONE & BEP'!D41 -> -117380 | D12: =-'COSTI DI GESTIONE & BEP'!E41 -> -123249 | E12: =-'COSTI DI GESTIONE & BEP'!F41 -> -129411.45 | F12: =-'COSTI DI GESTIONE & BEP'!G41 -> -135882.02 | J12: Immobilizzazioni operative nette | K12: =SUM(K13:K14) -> 8784248 | L12: Debiti finanziari | M12: =SUM(M13:M14) -> 8505498
B13: (Totale costo del lavoro) | C13: =-C6*incidenze!C11 -> -1498458 | D13: =-D6*incidenze!D11 -> -1604094.9 | E13: =-E6*incidenze!E11 -> -1644664.9 | F13: =-F6*incidenze!F11 -> -1715757 | J13: Immobilizzazioni materiali | K13: =C44 -> 8694725 | L13: Finanziamenti a breve termine | M13: =C76 -> 3395294
B14: di cui: accantonamenti TFR | C14: ='COSTI DI GESTIONE & BEP'!D15 -> 79658 | D14: ='COSTI DI GESTIONE & BEP'!E15 -> 78592.036 | E14: ='COSTI DI GESTIONE & BEP'!F15 -> 80579.747 | F14: ='COSTI DI GESTIONE & BEP'!G15 -> 84062.88 | J14: Immobilizzazioni immateriali | K14: =C43 -> 89523 | L14: Altri finanziamenti a medio/lungo termine | M14: =C75 -> 5110204
B15: EBITDA | C15: =C9+SUM(C11:C13) -> 2294188 | D15: =D9+SUM(D11:D13) -> 2956217.2 | E15: =E9+SUM(E11:E13) -> 3247173.5 | F15: =F9+SUM(F11:F13) -> 3558719.4
B16: % di crescita EBITDA | D16: =(D15-C15)/D15 -> 0.2239447 | E16: =(E15-D15)/E15 -> 0.089602942 | F16: =(F15-E15)/F15 -> 0.087544408 | J16: Attivo di gestione patrimoniale | K16: =SUM(K17:K18) -> 301132 | L16: Mezzi propri | M16: =SUM(M17:M19) -> 5757287
J17: Liquidità patrimoniali | K17: =C51 -> 242430 | L17: Capitale sociale | M17: =C62 -> 140000
B18: Ammortamenti per immobilizzazioni immateriali | C18: =-incidenze!C16 -> -37282 | D18: =-incidenze!D16 -> -36290 | E18: =-incidenze!E16 -> -2194 | F18: =-incidenze!F16 -> -2194 | J18: Immobilizzazioni patrimoniali | K18: =C45 -> 58702 | L18: Riserve | M18: =C63 -> 4717554
B19: Ammortamenti per immobilizzazioni materiali | C19: =-incidenze!C18 -> -879520 | D19: =-incidenze!D18 -> -763006.26 | E19: =-incidenze!E18 -> -747494.49 | F19: =-incidenze!F18 -> -728047.24 | L19: Reddito netto | M19: =C67 -> 899733
B20: Accantonamenti per rischi | C20: ='COSTI DI GESTIONE & BEP'!D48 -> 0 | D20: ='COSTI DI GESTIONE & BEP'!E48 -> 0 | E20: ='COSTI DI GESTIONE & BEP'!F48 -> 0 | F20: ='COSTI DI GESTIONE & BEP'!G48 -> 0
B21: Oneri diversi di gestione | C21: =-'COSTI DI GESTIONE & BEP'!D46 -> -52056 | D21: =-'COSTI DI GESTIONE & BEP'!E46 -> -54481.004 | E21: =-'COSTI DI GESTIONE & BEP'!F46 -> -57020.652 | F21: =-'COSTI DI GESTIONE & BEP'!G46 -> -59680.381 | J21: Tot. Impieghi | K21: =K5+K12+K16 -> 18790859 | L21: Tot. Fonti | M21: =M5+M12+M16 -> 18790859
B22: EBIT | C22: =C15+SUM(C18:C21) -> 1325330 | D22: =D15+SUM(D18:D21) -> 2102439.9 | E22: =E15+SUM(E18:E21) -> 2440464.3 | F22: =F15+SUM(F18:F21) -> 2768797.8
B23: % di crescita ebitda | C23: =C10 -> n.d. | D23: =(D22-C22)/C22 -> 0.586352 | E23: =(E22-D22)/D22 -> 0.16077721 | F23: =(F22-E22)/E22 -> 0.13453731
B25: Oneri finanziari su debiti a medio lungo | C25: =-FONTI!D46 -> -385142.81 | D25: =-FONTI!E46 -> -160840.81 | E25: =-FONTI!F46 -> -110921.14 | F25: =-FONTI!G46 -> -17905.762 | J25: Tabella 13A: Riclassificazione SP 2025
B26: Oneri finanziari su debiti a breve | C26: =-FONTI!D43 -> -118261.19 | D26: =-FONTI!E43 -> -109524.52 | E26: =-FONTI!F43 -> -60739.795 | F26: =-FONTI!G43 -> -11195.485
B27: Proventi finanziari | C27: =incidenze!C26*incidenze!C8 -> 1756 | D27: =incidenze!D26*incidenze!D8 -> 2242.2792 | E27: =incidenze!E26*incidenze!E8 -> 2342.5091 | F27: =incidenze!F26*incidenze!F8 -> 2447.2192 | J27: Impieghi | L27: Fonti
B28: Rettifiche di valore attività finanziarie | C28: =incidenze!C27 -> 0 | D28: =incidenze!D27 -> 0 | E28: =incidenze!E27 -> 0 | F28: =incidenze!F27 -> 0 | J28: Attivo circolante | K28: =SUM(K29:K32) -> 10136837 | L28: Passivo circolante | M28: =SUM(M29:M33) -> 5056114.4
B29: Svalutazione crediti | C29: =-21656 -> -21656 | D29: =(C29/(CCN!C9+CCN!C10))*(CCN!D9+CCN!D10) -> -23377.058 | E29: =(C29/(CCN!C9+CCN!C10))*(CCN!E10+CCN!E9) -> -24536.323 | F29: =(C29/(CCN!C9+CCN!C10))*(CCN!F9+CCN!F10) -> -25779.756 | J29: Rimanenze | K29: =D48 -> 4634976.5 | L29: Debiti verso fornitori | M29: =D77 -> 2372164.5
B30: Partite straordinarie | C30: =incidenze!C33*incidenze!C8 -> 285175 | D30: =incidenze!D33*incidenze!D8 -> 297922.32 | E30: =incidenze!E33*incidenze!E8 -> 311239.45 | F30: =incidenze!F33*incidenze!F8 -> 325151.85 | J30: Crediti verso clienti | K30: =D49 -> 4446660 | L30: Altri debiti | M30: =D78 -> 1436005.7
B31: Utile ante-imposte | C31: =C22+SUM(C25:C30) -> 1087201 | D31: =D22+SUM(D25:D30) -> 2108862.1 | E31: =E22+SUM(E25:E30) -> 2557849 | F31: =F22+SUM(F25:F30) -> 3041515.9 | J31: Altri crediti | K31: =D50 -> 965508.85 | L31: Ratei e risconti passivi | M31: =D79 -> 977677.27
J32: Ratei e risconti attivi | K32: =D52 -> 89691.168 | L32: Fondo TFR | M32: =D74 -> 270267.04
B33: Imposte | C33: =-187468 -> -187468 | D33: =-(incidenze!D39+incidenze!D43) -> -585090.24 | E33: =-(incidenze!E39+incidenze!E43) -> -700688.55 | F33: =-(incidenze!F39+incidenze!F43) -> -825126.81 | L33: Fondo imposte | M33: 0
B34: Utile netto | C34: =C31+C33 -> 899733 | D34: =D31+D33 -> 1523771.9 | E34: =E31+E33 -> 1857160.5 | F34: =F31+F33 -> 2216389.1
B35: % di crescita utile netto | C35: =C23 -> n.d. | D35: =(D34-C34)/C34 -> 0.69358229 | E35: =(E34-D34)/D34 -> 0.21879168 | F35: =(F34-E34)/E34 -> 0.19342895 | J35: Immobilizzazioni operative nette | K35: =SUM(K36:K37) -> 8013753.7 | L35: Debiti finanziari | M35: =SUM(M36:M37) -> 6056692.2
J36: Immobilizzazioni materiali | K36: =D44 -> 7955926.7 | L36: Finanziamenti a breve termine | M36: =FONTI!G73 -> 2417759.7
D37: =D31 -> 2108862.1 | E37: =D22 -> 2102439.9 | J37: Immobilizzazioni immateriali | K37: =D43 -> 57827 | L37: Altri finanziamenti a medio/lungo termine | M37: =FONTI!G74 -> 3638932.4
D38: =D33 -> -585090.24 | E38: =E37*D38/D37 -> -583308.44 | F38: =D38-E38-6449.46 -> -8231.2619
B39: Tabella 13: BP Stato patrimoniale previsionale | J39: Attivo di gestione patrimoniale | K39: =SUM(K40:K41) -> 243275.18 | L39: Mezzi propri | M39: =SUM(M40:M42) -> 7281058.9
J40: Liquidità patrimoniali | K40: =D51 -> 184573.18 | L40: Capitale sociale | M40: =D62 -> 140000
B41: STATO PATRIMONIALE | C41: 2024 | D41: 2025 | E41: 2026 | F41: 2027 | J41: Immobilizzazioni patrimoniali | K41: =D45 -> 58702 | L41: Riserve | M41: =D63 -> 5617287
B42: ATTIVO | L42: Reddito netto | M42: =D67 -> 1523771.9
B43: Immobilizzazioni immateriali | C43: =INV!C43 -> 89523 | D43: =INV!N43 -> 57827 | E43: =INV!O43 -> 21537 | F43: =INV!P43 -> 18351
B44: Immobilizzazioni materiali | C44: =INV!C54 -> 8694725 | D44: =INV!N54 -> 7955926.7 | E44: =INV!O54 -> 7208432.2 | F44: =INV!P54 -> 6480385 | J44: Tot. Impieghi | K44: =K28+K35+K39 -> 18393865 | L44: Tot. Fonti | M44: =M28+M35+M39 -> 18393865
B45: Immobilizzazioni finanziarie | C45: =INV!C63 -> 58702 | D45: =C45 -> 58702 | E45: =D45 -> 58702 | F45: =E45 -> 58702
B46: Totale attivo fisso | C46: =SUM(C43:C45) -> 8842950 | D46: =SUM(D43:D45) -> 8072455.7 | E46: =SUM(E43:E45) -> 7288671.2 | F46: =SUM(F43:F45) -> 6557438
B48: Rimanenze | C48: =CCN!C7 -> 4608814 | D48: =CCN!D7 -> 4634976.5 | E48: =CCN!E7 -> 4798127.7 | F48: =CCN!F7 -> 4967021.8
B49: Crediti vs clienti | C49: =incidenze!C47 -> 4256399 | D49: =incidenze!D47 -> 4446660 | E49: =incidenze!E47 -> 4645425.7 | F49: =incidenze!F47 -> 4853076.3
B50: Altri crediti | C50: =CCN!C10 -> 757317 | D50: =CCN!D10 -> 965508.85 | E50: =CCN!E10 -> 1035131.8 | F50: =CCN!F10 -> 1115356.2 | J50: Tabella 13A: Riclassificazione SP 2026
B51: Liquidità | C51: =FONTI!D5 -> 242430 | D51: =FONTI!E5 -> 184573.18 | E51: =FONTI!F5 -> 33419.72 | F51: =FONTI!G5 -> 40280.87
B52: Ratei e risconti attivi | C52: =incidenze!C58*incidenze!C8 -> 82949 | D52: =incidenze!D58*incidenze!D8 -> 89691.168 | E52: =incidenze!E58*incidenze!E8-7514.3 -> 86186.063 | F52: =incidenze!F58*incidenze!F8 -> 97888.77 | J52: Impieghi | L52: Fonti
B53: Totale attivo corrente | C53: =SUM(C48:C52) -> 9947909 | D53: =SUM(D48:D52) -> 10321410 | E53: =SUM(E48:E52) -> 10598291 | F53: =SUM(F48:F52) -> 11073624 | J53: Attivo circolante | K53: =SUM(K54:K61) -> 10564871 | L53: Passivo circolante | M53: =SUM(M54:M62) -> 5367447.1
J54: Rimanenze | K54: =E48 -> 4798127.7 | L54: Debiti verso fornitori | M54: =E77 -> 2455664.6
B55: Totale attivo | C55: =C46+C53 -> 18790859 | D55: =D46+D53 -> 18393865 | E55: =E46+E53 -> 17886962 | F55: =F46+F53 -> 17631062 | J55: Crediti verso clienti | K55: =E49 -> 4645425.7 | L55: Altri debiti | M55: =E78 -> 1539556.2
B56: VAR tot. Att. | D56: =D55-C55 -> -396993.51 | E56: =E55-D55 -> -506903.25 | F56: =F55-E55 -> -255900.33
B57: VAR ATT.FIX IMMO | D57: =D46-C46 -> -770494.26 | E57: =E46-D46 -> -783784.49 | F57: =F46-E46 -> -731233.24
B58: VAR ATT CORR | D58: =D53-C53 -> 373500.75 | E58: =E53-D53 -> 276881.24 | F58: =F53-E53 -> 475332.91
B59: VAR ATT CORR NECESSARIA
J60: Altri crediti | K60: =E50 -> 1035131.8 | L60: Ratei e risconti passivi | M60: =E79 -> 1021379.4
B61: PATRIMONIO NETTO | J61: Ratei e risconti attivi | K61: =E52 -> 86186.063 | L61: Fondo TFR | M61: =E74 -> 350846.78
B62: Capitale | C62: 140000 | D62: =C62 -> 140000 | E62: =D62 -> 140000 | F62: =E62 -> 140000 | L62: Fondo imposte | M62: 0
B63: Riserve (perdite a nuovo) | C63: =SUM(C64:C66) -> 4717554 | D63: =SUM(D64:D66) -> 5617287 | E63: =SUM(E64:E66) -> 7141058.9 | F63: =SUM(F64:F66) -> 8998219.3
B64: Riserva legale | C64: 28000 | D64: =C64 -> 28000 | E64: =D64 -> 28000 | F64: =E64 -> 28000 | J64: Immobilizzazioni operative nette | K64: =SUM(K65:K66) -> 7229969.2 | L64: Debiti finanziari | M64: =SUM(M65:M66) -> 3381295.9
B65: Utile a nuovo | C65: 0 | D65: =C67 -> 899733 | E65: =D67 -> 1523771.9 | F65: =E67 -> 1857160.5 | J65: Immobilizzazioni materiali | K65: =E44 -> 7208432.2 | L65: Finanziamenti a breve termine | M65: =FONTI!H73 -> 1349773.2
B66: Altre riserve | C66: =4689554 -> 4689554 | D66: =C63-C64 -> 4689554 | E66: =D63-D64 -> 5589287 | F66: =E63-E64 -> 7113058.9 | J66: Immobilizzazioni immateriali | K66: =E43 -> 21537 | L66: Altri finanziamenti a medio/lungo termine | M66: =FONTI!H74 -> 2031522.6
B67: Utile dell'esercizio | C67: =C34 -> 899733 | D67: =D34 -> 1523771.9 | E67: =E34 -> 1857160.5 | F67: =F34 -> 2216389.1
B68: Totale patrimonio netto | C68: =C67+SUM(C62:C63) -> 5757287 | D68: =D67+SUM(D62:D63) -> 7281058.9 | E68: =E67+SUM(E62:E63) -> 9138219.3 | F68: =F67+SUM(F62:F63) -> 11354608
B69: VAR PN | D69: =D68-C68 -> 1523771.9 | E69: =E68-D68 -> 1857160.5 | F69: =F68-E68 -> 2216389.1
B70: VAR COMPENSO RISERVA
J71: Attivo di gestione patrimoniale | K71: =SUM(K72:K73) -> 92121.72 | L71: Mezzi propri | M71: =SUM(M72:M74) -> 9138219.3
B72: PASSIVITA' | J72: Liquidità patrimoniali | K72: =E51 -> 33419.72 | L72: Capitale sociale | M72: =E62 -> 140000
B73: Fondi rischi e oneri | C73: =0-CCN!C18 -> 0 | D73: =0-CCN!D18 -> 0 | E73: =0-CCN!E18 -> 0 | F73: =0-CCN!F18 -> 0 | J73: Immobilizzazioni patrimoniali | K73: =E45 -> 58702 | L73: Riserve | M73: =E63 -> 7141058.9
B74: Fondo TFR | C74: =191675 -> 191675 | D74: =C74+HR!P8 -> 270267.04 | E74: =D74+HR!Q8 -> 350846.78 | F74: =E74+HR!R8 -> 434909.66 | L74: Reddito netto | M74: =E67 -> 1857160.5
B75: Debiti finanziari a L/T | C75: =FONTI!F74 -> 5110204 | D75: =M37 -> 3638932.4 | E75: =M66 -> 2031522.6 | F75: =M95 -> 344583.83
B76: Debiti finanziari a breve | C76: =FONTI!F73 -> 3395294 | D76: =M36 -> 2417759.7 | E76: =M65 -> 1349773.2 | F76: =M94 -> 228946.52 | J76: Tot. Impieghi | K76: =K53+K64+K71 -> 17886962 | L76: Tot. Fonti | M76: =M53+M64+M71 -> 17886962
B77: Debiti vs fornitori | C77: =incidenze!C61*-BP!C8 -> 2274193 | D77: =incidenze!D62 -> 2372164.5 | E77: =incidenze!E62 -> 2455664.6 | F77: =incidenze!F62 -> 2542104
B78: Altri debiti | C78: =CCN!C16 -> 1126361 | D78: =CCN!D16 -> 1436005.7 | E78: =CCN!E16 -> 1539556.2 | F78: =CCN!F16 -> 1658874.4
B79: Ratei e risconti passivi | C79: =incidenze!C67*incidenze!C8 -> 935845 | D79: =incidenze!D67*incidenze!D8 -> 977677.27 | E79: =incidenze!E67*incidenze!E8 -> 1021379.4 | F79: =incidenze!F67*incidenze!F8 -> 1067035.1
B80: Totale debiti | C80: =SUM(C73:C79) -> 13033572 | D80: =SUM(D73:D79) -> 11112807 | E80: =SUM(E73:E79) -> 8748742.9 | F80: =SUM(F73:F79) -> 6276453.5 | J80: Tabella 13A: Riclassificazione SP 2027
B82: Totale passivo | C82: =C80+C68 -> 18790859 | D82: =D80+D68 -> 18393865 | E82: =E80+E68 -> 17886962 | F82: =F80+F68 -> 17631062
B83: VAR PASS | D83: =D82-C82 -> -396993.51 | E83: =E82-D82 -> -506903.24 | F83: =F82-E82 -> -255900.33
B84: VAR DEBIT | D84: =D78+D76+D75-(C75+C76+C78) -> -2139161.1 | E84: =E78+E76+E75-(D75+D76+D78) -> -2571845.8 | F84: =F78+F76+F75-(E75+E76+E78) -> -2688447.3
J85: Impieghi | L85: Fonti
B86: check Attivo-passivo | C86: =C55-C82 -> 0.0041781068 | D86: =D55-D82 -> 0.0032100119 | E86: =E55-E82 -> -0.0046703257 | F86: =F55-F82 -> -0.0045167208 | J86: Attivo circolante | K86: =SUM(K87:K90) -> 11033343 | L86: Passivo circolante | M86: =SUM(M87:M91) -> 5702923.2
B87: Cashflow netto | D87: =((D51+D48)-(D80-C79-C77))-((C51+C48)-(C80-D79-D77)) -> 1749267.3 | E87: =((E51+E48)-(E80-D79-D77))-((D51+D48)-(D80-E79-E77)) -> 2248859.1 | F87: =((F51+F48)-(F80-E79-E77))-((E51+E48)-(E80-F79-F77)) -> 2515949.6 | J87: Rimanenze | K87: =F48 -> 4967021.8 | L87: Debiti verso fornitori | M87: =F77 -> 2542104
J88: Crediti verso clienti | K88: =F49 -> 4853076.3 | L88: Altri debiti | M88: =F78 -> 1658874.4
J89: Altri crediti | K89: =F50 -> 1115356.2 | L89: Ratei e risconti passivi | M89: =F79 -> 1067035.1
J90: Ratei e risconti attivi | K90: =F52 -> 97888.77 | L90: Fondo TFR | M90: =F74 -> 434909.66
B91: Tabella 14: BP Rendiconto finanziario previsionale | L91: Fondo imposte | M91: 0
B93: RENDICONTO FINANZIARIO | D93: 2025 | E93: 2026 | F93: 2027 | J93: Immobilizzazioni operative nette | K93: =SUM(K94:K95) -> 6498736 | L93: Debiti finanziari | M93: =SUM(M94:M95) -> 573530.35
B94: =B67 -> Utile dell'esercizio | D94: =D67 -> 1523771.9 | E94: =E67 -> 1857160.5 | F94: =F67 -> 2216389.1 | J94: Immobilizzazioni materiali | K94: =F44 -> 6480385 | L94: Finanziamenti a breve termine | M94: =FONTI!I73 -> 228946.52
B95: Ammortamenti | D95: =-(D18+D19) -> 799296.26 | E95: =-(E18+E19) -> 749688.49 | F95: =-(F18+F19) -> 730241.24 | J95: Immobilizzazioni immateriali | K95: =F43 -> 18351 | L95: Altri finanziamenti a medio/lungo termine | M95: =FONTI!I74 -> 344583.83
B96: Accantonamento TFR | D96: =D14 -> 78592.036 | E96: =E14 -> 80579.747 | F96: =F14 -> 84062.88
B97: Accantonamento per rischi | D97: 0 | E97: =E20 -> 0 | F97: =F20 -> 0 | J97: Attivo di gestione patrimoniale | K97: =SUM(K98:K99) -> 98982.87 | L97: Mezzi propri | M97: =SUM(M98:M100) -> 11354608
B98: Rettifiche di valore attività finanziarie | D98: =D28 -> 0 | E98: =E28 -> 0 | F98: =F28 -> 0 | J98: Liquidità patrimoniali | K98: =F51 -> 40280.87 | L98: Capitale sociale | M98: =F62 -> 140000
B99: Primary cash-flow | D99: =SUM(D94:D98) -> 2401660.2 | E99: =SUM(E94:E98) -> 2687428.7 | F99: =SUM(F94:F98) -> 3030693.2 | J99: Immobilizzazioni patrimoniali | K99: =F45 -> 58702 | L99: Riserve | M99: =F63 -> 8998219.3
B100: +/- variazione CCN | D100: =CCN!D24 -> -18090.838 | E100: =CCN!E24 -> 204796.13 | F100: =CCN!F24 -> 209544.25 | L100: Reddito netto | M100: =F67 -> 2216389.1
B101: utilizzo fondi TFR o rischi | D101: 0 | E101: 0 | F101: 0
B102: Cash-flow operativo | D102: =D99+SUM(D100:D101) -> 2383569.3 | E102: =E99+SUM(E100:E101) -> 2892224.8 | F102: =F99+SUM(F100:F101) -> 3240237.4 | J102: Tot. Impieghi | K102: =K86+K93+K97 -> 17631062 | L102: Tot. Fonti | M102: =M86+M93+M97 -> 17631062
B103: Investimenti immob. Immateriali | D103: 0 | E103: 0 | F103: 0
B104: Investimenti immob. Materiali | D104: 18912.705 | E104: 0 | F104: 0
B105: Investimenti immob. Finanziarie | D105: 0 | E105: 0 | F105: 0
B106: Levered cash-flow | D106: =D102-SUM(D103:D105) -> 2364656.6 | E106: =E102-SUM(E103:E105) -> 2892224.8 | F106: =F102-SUM(F103:F105) -> 3240237.4
...

Sheet ANALISI
B2: Tabella 15: BP Analisi indici finanziari previsionali | I2: Tabella 16: BP BENCHMARK settore indici finanziari previsionali
B4: INDICATORI FINANZIARI | C4: 2024 | D4: 2025 | E4: 2026 | F4: 2027 | I4: BENCHMARK DI SETTORE | J4: 2025 | K4: 2026 | L4: 2027 | M4: avg
B5: ROE | C5: =BP!C34/BP!C68 -> 0.15627725 | D5: =BP!D34/BP!D68 -> 0.20927888 | E5: =BP!E34/BP!E68 -> 0.20323002 | F5: =BP!F34/BP!F68 -> 0.19519731 | I5: ROE | J5: ='D. Benchmark di settore'!AI20 -> 0.030586494 | K5: ='D. Benchmark di settore'!AI21 -> 0.031953711 | L5: ='D. Benchmark di settore'!AI22 -> 0.033382042 | M5: =AVERAGE(J5:L5) -> 0.031974082
B6: ROI | C6: =BP!C22/BP!C55 -> 0.07053057 | D6: =BP!D22/BP!D55 -> 0.11430115 | E6: =BP!E22/BP!E55 -> 0.13643817 | F6: =BP!F22/BP!F55 -> 0.1570409 | I6: ROI | J6: ='D. Benchmark di settore'!AH20 -> 0.058143359 | K6: ='D. Benchmark di settore'!AH21 -> 0.060742367 | L6: ='D. Benchmark di settore'!AH22 -> 0.063457551 | M6: =AVERAGE(J6:L6) -> 0.060781092
B7: ROS | C7: =BP!C22/BP!C6 -> 0.061748432 | D7: =BP!D22/BP!D6 -> 0.093763519 | E7: =BP!E22/BP!E6 -> 0.10418164 | F7: =BP!F22/BP!F6 -> 0.11314057 | I7: ROS | J7: ='D. Benchmark di settore'!AG20 -> 0.031816919 | K7: ='D. Benchmark di settore'!AG21 -> 0.033239135 | L7: ='D. Benchmark di settore'!AG22 -> 0.034724925 | M7: =AVERAGE(J7:L7) -> 0.033260326
B8: MOL/Ricavi netti | C8: =BP!C15/BP!C6 -> 0.10688848 | D8: =BP!D15/BP!D6 -> 0.13183983 | E8: =BP!E15/BP!E6 -> 0.13861946 | F8: =BP!F15/BP!F6 -> 0.14541891
B9: Utile (perdita) / Ricavi netti | C9: =BP!C34/BP!C6 -> 0.041919448 | D9: =BP!D34/BP!D6 -> 0.067956384 | E9: =BP!E34/BP!E6 -> 0.079280822 | F9: =BP!F34/BP!F6 -> 0.090567655
B10: Ricavi netti /attivo | C10: =BP!C6/BP!C55 -> 1.1422245 | D10: =BP!D6/BP!D55 -> 1.2190364 | E10: =BP!E6/BP!E55 -> 1.3096182 | F10: =BP!F6/BP!F55 -> 1.3880158
B11: MOL/ Attivo | C11: =BP!C15/BP!C55 -> 0.12209064 | D11: =BP!D15/BP!D55 -> 0.16071756 | E11: =BP!E15/BP!E55 -> 0.18153856 | F11: =BP!F15/BP!F55 -> 0.20184374
B13: Copertura del debito
B14: EBIT/OF | C14: =BP!C22/-(BP!C25+BP!C26) -> 2.6327363 | D14: =BP!D22/-(BP!D25+BP!D26) -> 7.7762925 | E14: =BP!E22/-(BP!E25+BP!E26) -> 14.216772 | F14: =BP!F22/-(BP!F25+BP!F26) -> 95.143615
B15: NET DEB. / EBITDA | C15: =(BP!C75+BP!C76-BP!C51)/BP!C15 -> 3.6017397 | D15: =(BP!D75+BP!D76-BP!D51)/BP!D15 -> 1.9863625 | E15: =(BP!E75+BP!E76-BP!E51)/BP!E15 -> 1.0310124 | F15: =(BP!F75+BP!F76-BP!F51)/BP!F15 -> 0.14984308
B16: DEBT/EQUITY | C16: =(BP!C75+BP!C76)/BP!C68 -> 1.4773448 | D16: =(BP!D75+BP!D76)/BP!D68 -> 0.83184222 | E16: =(BP!E75+BP!E76)/BP!E68 -> 0.37001693 | F16: =(BP!F75+BP!F76)/BP!F68 -> 0.0505108
B18: Patrimonializzazione
B19: PN/ATTIVO | C19: =BP!C68/BP!C55 -> 0.30638764 | D19: =BP!D68/BP!D55 -> 0.39584169 | E19: =BP!E68/BP!E55 -> 0.51088716 | F19: =BP!F68/BP!F55 -> 0.6440116
B20: PN/ATTIVO FISSO | C20: =BP!C68/BP!C46 -> 0.65105954 | D20: =BP!D68/BP!D46 -> 0.90196331 | E20: =BP!E68/BP!E46 -> 1.2537566 | F20: =BP!F68/BP!F46 -> 1.7315617
B22: Gestione del circolante
B23: Tasso di rotazione crediti | C23: =BP!C49/BP!C6*365 -> 72.383087 | D23: =BP!D49/BP!D6*365 -> 72.383087 | E23: =BP!E49/BP!E6*365 -> 72.383087 | F23: =BP!F49/BP!F6*365 -> 72.383087
B24: Tasso di rotazione delle scorte | C24: =+-BP!C48/BP!C8*365 -> 111.17593 | D24: =+-BP!D48/BP!D8*365 -> 111.17593 | E24: =+-BP!E48/BP!E8*365 -> 111.17593 | F24: =+-BP!F48/BP!F8*365 -> 111.17593
B25: Tasso di rotazione debiti | C25: =+-BP!C77/BP!C8*365 -> 54.859129 | D25: =+-BP!D77/BP!D8*365 -> 56.899444 | E25: =+-BP!E77/BP!E8*365 -> 56.899444 | F25: =+-BP!F77/BP!F8*365 -> 56.899444
B26: Durata del ciclo di cassa | C26: =C23+C24-C25 -> 128.69989 | D26: =D23+D24-D25 -> 126.65957 | E26: =E23+E24-E25 -> 126.65957 | F26: =F23+F24-F25 -> 126.65957
B28: Composizione attivo fisso
B29: IMMOB IMMAT / ATT FISSO | C29: =BP!C43/BP!C46 -> 0.010123658 | D29: =BP!D43/BP!D46 -> 0.0071634955 | E29: =BP!E43/BP!E46 -> 0.0029548596 | F29: =BP!F43/BP!F46 -> 0.0027985015
B30: IMMOB MAT / ATT FISSO | C30: =BP!C44/BP!C46 -> 0.98323806 | D30: =BP!D44/BP!D46 -> 0.98556462 | E30: =BP!E44/BP!E46 -> 0.98899127 | F30: =BP!F44/BP!F46 -> 0.98824953
B32: Composizione attivo circolante
B33: Rimanenze / Attivo circolante | C33: =BP!C48/CCN!C12 -> 0.47486724 | D33: =BP!D48/CCN!D12 -> 0.45724092 | E33: =BP!E48/CCN!E12 -> 0.45383586 | F33: =BP!F48/CCN!F12 -> 0.45018285
B34: Liquidità / Attivo circolante | C34: =BP!C51/CCN!C12 -> 0.024978674 | D34: =BP!D51/CCN!D12 -> 0.018208164 | E34: =BP!E51/CCN!E12 -> 0.0031610387 | F34: =BP!F51/CCN!F12 -> 0.0036508309

Sheet RI
B2: Tabella 17: BP Analisi residual income
B4: ANALISI RESIDUAL INCOME | C4: 2024 | D4: 2025 | E4: 2026 | F4: 2027
B5: Utile netto | C5: =BP!C34 -> 899733 | D5: =BP!D34 -> 1523771.9 | E5: =BP!E34 -> 1857160.5 | F5: =BP!F34 -> 2216389.1
B6: cost-opportunity investments; BTP short-term 2028 | C6: 0.022 | D6: 0.022 | E6: 0.022 | F6: 0.022
B7: Totale attivo | C7: =BP!C55 -> 18790859 | D7: =BP!D55 -> 18393865 | E7: =BP!E55 -> 17886962 | F7: =BP!F55 -> 17631062
C8: =C6*C7 -> 413398.9 | D8: =D6*D7 -> 404665.04 | E8: =E6*E7 -> 393513.17 | F8: =F6*F7 -> 387883.36
B9: Residual income | C9: =C5-C8 -> 486334.1 | D9: =D5-D8 -> 1119106.8 | E9: =E5-E8 -> 1463647.3 | F9: =F5-F8 -> 1828505.7

Sheet extras →

Sheet B. calcolo prezzi medi di vend
B2: CALCOLO PREZZI MEDI DI MERCATO
B5: variabili di calcolo | I5: prezzi al kg per tipologia prodotto
B6: azienda | C6: prodotto | D6: dettagli | E6: specialità | F6: prezzo al kg | I6: arrosto all'inglese | J6: sottofesa | L6: 21.7 | N6: guanciale | O6: selection | Q6: =(10.25/350)*1000 -> 29.285714 | S6: pancetta | V6: =(9/350)*1000 -> 25.714286 | X6: speck | Z6: IGP | AA6: 80
B7: Bomè | C7: carne salada | E7: no ogm | F7: =1000*(6.11/120) -> 50.916667 | I7: arrosto all'inglese | J7: fesa | L7: 22.35 | N7: guanciale | O7: nero | Q7: 31.5 | S7: pancetta | T7: fette | V7: =1000*(4.5/80) -> 56.25 | X7: speck | Y7: cuore | Z7: IGP | AA7: 34.86
B8: Bomè | C8: pancetta | D8: affumicata | E8: no ogm | F8: =(23.2/1300)*1000 -> 17.846154 | N8: guanciale | O8: doppio affumicato | Q8: 35 | S8: pancetta | T8: affumicata | U8: Bioland | V8: =1000*(6.29/70) -> 89.857143 | X8: speck | Y8: sfuso | Z8: IGP | AA8: 17.44
B9: Bomè | C9: speck | D9: granfetta | F9: =1000*(10.9/550) -> 19.818182 | I9: bresaola | J9: di montagna | L9: 76.5 | N9: guanciale | O9: affumicata | Q9: 30 | S9: pancetta | T9: affumicata | V9: =1000*(12.9/600) -> 21.5 | X9: speck | Z9: IGP | AA9: =38/2 -> 19
B10: Fratelli Corrà | C10: bresaola | D10: di montagna | F10: 76.5 | I10: bresaola | J10: di montagna | L10: =190/3.9 -> 48.717949 | S10: pancetta | T10: affumicata | U10: no ogm | V10: =(23.2/1300)*1000 -> 17.846154 | X10: speck | Y10: light | AA10: =(13/400)*1000 -> 32.5
B11: Fratelli Corrà | C11: bresaola | D11: di montagna | F11: =190/3.9 -> 48.717949 | N11: lardo | O11: con erbe | Q11: 63.5 | S11: pancetta | T11: affumicata | V11: 20 | X11: speck | Y11: fette | Z11: IGP | AA11: =1000*(4.5/100) -> 45
B12: Fratelli Corrà | C12: carne salada | F12: 73 | I12: carne salada | K12: no ogm | L12: 50.92 | N12: lardo | O12: con erbe | Q12: 61.5 | S12: pancetta | T12: affumicata | V12: 20 | X12: speck | Y12: selection baffa | AA12: =88.5/5 -> 17.7
B13: Fratelli Corrà | C13: carne salada | F13: 67.5 | I13: carne salada | L13: 73 | N13: lardo | O13: con erbe | Q13: 62 | X13: speck | Y13: =Y12 -> selection baffa | AA13: 25.5
B14: Fratelli Corrà | C14: coppa | F14: 56 | I14: carne salada | L14: 67.5 | N14: Lardo | O14: con erbe | Q14: 61.5 | S14: prosciutto cotto | T14: trancio | V14: =(13.2/600)*1000 -> 22 | X14: speck | Y14: selection cuore | AA14: =1000*(15/350) -> 42.857143
B15: Fratelli Corrà | C15: Filetto | D15: affumicata | F15: =1000*(16.5/240) -> 68.75 | I15: carne salada | L15: 18.8 | N15: lardo | O15: salato | Q15: 10.95 | S15: prosciutto cotto | T15: Praga mini | V15: =1000*(10.2/800) -> 12.75 | X15: speck | Y15: selection | AA15: =46.5/2 -> 23.25
B16: Fratelli Corrà | C16: Filetto | D16: affumicata | F16: =1000*(15/290) -> 51.724138 | I16: carne salada | L16: 20.2 | N16: Lardo | O16: salato | Q16: 10.8 | S16: prosciutto cotto | T16: affumicata | V16: 56 | X16: speck | Y16: selection fette | AA16: =1000*(3.5/80) -> 43.75
B17: Fratelli Corrà | C17: guanciale | D17: nero | F17: 31.5 | I17: carne salada | L17: 20.2 | N17: lardo | Q17: 28.55 | S17: prosciutto cotto | V17: 56 | X17: speck | Y17: cuore | Z17: Bio | AA17: =1000*(22/350) -> 62.857143
B18: Fratelli Corrà | C18: guanciale | D18: doppio affumicato | F18: 35 | I18: carne salada | J18: fette | L18: 23.9 | S18: prosciutto cotto | T18: affumicata | V18: 69 | X18: speck | Y18: bioland fette | Z18: Bioland | AA18: =1000*(6.29/70) -> 89.857143
B19: Fratelli Corrà | C19: guanciale | D19: affumicata | F19: 30 | I19: carne salada | L19: 25.1 | N19: lonzino | O19: affumicata | Q19: 23.99 | S19: prosciutto cotto | T19: intero | V19: 12.7 | X19: speck | Y19: cuore | Z19: Bioland | AA19: =1000*(26.5/350) -> 75.714286
B20: Fratelli Corrà | C20: lardo | D20: con erbe | F20: 63.5 | I20: carne salada | J20: carpaccio | L20: 25.1 | S20: prosciutto cotto | T20: mezzo | V20: 12.85 | X20: speck | Y20: Preziose bontà | AA20: =39.9/2.5 -> 15.96
B21: Fratelli Corrà | C21: lardo | D21: con erbe | F21: 61.5 | N21: Manzo | O21: affumicata | Q21: =15*5 -> 75 | X21: speck | Y21: Preziose bontà | AA21: =29.9/1.3 -> 23
B22: Fratelli Corrà | C22: lardo | D22: con erbe | F22: 62 | I22: coppa | J22: fette | L22: =5.1*10 -> 51 | S22: punta d'anca | T22: cotta | V22: 14.2 | X22: speck | Z22: IGP | AA22: =1000*(13.9/400) -> 34.75
B23: Fratelli Corrà | C23: Lardo | D23: con erbe | F23: 61.5 | I23: coppa | J23: fette | K23: Bioland | L23: =1000*(6.29/70) -> 89.857143 | N23: mortadella | O23: affumicata | Q23: =1000*(11.1/230) -> 48.26087 | X23: speck | Y23: intero | AA23: =(80/4.5) -> 17.777778
B24: Fratelli Corrà | C24: Manzo | D24: affumicata | F24: =15*5 -> 75 | I24: coppa | L24: 56 | N24: mortadella | O24: affumicata | Q24: =1000*(9/260) -> 34.615385 | X24: speck | Y24: granfetta | AA24: =1000*(10.9/550) -> 19.818182
B25: Fratelli Corrà | C25: mortadella | D25: affumicata | F25: =1000*(11.1/230) -> 48.26087 | N25: mortadella | O25: affumicata | Q25: 16.9 | X25: speck | AA25: =310/7 -> 44.285714
B26: Fratelli Corrà | C26: mortadella | D26: affumicata | F26: =1000*(9/260) -> 34.615385 | I26: Filetto | J26: affumicata | L26: =1000*(16.5/240) -> 68.75 | N26: mortadella | O26: affumicata | Q26: 15.55 | X26: speck | AA26: =142/5 -> 28.4
B27: Fratelli Corrà | C27: prosciutto cotto | D27: affumicata | F27: 56 | I27: Filetto | J27: affumicata | L27: =1000*(15/290) -> 51.724138 | X27: speck | AA27: 44
B28: Fratelli Corrà | C28: prosciutto cotto | F28: 56 | X28: speck | AA28: 45
B29: Pfitscher | C29: speck | E29: IGP BIO | X29: speck | AA29: =1000*(15.9/360) -> 44.166667
B30: Segata | C30: speck | D30: tridentum | X30: speck | AA30: =1000*(30.5/720) -> 42.361111
B31: Segata | C31: speck | D31: tridentum | X31: speck | AA31: 64
B32: Segata | C32: speck | D32: tridentum | X32: speck | Y32: mezzo | AA32: 12.8
B33: Segata | C33: speck | D33: tridentum | X33: speck | Y33: cotto | AA33: 12.5
B34: Segata | C34: speck | D34: tridentum | X34: speck | Y34: tradizionale | AA34: 15.5
B35: Segata | C35: speck | D35: tridentum | X35: speck | Y35: tradizionale | AA35: 18
B36: Segata | C36: speck | D36: tridentum | X36: speck | Y36: tradizionale | AA36: 18
B37: Fratelli Corrà | C37: prosciutto cotto | D37: affumicata | F37: 69 | X37: speck | Y37: tradizionale | AA37: 24
B38: Fratelli Corrà | C38: speck | F38: =310/7 -> 44.285714 | X38: speck | Y38: premium | AA38: 20.25
B39: Segata | C39: speck | D39: Preziose bontà | X39: speck | Y39: premium | AA39: 20.25
B40: Segata | C40: speck | D40: Preziose bontà | X40: speck | Y40: premium | AA40: 21.85
B41: Segata | C41: speck | D41: Preziose bontà | X41: speck | Y41: intero | AA41: 12.8
B42: Segata | C42: speck | D42: Preziose bontà | X42: speck | Y42: premium | AA42: 18
B43: Segata | C43: speck | D43: Preziose bontà
B44: Segata | C44: speck | D44: classici
B45: Segata | C45: speck | D45: classici
B46: Segata | C46: speck | D46: classici
B47: Segata | C47: speck | D47: classici
B48: Segata | C48: speck | D48: classici
B49: Segata | C49: speck | D49: classici
B50: Segata | C50: prosciutto cotto | D50: alta qualità
B51: Segata | C51: prosciutto cotto | D51: alta qualità
B52: Segata | C52: prosciutto cotto | D52: alta qualità
B53: Segata | C53: prosciutto cotto | D53: alta qualità
B54: Segata | C54: prosciutto cotto | D54: amadeus
... B82: Segata | C82: poulet | D82: arrosto
B83: Segata | C83: mortadella | D83: bologna | E83: IGP
B84: Segata | C84: mortadella | D84: bologna | E84: IGP
B85: Segata | C85: mortadella | D85: bologna | E85: IGP
B86: Segata | C86: mortadella | D86: bologna | E86: IGP
B87: Segata | C87: mortadella | D87: bologna
B88: Segata | C88: mortadella | D88: bologna
B89: Segata | C89: mortadella | D89: bologna
B90: Segata | C90: mortadella | D90: bologna
B91: Segata | C91: mortadella | D91: bologna
B92: Segata | C92: mortadella | D92: bologna
B93: Segata | C93: mortadella | D93: bologna
B94: Segata | C94: mortadella | D94: bologna
B95: Segata | C95: mortadella | D95: bologna
B96: Segata | C96: mortadella | D96: bologna
B97: Segata | C97: mortadella | D97: bologna
B98: Segata | C98: mortadella | D98: bologna
... B123: Segata | C123: stinco | D123: affumicata
B124: Segata | C124: prosciutto crudo | E124: Parma
B125: Segata | C125: prosciutto crudo
B126: Segata | C126: prosciutto crudo
B127: Segata | C127: prosciutto crudo
B128: Fratelli Corrà | C128: speck | F128: =142/5 -> 28.4
B129: Fratelli Corrà | C129: speck | F129: 44
B130: Fratelli Corrà | C130: speck | F130: 45 | I130: Calcolo della media disponibile per prodotto
B131: Fratelli Corrà | C131: speck | F131: =1000*(15.9/360) -> 44.166667 | I131: prodotto | J131: media | K131: mediana | L131: beta | M131: quant
B132: Fratelli Corrà | C132: speck | F132: =1000*(30.5/720) -> 42.361111 | I132: arrosto all'inglese | J132: =AVERAGE(L6:L7) -> 22.025 | K132: =MEDIAN(L6:L7) -> 22.025
B133: Fratelli Corrà | C133: speck | F133: 64 | I133: bresaola | J133: =AVERAGE(L9:L10) -> 62.608974 | K133: =MEDIAN(L9:L10) -> 62.608974
B134: Pfitscher | C134: coppa | D134: fette | F134: =5.1*10 -> 51 | I134: carne salada | J134: =AVERAGE(L12:L20) -> 36.08 | K134: =MEDIAN(L12:L20) -> 25.1 | L134: =L12/J134 -> 1.4113082
B135: Pfitscher | C135: coppa | D135: fette | E135: Bioland | F135: =1000*(6.29/70) -> 89.857143 | I135: coppa | J135: =AVERAGE(L22:L24) -> 65.619048 | K135: =MEDIAN(L22:L24) -> 56
B136: Pfitscher | C136: guanciale | D136: selection | F136: =(10.25/350)*1000 -> 29.285714 | I136: Filetto | J136: =AVERAGE(L26:L27) -> 60.237069 | K136: =MEDIAN(L26:L27) -> 60.237069
B137: Pfitscher | C137: pancetta | F137: =(9/350)*1000 -> 25.714286 | I137: guanciale | J137: =AVERAGE(Q6:Q9) -> 31.446429 | K137: =MEDIAN(Q6:Q9) -> 30.75
B138: Pfitscher | C138: pancetta | D138: fette | F138: =1000*(4.5/80) -> 56.25 | I138: lardo | J138: =AVERAGE(Q11:Q17) -> 42.685714 | K138: =MEDIAN(Q11:Q17) -> 61.5
B139: Pfitscher | C139: pancetta | D139: affumicata | E139: Bioland | F139: =1000*(6.29/70) -> 89.857143 | I139: lonzino | J139: =AVERAGE(Q19) -> 23.99 | K139: =MEDIAN(Q19) -> 23.99
B140: Pfitscher | C140: prosciutto cotto | D140: trancio | F140: =(13.2/600)*1000 -> 22 | I140: Manzo | J140: =AVERAGE(Q21) -> 75 | K140: =MEDIAN(Q21) -> 75
B141: Pfitscher | C141: prosciutto cotto | D141: Praga mini | F141: =1000*(10.2/800) -> 12.75 | I141: mortadella | J141: =AVERAGE(Q23:Q26) -> 28.831564 | K141: =MEDIAN(Q23:Q26) -> 25.757692
B142: Pfitscher | C142: speck | E142: IGP | F142: 80 | I142: pancetta | J142: =AVERAGE(V6:V12) -> 35.881083 | K142: =MEDIAN(V6:V12) -> 21.5 | L142: =V10/J142 -> 0.49736943
B143: Pfitscher | C143: speck | D143: cuore | E143: IGP | F143: 34.86 | I143: prosciutto cotto | J143: =AVERAGE(V14:V20) -> 34.471429 | K143: =MEDIAN(V14:V20) -> 22
B144: Pfitscher | C144: speck | D144: sfuso | E144: IGP | F144: 17.44 | I144: punta d'anca | J144: =AVERAGE(V22) -> 14.2 | K144: =MEDIAN(V22) -> 14.2
B145: Pfitscher | C145: speck | E145: IGP | F145: =38/2 -> 19 | I145: speck | J145: =AVERAGE(AA6:AA38) -> 34.995611 | K145: =MEDIAN(AA6:AA38) -> 28.4 | L145: =AA24/J145 -> 0.56630478
B146: Pfitscher | C146: speck | D146: light | F146: =(13/400)*1000 -> 32.5
B147: Pfitscher | C147: speck | D147: fette | E147: IGP | F147: =1000*(4.5/100) -> 45
B148: Pfitscher | C148: speck | D148: selection baffa | F148: =88.5/5 -> 17.7
B149: Pfitscher | C149: speck | D149: =D148 -> selection baffa | F149: 25.5
B150: Pfitscher | C150: speck | D150: selection cuore | F150: =1000*(15/350) -> 42.857143
B151: Pfitscher | C151: speck | D151: selection | F151: =46.5/2 -> 23.25
B152: Pfitscher | C152: speck | D152: selection fette | F152: =1000*(3.5/80) -> 43.75
B153: Pfitscher | C153: speck | D153: cuore | E153: Bio | F153: =1000*(22/350) -> 62.857143
B154: Pfitscher | C154: speck | D154: bioland fette | E154: Bioland | F154: =1000*(6.29/70) -> 89.857143
...

Sheet B. linea prodotti Bomè
B2: ANALISI PRODOTTI DI BOME'
B5: TAB. Categorie di prodotto e prodotti venduti da Bomè S.p.A.
B6: La seguente tabella riporta le linee di prodotto e i rispettivi prodotti presenti sul listino di Bomè sul proprio sito.
B8: linea | C8: prodotti | D8: prezzo ipotetico | E8: cat. di riferimento | F8: quota nazionale
B9: bio | C9: carne salada bio | E9: bresaola
B10: bio | C10: speck bio | E10: prosciutto crudo
B11: bio | C11: speck bio mattonella | E11: prosciutto crudo
B12: carne salada | C12: carpaccio | E12: bresaola
B13: carne salada | C13: fesa | E13: bresaola
B14: carne salada | C14: girello | E14: bresaola
B15: cotti | C15: porchetta | E15: prosciutto cotto
B16: cotti | C16: speckotto | E16: prosciutto cotto
B17: cotti | C17: speckotto al rosmarino | E17: prosciutto cotto
B18: cotti | C18: tacchinella alle erbe | E18: mortadella e wurstel
B19: halal | C19: carne salada | E19: bresaola
B20: halal | C20: fumatello affumicato | E20: bresaola
... B50: speck | C50: tranci | E50: prosciutto crudo
B57: SVILUPPO DI UN MIX PRODOTTI
B60: a. Linee prodotti | H60: b.Prezzi di mercato e coefficienti quantitavi
B61: Si elencano i prodotti presentati in precedenza, e si individuano per ciascuno la materia prima principale e gli step lavorativi principali.
B62: Si assegna la categoria prodotto sulla base della struttura di lavorazione principale e materia prima
B64: linea | C64: prodotti | D64: cat. Prod. | E64: ingrediente principale | F64: lavorazione principale | H64: Linee individuate | I64: prezzo di mkt | K64: come?
B65: biologico | C65: carne salada bio | D65: carne salada | E65: bovino | F65: salatura; | H65: Carne salada | I65: 36.08 | K65: Raggruppamento sulla base di tipologia di lavorazione, omgrediente principale e tipologia di prodotto
B66: carne salada | C66: carpaccio | D66: carne salada | E66: bovino | F66: aromatizzata; salatura; | H66: Grasso e Lardo | I66: 35.88
B67: carne salada | C67: fesa | D67: carne salada | E67: bovino | F67: aromatizzata; salatura; | H67: Prosciutto alternativo | I67: 34.47 | K67: si ipotizza prezzo simile al prosciutto cotto, processo simile ma ingrediente principale in input molto variegato
B68: carne salada | C68: girello | D68: carne salada | E68: bovino | F68: aromatizzata; salatura; | H68: Salume cotto | I68: 28.83 | K68: usato prezzo medio mortadella vista la similarità in uso ingrediente e processo produzione e prodotto finale
B69: halal | C69: carne salada | D69: carne salada | E69: bovino | F69: aromatizzata; salatura; | H69: Speck | I69: 35
B70: halal | C70: fumatello affumicato | D70: carne salada | E70: bovino | F70: aromatizzata; salatura; affumicata;
B71: halal | C71: girello di carne salada | D71: carne salada | E71: bovino | F71: aromatizzata; salatura; | K71: come misurare la quantità venduta? | M71: si ipotizza che sulla base delle percentuali di valore prodotto totale a livello nazionale si usano le percentuali relative ai prodotti effettivamente venduti da bomè. Si scalano i valori percentuali fino al compimento del 100% del prodotto aziendale
B72: specialità | C72: fumatello | D72: carne salada | E72: bovino | F72: aromatizzata; affumicata; | H72: Linee individuate | I72: quota produzione media nazionale | J72: ridistribuzione su tot
B73: halal | C73: pancetta affumicata di bovino | D73: grasso | E73: bovino | F73: salatura; affumicata; stagionata; | H73: Carne salada | I73: 0.024 | J73: =I73*$J$78/$I$78 -> 0.074534161
B74: halal | C74: pancetta tesa di bovino | D74: grasso | E74: bovino | F74: salatura; stagionata; | H74: Grasso e Lardo | I74: 0.038 | J74: =I74*$J$78/$I$78 -> 0.11801242
B75: pancetta | C75: affumicata | D75: grasso | E75: suino | F75: salatura; affumicata; stagionata; | H75: Prosciutto alternativo | I75: 0.076 | J75: =I75*$J$78/$I$78 -> 0.23602484
B76: pancetta | C76: affumicata doppia | D76: grasso | E76: suino | F76: salatura; affumicata; | H76: Salume cotto | I76: 0.155 | J76: =I76*$J$78/$I$78 -> 0.48136646
B77: pancetta | C77: stufata | D77: grasso | E77: suino | F77: cotta al vapore; affumicata; | H77: Speck | I77: 0.029 | J77: =I77*$J$78/$I$78 -> 0.090062112
B78: pancetta | C78: stufata doppia | D78: grasso | E78: suino | F78: cotta al vapore; affumicata; | H78: TOTALE | I78: =SUM(I73:I77) -> 0.322 | J78: 1 | K78: -> costituiscono le quote di mix prodotto, si usano per suddividere il fatturato rispetto alle varie linee
B79: pancetta | C79: tesa | D79: grasso | E79: suino | F79: salatura; stagionata; | H79: src: pg 95 ASSica rapoporto 2024) | K79: si considerano i ratio stabili per gli anni successivi data la completa assenza di dati relativi.
B80: pancetta | C80: tesa doppia | D80: grasso | E80: suino | F80: salatura; stagionata;
B81: specialità | C81: guanciale de bellotta | D81: grasso | E81: suino | F81: aromatizzata; massaggiata; affumicata; stagionata; | H81: c. Prospettive di crescita future BT
B82: specialità | C82: lardo | D82: grasso | E82: suino | F82: aromatizzata; stagionata;
B83: halal | C83: prosciutto di agnello | D83: prosciutto alternativo | E83: ovino | F83: aromatizzata; affumicata; stagionata; | H83: Variabili | I83: 2020 | J83: 2021 | K83: 2022 | L83: 2023 | M83: 2024 | N83: 2025 | O83: 2026 | P83: 2027 | Q83: trend forecast | R83: CAGR (2020-2024)
B84: halal | C84: prosciutto di bovino | D84: prosciutto alternativo | E84: bovino | F84: aromatizzata; stagionata; | H84: Fatturato naz. [mln] | I84: 8191 | J84: 8725 | K84: 8907 | L84: 9498 | M84: 9787 | N84: =_xlfn.FORECAST.LINEAR(N83,I84:M84,I83:M83) -> 10211.1 | O84: =_xlfn.FORECAST.LINEAR(O83,I84:M84,I83:M83) -> 10607.6 | P84: =_xlfn.FORECAST.LINEAR(P83,I84:M84,I83:M83) -> 11004.1 | Q84: =(N84-M84)/L84 -> 0.044651506 | R84: =((M84/I84)^(1/5))-1 -> 0.036245201 | T84: <- pag 111; ASSICA: Rapporto annuale 2024
B85: specialità | C85: prosciutto di agnello | D85: prosciutto alternativo | E85: ovino | F85: aromatizzata; affumicata; stagionata; | H85: Esportazioni [mln] | I85: 1741 | J85: 1994 | K85: 2149 | L85: 2309 | M85: 2480 | N85: =_xlfn.FORECAST.LINEAR(N83,I85:M85,I83:M83) -> 2672.5 | O85: =N85*(1+Q85) -> 2879.942 | P85: =O85*(1+Q85) -> 3103.4859 | Q85: =(N85-M85)/M85 -> 0.077620968
B86: cotti | C86: speckotto | D86: prosciutto cotto | E86: suino | F86: cotta al forno; affumicata; | H86: Importazioni [mln] | I86: 258 | J86: 310 | K86: 323 | L86: 352 | M86: 358 | N86: =_xlfn.FORECAST.LINEAR(N83,I86:M86,I83:M83) -> 392.8 | O86: =N86*(1+Q86) -> 430.98279 | P86: =O86*(Q86+1) -> 472.87721 | Q86: =(N86-M86)/M86 -> 0.097206704
B87: cotti | C87: speckotto al rosmarino | D87: prosciutto cotto | E87: suino | F87: aromatizzata; cotta al forno; affumicata; | H87: Saldo commerciale [mln] | I87: =I85-I86 -> 1483 | J87: =J85-J86 -> 1684 | K87: =K85-K86 -> 1826 | L87: =L85-L86 -> 1957 | M87: =M85-M86 -> 2122 | N87: =N85-N86 -> 2279.7 | O87: =O85-O86 -> 2448.9592 | P87: =P85-P86 -> 2630.6087 | Q87: =Q86-Q85 -> 0.019585736
B88: specialità | C88: lonzino | D88: speck | E88: suino | F88: aromatizzata; stagionata;
B89: cotti | C89: porchetta | D89: salume cotto | E89: suino | F89: aromatizzata; cotta al forno; | I89: chosing simple linear regression, based on Michael Boyles from hbs explaining that on short term is better than using Cagr if business growth is stable. Since CAGR is 3,62%, the linear regression is more accurate with a rate of 4,47%
B90: cotti | C90: tacchinella alle erbe | D90: salume cotto | E90: aviario | F90: aromatizzata; cotta al vapore; | H90: metodo: | I90: https://online.hbs.edu/blog/post/financial-forecasting-methods
B91: halal | C91: gran beef | D91: salume cotto | E91: bovino | F91: aromatizzata; cotta al forno;
B92: halal | C92: pancetta stufata di vitello arrotolata | D92: salume cotto | E92: bovino | F92: salatura; cotta al vapore;
B93: halal | C93: pancetta stufata di vitello doppia | D93: salume cotto | E93: bovino | F93: salatura; cotta al vapore;
B94: halal | C94: pastrami al pepe nero | D94: salume cotto | E94: bovino | F94: aromatizzata; cotta al forno;
B95: halal | C95: tacchino | D95: salume cotto | E95: aviario | F95: aromatizzata; cotta al vapore;
B96: specialità | C96: gran beef all'inglese | D96: salume cotto | E96: bovino | F96: aromatizzata; cotta al forno;
B97: specialità | C97: sottofesa all'ingese | D97: salume cotto | E97: bovino | F97: aromatizzata; cotta al vapore;
B98: specialità | C98: prosciutto black angus | D98: salume cotto | E98: bovino | F98: aromatizzata; affumicata; stagionata;
B99: biologico | C99: speck bio | D99: speck | E99: suino | F99: aromatizzata; affumicata;
B100: biologico | C100: speck bio mattonella | D100: speck | E100: suino | F100: aromatizzata; affumicata;
B101: speck | C101: adamello | D101: speck | E101: suino | F101: stagionata;
B102: speck | C102: granfetta | D102: speck | E102: suino | F102: aromatizzata; stagionata;
... B106: speck | C106: tranci | D106: speck | E106: suino | F106: stagionata;
H117: d. Quantificazione variabilità prezzi futuri
H119: Prezzi di vendita previsti
H120: prodotto | I120: 2024 | J120: 2025 | K120: 2026 | L120: 2027 | N120: Prezzi del 2024 rappresentano i prezzi medi di mercato del settore, zona e prezzi di riferimento.
H121: Carne Salada | I121: 36.08 | J121: =I121*(1+I$138)*(1+$M129) -> 37.243472 | K121: =J121*(1+J$138)*(1+$M129) -> 38.708555 | L121: =K121*(1+K$138)*(1+$M129) -> 39.996002 | N121: La crescita è proiettata rispetto all'inflazione e il rapporto ingrediente-totale e il peso rispetto al prezzo di vendita
H122: Grasso e Lardo | I122: 35.88 | J122: =I122*(1+I$138)*(1+$M130) -> 36.66848 | K122: =J122*(1+J$138)*(1+$M130) -> 37.731717 | L122: =K122*(1+K$138)*(1+$M130) -> 38.598731 | N122: Il calcolo è effettuato per prevedere futuri prezzi di vendita basandosi sulle prospettive di crescita dei prezzi di ingredienti presentata da ASSICA e dall'andamento inflazionistico.
H123: Prosciutto alternativo | I123: 34.47 | J123: =I123*(1+I$138)*(1+$M131) -> 35.593848 | K123: =J123*(1+J$138)*(1+$M131) -> 37.00682 | L123: =K123*(1+K$138)*(1+$M131) -> 38.250879
H124: Salume cotto | I124: 28.83 | J124: =I124*(1+I$138)*(1+$M132) -> 29.540523 | K124: =J124*(1+J$138)*(1+$M132) -> 30.476486 | L124: =K124*(1+K$138)*(1+$M132) -> 31.258232
H125: Speck | I125: 35 | J125: =I125*(1+I$138)*(1+$M133) -> 35.679266 | K125: =J125*(1+J$138)*(1+$M133) -> 36.62157 | L125: =K125*(1+K$138)*(1+$M133) -> 37.368943
H127: dinamica prezzi più complessa del previsto; difficile effettuare forecast realistico; conviene usare dato provvisto da ricerche di mercato;
H128: prodotto | I128: rapp. Ingrediente suino | J128: rapp. Ingrediente bovino | K128: rapp. Ingrediente ovino | L128: rapp. ingrediente aviario | M128: influenza prezzo di vendita
H129: Carne Salada | I129: =0 -> 0 | J129: 1 | K129: 0 | L129: 0 | M129: =I129*$I$134+J129*$J$134+K129*$K$134+L129*$L$134 -> 0.013
H130: Grasso e Lardo | I130: =0.8 -> 0.8 | J130: =2/10 -> 0.2 | K130: 0 | L130: 0 | M130: =I130*$I$134+J130*$J$134+K130*$K$134+L130*$L$134 -> 0.00292
H131: Prosciutto alternativo | I131: =1/4 -> 0.25 | J131: =1/4 -> 0.25 | K131: =2/4 -> 0.5 | L131: 0 | M131: =I131*$I$134+J131*$J$134+K131*$K$134+L131*$L$134 -> 0.01335
H132: Salume cotto | I132: =1/10 -> 0.1 | J132: =7/10 -> 0.7 | K132: 0 | L132: =2/10 -> 0.2 | M132: =I132*$I$134+J132*$J$134+K132*$K$134+L132*$L$134 -> 0.00554
H133: Speck | I133: =1 -> 1 | J133: 0 | K133: 0 | L133: 0 | M133: =I133*$I$134+J133*$J$134+K133*$K$134+L133*$L$134 -> 0.0004
H134: inflazione ingredienti compl. | I134: 0.0004 | J134: 0.013 | K134: 0.02 | L134: -0.018 | M134: =SUM(M129:M133) -> 0.03521
H135: https://www.assica.it/magazine/prospettive-a-breve-termine-dei-mercati-agricoli-dellue/
H137: Anno | I137: 2025 | J137: 2026 | K137: 2027
H138: inflazione BCE | I138: 0.019 | J138: 0.026 | K138: 0.02
H139: https://global.morningstar.com/it/economia/nonostante-la-tregua-la-bce-potrebbe-aumentare-i-tassi-di-interesse-questanno#:~:text=Attualmente%20prevedono%20che%20l'inflazione,rispetto%20all'1%2C8%25)
B146: PRODUZIONE SALUMI
B149: Sulla base della struttura di lavorazione principale dei prodotti Bomè si identificano questi key processes:
B150: aromatizzazione | C150: a cui si aggiungono per standard normativi i seguenti processi: | D150: stuccatura
B151: salatura | D151: asciugatura
B152: affumicatura | D152: confezionamento
B153: stagionatura | D153: massaggiatura
B154: cottura al vapore | D154: raffredamento
B155: cottura al forno | D155: lavaggio
B158: Per ciascuna categoria di pocesso si individua il lavoro effetivamente necessario.
B159: Prosciutto crudo | C159: selezione | D159: rifilatura | E159: massaggiatura | F159: salatura | G159: raffreddamento | H159: lavaggio | I159: asciugatura | J159: stagionatura | K159: stuccatura
B160: Pancetta | C160: selezione | D160: rifilatura | E160: sgrassatura | F160: aromatizzazione | G160: raffreddamento | H160: lavaggio | I160: taglio | K160: eventualmente stagionatura; affumicatura;
B161: Mortadella e simili | C161: selezione | D161: triturazione | E161: sgrassatura | F161: impastatura | G161: insaccatura | H161: asciugatura | I161: precottura | J161: cottura | K161: raffreddamento | L161: celle di raffreddamento
B162: Lardo e Grassi | C162: selezione | D162: sgrassatura | E162: aromatizzazione | F162: massaggiatura | G162: raffreddamento | H162: stagionatura
B163: Speck | C163: selezione | D163: salatura | E163: aromatizzazione | F163: asciugatura | G163: affumicatura | H163: stagionatura
B164: Prosciutto cotto | C164: selezione | D164: taglio | E164: disosso | F164: aromatizzazione | G164: cottura | H164: raffredamento
B165: Carne salada | C165: selezione | D165: aromatizzazione | E165: massaggiatura | F165: salatura
B167: http://www.giuseppezeppa.com/files/salumi-giu-17.pdf
B170: PRODUCTION PROCESS ANALYSIS
C173: SELEZIONE CARNI | F173: TAGLIO e RIDIMENSIONAMENTO o RIFILATURA CARNI | J173: SGRASSATURA | M173: IMPASTATURA & INSACCATURA
...

Sheet C. bilanci
B1: BOME' S.P.A.
A3: 38085 Pieve di Bono-Prezzo | V3: Codice fiscale | AG3: 00369120225
V4: Numero CCIAA | AG4: TN0090691
A5: Società privata
A7: This company is Independent (but not the Global Ultimate Owner of a Corporate Group)
A10: Anagrafica
A13: Indirizzo sede legale
A14: BEN, 3/G | V14: Numero di telefono | AG14: 0465674226
A15: 38085 Pieve Di Bono-Prezzo | V15: Sito web | AG15: =HYPERLINK("http://www.bome.it/","www.bome.it") -> www.bome.it
A16: TRENTO(TRENTINO-ALTO ADIGE/SÜDTIROL)
A18: Indirizzo sede operativa
A19: VIALE AL BEN 3/G | V19: Numero di telefono | AG19: 0465674226
A20: 38085 Pieve Di Bono-Prezzo
A21: TRENTO(TRENTINO-ALTO ADIGE)
A24: Informazioni commerciali e legali
A27: Ragione sociale precedente
A28: 05/2025 | O28: BOME' S.R.L.
A29: La data di variazione del nome è la data di acquisizione dell’informazione da parte di BvD
A31: Stato giuridico | O31: Attiva | V31: Data di chiusura ultimo bilancio | AG31: 31/12/2024
A32: Forma giuridica | O32: S.P.A.
V33: Numero di anni disponibili | AG33: 8
A34: Data di costituzione | O34: 28482
V35: Bilanci disponibili | AG35: Bilancio non consolidato
V37: Ultimo modello di contabilità - Bilancio | AG37: Dettagliato
A40: Informazioni su dimensione e gruppo
A43: Ricavi del vendite (2024) | O43: 21.463.379 EUR | V43: Indicatore d'Indipendenza BvD | AG43: B+
A44: Utile netto (2024) | O44: 899.733 EUR
V45: N° azionisti registrati | AG45: 4
A46: Totale Attività (2024) | O46: 18.790.859 EUR
V47: N° partecipate registrate | AG47: 1
A48: Dipendenti (2024) | O48: 30
A50: Capitale sociale (2024) | O50: 140 migl EUR
A52: Principale Borsa | O52: Non quotata
A55: Classificazione mercelogica
A58: Descrizione attività italiano | O58: PRODUZIONE DI PRODOTTI A BASE DI CARNE (INCLUSA LA CARNE DI VOLATI )
A60: Descrizione attività inglese | O60: Production of meat and poultry meat products
A62: Ateco 2007 | O62: 101300 Produzione di prodotti a base di carne (inclusa la carne di volatili)
A64: SAE code | O64: 430 Imprese produttive
A66: RAE code | O66: 412 Carni fresche e conservate e altri prodotti della macellazione
A69: Gruppo dei pari
A72: Nome | O72: 101 VL (Aziende Molto Grandi)
A73: Descrizione | O73: Lavorazione e conservazione di carne e produzione di prodotti a base di carne
A74: Dimensione | O74: 388 società
A77: Profilo finanziario e dipendenti
A79: Bilancio non consolidato | T79: 31/12/2024 | Y79: 31/12/2023 | AE79: 31/12/2022 | AL79: 31/12/2021 | AV79: 31/12/2020 | BD79: 31/12/2019 | BH79: 31/12/2018 | BL79: 31/12/2017
T80: EUR | Y80: EUR | AE80: EUR | AL80: EUR | AV80: EUR | BD80: EUR | BH80: EUR | BL80: EUR
U81: 12 mesi | Z81: 12 mesi | AF81: 12 mesi | AM81: 12 mesi | AX81: 12 mesi | BE81: 12 mesi | BI81: 12 mesi | BM81: 12 mesi
U82: Dettagliato | Z82: Dettagliato | AF82: Dettagliato | AM82: Dettagliato | AX82: Dettagliato | BE82: Dettagliato | BI82: Dettagliato | BM82: Dettagliato
U83: ICS | Z83: ICS | AF83: ICS | AM83: ICS | AX83: ICS | BE83: ICS | BI83: ICS | BM83: ICS
A86: Ricavi delle vendite | S86: 21463379 | X86: 20988520 | AD86: 17588847 | AJ86: 15559839 | AU86: 14316092 | BC86: 13473198 | BG86: 11493812 | BK86: 9891413
A87: EBITDA | S87: 2527307 | X87: 2036923 | AD87: 1835077 | AJ87: 1897638 | AU87: 1536949 | BC87: 1263505 | BG87: 1249873 | BK87: 818309
A88: Utile Netto | S88: 899733 | X88: 566667 | AD88: 678581 | AJ88: 961303 | AU88: 921282 | BC88: 751636 | BG88: 670425 | BK88: 364746
A89: Totale Attività | S89: 18790859 | X89: 20554377 | AD89: 20723060 | AJ89: 18204611 | AU89: 14795011 | BC89: 9311398 | BG89: 6455031 | BK89: 6151737
A90: Patrimonio Netto | S90: 5757287 | X90: 5227552 | AD90: 4660887 | AJ90: 4082303 | AU90: 3206001 | BC90: 2384718 | BG90: 1733081 | BK90: 1062658
A91: Posizione finanziaria netta | S91: 8263503 | X91: 9788289 | AD91: 10079836 | AJ91: 8598021 | AU91: 7239662 | BC91: 3375102 | BG91: 2296704 | BK91: 2193786
A93: EBITDA/Vendite (%) | S93: 11.62 | X93: 9.51 | AD93: 10.19 | AJ93: 12.12 | AU93: 10.69 | BC93: 9.29 | BG93: 10.83 | BK93: 8.25
A94: Redditività delle vendite (ROS) (%) | S94: 7.31 | X94: 5.22 | AD94: 5.35 | AJ94: 9.01 | AU94: 9.41 | BC94: 7.86 | BG94: 9.12 | BK94: 6.41
A95: Redditività del totale attivo (ROA) (%) | S95: 8.46 | X95: 5.44 | AD95: 4.65 | AJ95: 7.75 | AU95: 9.14 | BC95: 11.49 | BG95: 16.31 | BK95: 10.34
A96: Redditività del capitale proprio (ROE) (%) | S96: 15.63 | X96: 10.84 | AD96: 14.56 | AJ96: 23.55 | AU96: 28.74 | BC96: 31.52 | BG96: 38.68 | BK96: 34.32
A97: Debt/Equity ratio | S97: 1.48 | X97: 2.04 | AD97: 2.41 | AJ97: 2.66 | AU97: 2.88 | BC97: 1.67 | BG97: 1.52 | BK97: 2.74
A98: Debiti v/banche su fatt. (%) | S98: 39.11 | X98: 49.88 | AD98: 62.25 | AJ98: 69.17 | AU98: 64.21 | BC98: 29.25 | BG98: 22.82 | BK98: 29.3
... A102: Dipendenti | S102: 30 | X102: 32 | AD102: 31 | AJ102: 27 | AU102: 24 | BC102: 25 | BG102: 25 | BK102: 27
A105: Stato patrimoniale
A107: Bilancio non consolidato | T107: 31/12/2024 | Y107: 31/12/2023 | AE107: 31/12/2022 | AL107: 31/12/2021 | AV107: 31/12/2020 | BD107: 31/12/2019 | BH107: 31/12/2018 | BL107: 31/12/2017
T108: EUR | Y108: EUR | AE108: EUR | AL108: EUR | AV108: EUR | BD108: EUR | BH108: EUR | BL108: EUR
U109: 12 mesi | Z109: 12 mesi | AF109: 12 mesi | AM109: 12 mesi | AX109: 12 mesi | BE109: 12 mesi | BI109: 12 mesi | BM109: 12 mesi
U110: Dettagliato | Z110: Dettagliato | AF110: Dettagliato | AM110: Dettagliato | AX110: Dettagliato | BE110: Dettagliato | BI110: Dettagliato | BM110: Dettagliato
U111: ICS | Z111: ICS | AF111: ICS | AM111: ICS | AX111: ICS | BE111: ICS | BI111: ICS | BM111: ICS
A113: Attivo
A114: A. CREDITI VERSO SOCI | S114: 0 | X114: 0 | AD114: 0 | AJ114: 0 | AU114: 0 | BC114: 0 | BG114: 0 | BK114: 0
A115: Quota di capitale richiamata | S115: 0 | X115: 0 | AD115: 0 | AJ115: 0 | AU115: 0 | BC115: 0 | BG115: 0 | BK115: 0
A117: B. TOTALE IMMOBILIZZAZIONI sep.ind. Di quelle conc. In loc. Finanz. | S117: 8842950 | X117: 9182852 | AD117: 9614947 | AJ117: 9565702 | AU117: 7073181 | BC117: 2616289 | BG117: 1201123 | BK117: 908499 | BP117: amto tot | BQ117: =S331+S332 -> 916802 | BR117: =X332+X331 -> 899828 | BS117: =AD331+AD332 -> 856051
A118: B.I. TOTALE IMMOB. IMMATERIALI | S118: 89523 | X118: 106380 | AD118: 139717 | AJ118: 76490 | AU118: 33453 | BC118: 7543 | BG118: 0 | BK118: 1977 | BP118: imm tot | BQ118: =S117-X117 -> -339902 | BR118: =X117-AD117 -> -432095 | BS118: =AD117-AJ117 -> 49245
A119: B.I.1. Costi impianto e ampl. | S119: 0 | X119: 0 | AD119: 0 | AJ119: 0 | AU119: 0 | BC119: 0 | BG119: 0 | BK119: 0
A120: B.I.2. Costi ricerca e pubb. | S120: 0 | X120: 0 | AD120: 0 | AJ120: 0 | AU120: 0 | BC120: 0 | BG120: 0 | BK120: 0
A121: B.I.3. Diritti brevetto ind. | S121: 64590 | X121: 97381 | AD121: 130172 | AJ121: 3968 | AU121: 4960 | BC121: 0 | BG121: 0 | BK121: 0
A122: B.I.4. Concessioni, licenze | S122: 8453 | X122: 8999 | AD122: 9545 | AJ122: 0 | AU122: 0 | BC122: 0 | BG122: 0 | BK122: 0
A123: B.I.5. Avviamento/Differenza di consolidamento | S123: 0 | X123: 0 | AD123: 0 | AJ123: 0 | AU123: 0 | BC123: 0 | BG123: 0 | BK123: 0
A124: di cui: Avviamento | S124: 0 | X124: 0 | AD124: 0 | AJ124: 0 | AU124: 0 | BC124: 0 | BG124: 0 | BK124: 0
A125: B.I.6. Imm. in corso | S125: 0 | X125: 0 | AD125: 0 | AJ125: 67622 | AU125: 28493 | BC125: 7543 | BG125: 0 | BK125: 0
A126: B.I.7. Altre immobiliz. Immateriali | S126: 16480 | X126: 0 | AD126: 0 | AJ126: 4900 | AU126: 0 | BC126: 0 | BG126: 0 | BK126: 1977
A127: Fondo amm.to Immob. Immateriali | S127: n.d. | X127: n.d. | AD127: n.d. | AJ127: n.d. | AU127: n.d. | BC127: n.d. | BG127: n.d. | BK127: n.d.
A129: B.II. TOTALE IMMOB. MATERIALI | S129: 8694725 | X129: 9017770 | AD129: 9416528 | AJ129: 9430510 | AU129: 7025024 | BC129: 2594042 | BG129: 1186419 | BK129: 891818
A130: di cui: Beni materiali concessi in locazione finanziaria | S130: n.d. | X130: n.d. | AD130: n.d. | AJ130: n.d. | AU130: n.d. | BC130: n.d. | BG130: n.d. | BK130: n.d.
A131: B.II.1. Terreni e fabbricati | S131: 6069102 | X131: 6328571 | AD131: 6543383 | AJ131: 6374984 | AU131: 396319 | BC131: 412628 | BG131: 418736 | BK131: 324645
A132: B.II.2. Impianti | S132: 1774810 | X132: 2137598 | AD132: 2352511 | AJ132: 2232169 | AU132: 1801043 | BC132: 258024 | BG132: 302043 | BK132: 336024
A133: B.II.3. Attrez. industriali | S133: 197170 | X133: 187192 | AD133: 184756 | AJ133: 168289 | AU133: 141111 | BC133: 110856 | BG133: 130147 | BK133: 133231
A134: B.II.4. Altri beni | S134: 177873 | X134: 244518 | AD134: 312178 | AJ134: 236539 | AU134: 116965 | BC134: 45295 | BG134: 68843 | BK134: 97918
A135: B.II.5. Imm. in corso/acconti | S135: 475770 | X135: 119891 | AD135: 23700 | AJ135: 418529 | AU135: 4569586 | BC135: 1767239 | BG135: 266650 | BK135: 0
A136: Fondo amm.to Immob. Materiali | S136: n.d. | X136: n.d. | AD136: n.d. | AJ136: n.d. | AU136: n.d. | BC136: n.d. | BG136: n.d. | BK136: n.d.
A138: B.III. TOTALE IMMOB. FINANZIARIE | S138: 58702 | X138: 58702 | AD138: 58702 | AJ138: 58702 | AU138: 14704 | BC138: 14704 | BG138: 14704 | BK138: 14704
A139: di cui: esigibili entro l'esercizio successivo | S139: 0 | X139: 0 | AD139: 0 | AJ139: 0 | AU139: 8192 | BC139: 8192 | BG139: 8192 | BK139: 0
A140: B.III.1. TOT Partecipazioni | S140: 58702 | X140: 58702 | AD140: 58702 | AJ140: 58702 | AU140: 6512 | BC140: 6512 | BG140: 6512 | BK140: 6512
A141: B.III.1.a. Imprese controllate | S141: 0 | X141: 0 | AD141: 0 | AJ141: 0 | AU141: 0 | BC141: 0 | BG141: 0 | BK141: 0
A142: B.III.1.b. Imprese collegate | S142: 0 | X142: 0 | AD142: 0 | AJ142: 0 | AU142: 0 | BC142: 0 | BG142: 0 | BK142: 0
A143: B.III.1.c. Imprese controllanti | S143: 0 | X143: 0 | AD143: 0 | AJ143: 0 | AU143: 0 | BC143: 0 | BG143: 0 | BK143: 0
A144: B.III.1.d. In imprese sottoposte al controllo delle controllanti | S144: 0 | X144: 0 | AD144: 0 | AJ144: 0 | AU144: 0 | BC144: 0 | BG144: 0 | BK144: 0
A145: B.III.1.d.bis. Altre imprese | S145: 58702 | X145: 58702 | AD145: 58702 | AJ145: 58702 | AU145: 6512 | BC145: 6512 | BG145: 6512 | BK145: 6512
A146: B.III.2. TOT CREDITI Imm. Fin. | S146: 0 | X146: 0 | AD146: 0 | AJ146: 0 | AU146: 8192 | BC146: 8192 | BG146: 8192 | BK146: 8192
A147: B.III.2.a. Cred. vs Controllate entro | S147: 0 | X147: 0 | AD147: 0 | AJ147: 0 | AU147: 0 | BC147: 0 | BG147: 0 | BK147: 0
...

Sheet D. Benchmark di settore
B2: BENCHMARK DI SETTORE
B5: Ragione sociale | C5: Ricavi | D5: Costo del venduto | E5: Costo dei servizi | F5: Costo del lavoro | G5: accantonamento risci | H5: Crediti v clienti | I5: Altri crediti | J5: rimanenze | K5: Debiti vs fornitori | L5: proventi finanziari | M5: Ratei risconti attivi | N5: ratei risconti passivi | O5: Tempo medio di incasso crediti | P5: Costo del venduto/Ricavi [%] | Q5: Costo dei servizi/Ricavi [%] | R5: Costo del lavoro/Ricavi [%] | S5: Accantonamento rischi/Ricavi [%] | T5: debito a bt | U5: debito lt | V5: Rapporto Debiti a BT/Tot | W5: Oneri finanziari | X5: Costo medio dell'indebitamento M/L [%] | Y5: Costo medio dell'indebitamento BT | Z5: Proventi finanziari/Ricavi [%] | AA5: Crediti vs clienti/Ricavi [%] | AB5: Altri crediti/Ricavi [%] | AC5: Rimanenze/Costo del venduto [%] | AD5: Debiti vs fornitori/Costo del venduto [%] | AE5: Ratei e risconti attivi/Ricavi [%] | AF5: Ratei e risconti passivi/Ricavi [%] | AG5: ROS | AH5: ROI | AI5: ROE
B6: Segata SpA | C6: 57616884 | D6: 40746735 | E6: 9190580 | F6: 5396472 | G6: 136494 | H6: 8659767 | I6: =9795621-H6 -> 1135854 | J6: 7492124 | K6: 6387006 | L6: 34992 | M6: 58447 | N6: 832426 | O6: =(AA6*C6)/(C6*1.22/365) -> 44.96654 | P6: =D6/C6 -> 0.7072013 | Q6: =E6/C6 -> 0.15951192 | R6: =F6/C6 -> 0.093661296 | S6: =G6/C6 -> 0.0023689931 | T6: 13713494 | U6: 1400853 | V6: =T6/(T6+U6) -> 0.90731634 | W6: 434113 | X6: =(W6*(1-V6))/(U6+T6) -> 0.0026620523 | Y6: =(W6*V6)/(T6) -> 0.028721916 | Z6: =L6/C6 -> 0.00060732198 | AA6: =H6/C6 -> 0.15029912 | AB6: =I6/C6 -> 0.019713909 | AC6: =J6/D6 -> 0.18387054 | AD6: =K6/D6 -> 0.1567489 | AE6: =J6/C6 -> 0.13003348 | AF6: =N6/C6 -> 0.014447605 | AG6: 0.0304 | AH6: 0.0898 | AI6: 0.081
B7: G. Pfitscher | C7: 32585062 | D7: 22885536 | O7: =(AA7*C7)/(C7*1.22/365) -> 46.57358 | P7: =D7/C7 -> 0.70233213 | Q7: =4713095/C7 -> 0.14463974 | R7: =2681925/C7 -> 0.082305352 | S7: 0 | T7: 16672665 | U7: 20902923 | V7: =T7/(T7+U7) -> 0.44371002 | W7: 1737633 | X7: =(W7*(1-V7))/(U7+T7) -> 0.025724889 | Y7: =(W7*V7)/(T7) -> 0.046243668 | Z7: =(153+5374)/C7 -> 0.0001696176 | AA7: =5072536/C7 -> 0.1556706 | AB7: =(12595990-5072536)/C7 -> 0.23088659 | AC7: =9013430/D7 -> 0.39384832 | AD7: =7743380/D7 -> 0.33835257 | AE7: =332754/C7 -> 0.010211857 | AF7: =17462210/C7 -> 0.53589617 | AG7: 0.0689 | AH7: 0.0658 | AI7: 0.0519
B8: Merano Speck | C8: 32440820 | D8: 24111988 | E8: 4318196 | F8: 3984151 | G8: 0 | H8: 4136369 | I8: =9161304-H8 -> 5024935 | J8: 17800000 | K8: 7957316 | L8: 3298 | M8: 179493 | N8: 163736 | O8: =(AA8*C8)/(C8*1.22/365) -> 38.147008 | P8: =D8/C8 -> 0.74326074 | Q8: =D9/C9 -> 0.82715606 | R8: =F8/C8 -> 0.12281289 | S8: 0 | T8: 14338592 | U8: 5242259 | V8: =T8/(T8+U8) -> 0.73227624 | W8: 396335 | X8: =(W8*(1-V8))/(U8+T8) -> 0.0054189828 | Y8: =(W8*V8)/(T8) -> 0.020240949 | Z8: =L8/C8 -> 0.00010166204 | AA8: =H8/C8 -> 0.12750507 | AB8: =I8/C8 -> 0.15489544 | AC8: =J8/C8 -> 0.54869143 | AD8: =K8/D8 -> 0.33001493 | AE8: =M8/C8 -> 0.0055329366 | AF8: =N8/C8 -> 0.0050472214 | AG8: 0.0103 | AH8: 0.0184 | AI8: 0.0023
B9: Ala carni | C9: 19516027 | D9: =P9*C9 -> 16142800 | O9: =(AA9*C9)/(C9*1.22/365) -> 31.172107 | P9: =16142800/19516027 -> 0.82715606 | Q9: =1670812/19516027 -> 0.085612302 | R9: =934172/19516027 -> 0.047866915 | S9: =110000/19516027 -> 0.0056363931 | T9: 5259426 | U9: 1383136 | V9: =T9/(T9+U9) -> 0.79177673 | W9: 136127 | X9: =(W9*(1-V9))/(U9+T9) -> 0.0042671502 | Y9: =(W9*V9)/(T9) -> 0.020493147 | Z9: =24663/19516027 -> 0.0012637306 | AA9: =2033408/C9 -> 0.1041917 | AB9: =(2353999-2033408)/C9 -> 0.016427063 | AC9: =733759/D9 -> 0.045454258 | AD9: =2093228/D9 -> 0.12966945 | AE9: =21415/C9 -> 0.0010973033 | AF9: =443529/C9 -> 0.022726398 | AG9: -0.0127 | AH9: -0.0463 | AI9: -0.0794
B10: Tirolinger | C10: 19062158 | D10: 18128912 | E10: 1383987 | F10: 2500 | G10: 0 | H10: 2709211 | I10: =3534191-H10 -> 824980 | J10: 0 | K10: 938037 | L10: 22408 | M10: 126 | N10: 796 | O10: =(AA10*C10)/(C10*1.22/365) -> 42.521032 | P10: =D10/C10 -> 0.95104195 | Q10: =D10/C10 -> 0.95104195 | R10: =F10/C10 -> 0.00013114989 | S10: =G10/C10 -> 0 | T10: 2904083 | U10: 109899 | V10: =T10/(T10+U10) -> 0.96353694 | W10: 9023 | X10: =(W10*(1-V10))/(U10+T10) -> 0.00010915997 | Y10: =(W10*V10)/(T10) -> 0.002993714 | Z10: =L10/C10 -> 0.0011755227 | AA10: =H10/C10 -> 0.14212509 | AB10: =I10/C10 -> 0.043278416 | AC10: =J9/C9 -> 0 | AD10: =K10/D10 -> 0.051742598 | AE10: =M10/C10 -> 6.6099547e-06 | AF10: =N10/C10 -> 4.1758126e-05 | AG10: 0.0058 | AH10: 0.025 | AI10: 0.0156
B11: Salumificio Val Rendena | C11: 15607657 | D11: 11242690 | E11: 2610510 | F11: 1290406 | G11: 0 | H11: 1886858 | I11: =2406141-H11 -> 519283 | J11: 4030465 | K11: 3411923 | L11: 30062 | M11: 74713 | N11: 528860 | O11: =(AA11*C11)/(C11*1.22/365) -> 36.168837 | P11: =D11/C11 -> 0.72033169 | Q11: =D11/C11 -> 0.72033169 | R11: =F11/C11 -> 0.082677752 | S11: =G11/C11 -> 0 | T11: 5693509 | U11: 2141485 | V11: =T11/(T11+U11) -> 0.72667688 | W11: 153139 | X11: =(W11*(1-V11))/(U11+T11) -> 0.0053422414 | Y11: =(W11*V11)/(T11) -> 0.019545516 | Z11: =L11/C11 -> 0.0019261059 | AA11: =H11/C11 -> 0.1208931 | AB11: =I11/C11 -> 0.033271041 | AC11: =J11/D11 -> 0.3584965 | AD11: =K11/D11 -> 0.30347924 | AE11: =M11/C11 -> 0.0047869453 | AF11: =N11/C11 -> 0.03388465 | AG11: 0.0182 | AH11: 0.0333 | AI11: 0.026
B12: Trockner Sebastian | C12: 10748162 | D12: 8042729 | E12: 1042479 | F12: 1065444 | G12: 0 | H12: 1351939 | I12: =1359755-H12 -> 7816 | J12: 1163582 | K12: =962516+38909 -> 1001425 | L12: 1525 | M12: 46451 | N12: 37712 | O12: =(AA12*C12)/(C12*1.22/365) -> 37.631881 | P12: =D12/C12 -> 0.74828878 | Q12: =D12/C12 -> 0.74828878 | R12: =F12/C12 -> 0.099128018 | S12: =G12/C12 -> 0 | T12: 1982965 | U12: 801814 | V12: =T12/(T12+U12) -> 0.71207266 | W12: 110269 | X12: =(W12*(1-V12))/(U12+T12) -> 0.01140107 | Y12: =(W12*V12)/(T12) -> 0.039597038 | Z12: =L12/C12 -> 0.00014188472 | AA12: =H12/C12 -> 0.12578327 | AB12: =I12/C12 -> 0.0007271941 | AC12: =J12/D12 -> 0.14467502 | AD12: =K12/D12 -> 0.12451309 | AE12: =M12/C12 -> 0.0043217622 | AF12: =N12/C12 -> 0.0035086929 | AG12: 0.0194 | AH12: 0.0425 | AI12: 0.0142
B13: Salumificio Trentino | C13: 10390781 | D13: 6575130 | E13: 1487344 | F13: 1159640 | G13: 0 | H13: 1185050 | I13: =1637695-H13 -> 452645 | J13: 640373 | K13: 766889 | L13: 72321 | M13: 21209 | N13: 241888 | O13: =(AA13*C13)/(C13*1.22/365) -> 34.120982 | P13: =D13/C13 -> 0.63278497 | Q13: =D13/C13 -> 0.63278497 | R13: =F13/C13 -> 0.11160278 | S13: =G13/C13 -> 0 | T13: 1541499 | U13: 61295 | V13: =T13/(T13+U13) -> 0.96175741 | W13: 8344 | X13: =(W13*(1-V13))/(U13+T13) -> 0.00019908747 | Y13: =(W13*V13)/(T13) -> 0.0052059092 | Z13: =L13/C13 -> 0.006960112 | AA13: =H13/C13 -> 0.11404821 | AB13: =I13/C13 -> 0.043562173 | AC13: =J13/D13 -> 0.097393207 | AD13: =K13/D13 -> 0.1166348 | AE13: =M13/C13 -> 0.0020411363 | AF13: =N13/C13 -> 0.023279097 | AG13: 0.0941 | AH13: 0.1727 | AI13: 0.0971
B14: Salumi Simonini | C14: 9337427 | D14: 6451185 | E14: 915711 | F14: 1280628 | G14: 0 | H14: 1624118 | I14: =1813449-H14 -> 189331 | J14: 419563 | K14: 1148054 | L14: 57 | M14: 209 | N14: 218429 | O14: =(AA14*C14)/(C14*1.22/365) -> 52.038335 | P14: =D14/C14 -> 0.69089536 | Q14: =D14/C14 -> 0.69089536 | R14: =F14/C14 -> 0.13714999 | S14: =G14/C14 -> 0 | T14: 1397702 | U14: 0 | V14: =T14/(T14+U14) -> 1 | W14: 1 | Y14: =(W14*V14)/(T14) -> 7.1546009e-07 | Z14: =L14/C14 -> 6.1044654e-06 | AA14: =H14/C14 -> 0.17393635 | AB14: =I14/C14 -> 0.020276571 | AC14: =J14/D14 -> 0.065036579 | AD14: =K14/D14 -> 0.17796017 | AE14: =M14/C14 -> 2.238304e-05 | AF14: =N14/C14 -> 0.023392847 | AG14: 0.0397 | AH14: 0.0997 | AI14: 0.0548
B15: Benchmark settore | O15: =AVERAGE(O6:O14) -> 40.371145 | P15: =AVERAGE(P6:P14) -> 0.74703255 | Q15: =AVERAGE(Q6:Q14) -> 0.55114031 | R15: =AVERAGE(R6:R14) -> 0.086370682 | S15: =AVERAGE(S6:S14) -> 0.00088948735 | T15: =AVERAGE(T6:T14) -> 7055992.8 | U15: =AVERAGE(U6:U14) -> 3560407.1 | V15: =AVERAGE(V6:V14) -> 0.80434702 | ... AI15: =AVERAGE(AI6:AI14) -> 0.029277778
AF18: Proiezioni di cresita: | AG18: 0.0447 | AH18: linear regression | AI18: https://www.mordorintelligence.it/industry-reports/global-cold-cuts-market
AG19: ROS | AH19: ROI | AI19: ROE
AF20: 2025 | AG20: =AG15*(1+$AG$18) -> 0.031816919 | AH20: =AH15*(1+$AG$18) -> 0.058143359 | AI20: =AI15*(1+$AG$18) -> 0.030586494
AF21: 2026 | AG21: =AG20*(1+$AG$18) -> 0.033239135 | AH21: =AH20*(1+$AG$18) -> 0.060742367 | AI21: =AI20*(1+$AG$18) -> 0.031953711
AF22: 2027 | AG22: =AG21*(1+$AG$18) -> 0.034724925 | AH22: =AH21*(1+$AG$18) -> 0.063457551 | AI22: =AI21*(1+$AG$18) -> 0.033382042

Sheet D. situazione competitiva
B2: DATI STORICI | C2: analisi precedenti
B4: Ragione | C4: sociale | D4: 2021 | E4: 2022 | F4: 2023 | G4: 2024
B5: Bomè | C5: S.p.A. | D5: 0.0902 | E5: 0.0541 | F5: 0.0528 | G5: 0.0734
B6: Ala | C6: Carni | D6: -0.0187 | E6: -0.0039 | F6: 0.0302 | G6: -0.0127
B7: G. | C7: Pfitscher | D7: -0.0122 | E7: 0.0566 | F7: 0.0695 | G7: 0.0689
B8: Merano | C8: Speck | D8: 0.0118 | E8: -0.0041 | F8: 0 | G8: 0.0103
B9: Salumi | C9: Simonini | D9: n.d. | E9: 0.0763 | F9: 0.0844 | G9: 0.0397
B10: Salumificio | C10: Trentino | D10: 0.1289 | E10: 0.0614 | F10: 0.1275 | G10: 0.0941
B11: Salumificio | C11: Val Rendena | D11: -0.0176 | E11: 0.0115 | F11: 0.0132 | G11: 0.0182
B12: Segata | C12: S.p.A. | D12: -0.0017 | E12: 0.0336 | F12: 0.0312 | G12: 0.0304
B13: Tirolinger | D13: 0.0204 | E13: 0.0117 | F13: 0.0071 | G13: 0.0058
B14: Trockner | C14: Sebastian | D14: 0.0197 | E14: 0.0242 | F14: 0.015 | G14: 0.0194
B17: Ragione | C17: sociale | D17: 2021 | E17: 2022 | F17: 2023 | G17: 2024
B18: Bomè | C18: S.p.A. | D18: 0.1224 | E18: 0.0706 | F18: 0.0754 | G18: 0.1099
B19: Ala | C19: Carni | D19: -0.0762 | E19: -0.0168 | F19: 0.1112 | G19: -0.0463
B20: G. | C20: Pfitscher | D20: -0.0114 | E20: 0.0339 | F20: 0.0547 | G20: 0.0658
B21: Merano | C21: Speck | D21: 0.0259 | E21: -0.0066 | F21: 0 | G21: 0.0184
B22: Salumi | C22: Simonini | D22: n.d. | E22: 0.3223 | F22: 0.2413 | G22: 0.0997
B23: Salumificio | C23: Trentino | D23: 0.1995 | E23: 0.1015 | F23: 0.233 | G23: 0.1727
B24: Salumificio | C24: Val Rendena | D24: -0.0263 | E24: 0.0192 | F24: 0.0216 | G24: 0.0333
B25: Segata | C25: S.p.A. | D25: -0.0038 | E25: 0.0883 | F25: 0.0867 | G25: 0.0898
B26: Tirolinger | D26: 0.08 | E26: 0.049 | F26: 0.0322 | G26: 0.025
B27: Trockner | C27: Sebastian | D27: 0.0338 | E27: 0.0511 | F27: 0.0316 | G27: 0.0425
B30: Ragione | C30: sociale | D30: 2021 | E30: 2022 | F30: 2023 | G30: 2024
B31: Bomè | C31: S.p.A. | D31: 0.2638 | E31: 0.1552 | F31: 0.1146 | G31: 0.1638
B32: Ala | C32: Carni | D32: -0.1268 | E32: -0.0287 | F32: 0.0835 | G32: -0.0794
B33: G. | C33: Pfitscher | D33: -0.0506 | E33: 0.043 | F33: 0.0542 | G33: 0.0519
B34: Merano | C34: Speck | D34: 0.0549 | E34: 0.0296 | F34: 0.0006 | G34: 0.0023
B35: Salumi | C35: Simonini | D35: n.d. | E35: 0.1496 | F35: 0.1322 | G35: 0.0548
B36: Salumificio | C36: Trentino | D36: 0.113 | E36: 0.0619 | F36: 0.137 | G36: 0.0971
B37: Salumificio | C37: Val Rendena | D37: -0.05 | E37: 0.0233 | F37: 0.0103 | G37: 0.026
B38: Segata | C38: S.p.A. | D38: -0.017 | E38: 0.1264 | F38: 0.091 | G38: 0.081
B39: Tirolinger | D39: 0.0378 | E39: 0.0173 | F39: 0.0082 | G39: 0.0156
B40: Trockner | C40: Sebastian | D40: 0.029 | E40: 0.0424 | F40: 0.0071 | G40: 0.0142
B44: Ragione | C44: sociale | D44: Provincia | E44: Fatturato 2024
B45: Segata | C45: S.p.A. | D45: Trento | E45: 57620000
B46: G. | C46: Pfitscher | D46: Bolzano | E46: 32590000
B47: Merano | C47: speck | D47: Bolzano | E47: 32440000
B48: Bomé | C48: S.p.A. | D48: Trento | E48: 21460000
B49: Ala | C49: Carni | D49: Trento | E49: 19520000
B50: Tirolinger | D50: Bolzano | E50: 19060000
B51: Salumifico | C51: Val Rendena | D51: Trento | E51: 15610000
B52: Trockner | C52: Sebastian | D52: Bolzano | E52: 10750000
B53: Salumificio | C53: trentino | D53: Trento | E53: 10390000
B54: Salumi | C54: Simonini | D54: Trento | E54: 9340000
